Workbook

Sheet ДУ
A1: Сентрас Секьюритиз | B1: 45866
A2: 1) Активы
A4: ЦБ
A5: Наименование эмитента и вид ЦБ | B5: ISIN | C5: Количество ЦБ | D5: Номинальная стоимость. тенге | E5: Ставка | F5: Дата зачисления/приобретения | G5: Дата погашения | H5: Чистая покупная стоимоcть | I5: Расчетная цена на 28.07.25 | J5: Расчетная грязная цена на 28.07.25 | K5: Накопленный купон | L5: Суммарно-текущая рыночная стоимость | M5: Вес
A6: Министерство Финансов Республики Казахстан купонные МЕУКАМ | B6: KZKD00000535 | C6: =3250000-500000-500000-500000 -> 1750000 | D6: =3250000000-500000000-500000000-500000000 -> 1750000000 | E6: 5.49 | F6: 45491 | G6: 27.03.2027 | H6: =2755458875/3250000000*D6 -> 1483708625 | I6: =VLOOKUP(B6,'KASE за 28.07.25'!$C$5:$F$162,4,0) -> 84.3526 | J6: =VLOOKUP(B6,'KASE за 28.07.25'!$C$5:$G$162,5,0) -> 86.1979 | K6: 32291875 | L6: =D6*I6/100+K6 -> 1508462375 | M6: =L6/$L$59 -> 0.058750984 | N6: =D6*E6%/360 -> 266875 | O6: =K6+N6 -> 32558750
A7: Министерство Финансов Республики Казахстан купонные МЕУКАМ | B7: KZKD00001137 | C7: 1950000 | D7: 1950000000 | E7: 10.4 | F7: 45491 | G7: 12.04.2028 | H7: 1838876000 | I7: =VLOOKUP(B7,'KASE за 28.07.25'!$C$5:$F$162,4,0) -> 86.47 | J7: =VLOOKUP(B7,'KASE за 28.07.25'!$C$5:$G$162,5,0) -> 89.5322 | K7: 59713333 | L7: =D7*I7/100+K7 -> 1.7458783e+09 | M7: =L7/$L$59 -> 0.067997765 | N7: =D7*E7%/360 -> 563333.33 | O7: =K7+N7 -> 60276667
A8: Министерство Финансов Республики Казахстан МЕУКАМ | B8: KZKD00001087 | C8: =1950000-202300-182000-187350 -> 1378350 | D8: =C8*1000 -> 1378350000 | E8: 11 | F8: 45491 | G8: 31.03.2029 | H8: =1855844250/1950000000*D8 -> 1.3117964e+09 | I8: =VLOOKUP(B8,'KASE за 28.07.25'!$C$5:$F$162,4,0) -> 84.7569 | J8: =VLOOKUP(B8,'KASE за 28.07.25'!$C$5:$G$162,5,0) -> 88.3625 | K8: 49697175 | L8: =D8*I8/100+K8 -> 1.2179439e+09 | M8: =L8/$L$59 -> 0.047435988 | N8: =D8*E8%/360 -> 421162.5 | O8: =K8+N8 -> 50118338
A9: Министерство Финансов Республики Казахстан купонные МЕУКАМ | B9: KZKD00001160 | C9: =1950000-225000-225000-208000-225000-225000 -> 842000 | D9: =C9*1000 -> 842000000 | E9: 10.55 | F9: 45491 | G9: 28.07.2029 | H9: =1504310166.66923/1500000000*D9 -> 8.4441944e+08 | I9: =VLOOKUP(B9,'KASE за 28.07.25'!$C$5:$F$162,4,0) -> 82.8642 | J9: =VLOOKUP(B9,'KASE за 28.07.25'!$C$5:$G$162,5,0) -> 82.8642 | K9: =88830999.9999999-88830999.9999999 -> 0 | L9: =D9*I9/100+K9 -> 697716564 | M9: =L9/$L$59 -> 0.027174383 | N9: =D9*E9%/360 -> 246752.78 | O9: =K9+N9 -> 246752.78
A10: Министерство Финансов Республики Казахстан купонные МЕУКАМ | B10: KZKD00001129 | C10: 1450000 | D10: 1450000000 | E10: 10.3 | F10: 45491 | G10: 17.03.2031 | H10: 1.307499e+09 | I10: =VLOOKUP(B10,'KASE за 28.07.25'!$C$5:$F$162,4,0) -> 77.9074 | J10: =VLOOKUP(B10,'KASE за 28.07.25'!$C$5:$G$162,5,0) -> 81.6555 | K10: 54346806 | L10: =D10*I10/100+K10 -> 1.1840041e+09 | M10: =L10/$L$59 -> 0.046114114 | N10: =D10*E10%/360 -> 414861.11 | O10: =K10+N10 -> 54761667
A11: Министерство Финансов Республики Казахстан МЕУКАМ | B11: KZKD00000949 | C11: 1950000 | D11: 1950000000 | E11: 8.45 | F11: 45491 | G11: 16.04.2032 | H11: 1.5403351e+09 | I11: =VLOOKUP(B11,'KASE за 28.07.25'!$C$5:$F$162,4,0) -> 68.6015 | J11: =VLOOKUP(B11,'KASE за 28.07.25'!$C$5:$G$162,5,0) -> 70.9957 | K11: 46686250 | L11: =D11*I11/100+K11 -> 1384415500 | M11: =L11/$L$59 -> 0.053919656 | N11: =D11*E11%/360 -> 457708.33 | O11: =K11+N11 -> 47143958
A12: Министерство Финансов Республики Казахстан Купонные Облигации | B12: KZKD00001152 | C12: =1950000-250000-250000-250000-218000 -> 982000 | D12: =C12*1000 -> 982000000 | E12: 10.65 | F12: 45491 | G12: 26.07.2032 | H12: =1897171250/1950000000*D12 -> 9.5539598e+08 | I12: =VLOOKUP(B12,'KASE за 28.07.25'!$C$5:$F$162,4,0) -> 76.778 | J12: =VLOOKUP(B12,'KASE за 28.07.25'!$C$5:$G$162,5,0) -> 76.8372 | K12: 581016.67 | L12: =D12*I12/100+K12 -> 7.5454098e+08 | M12: =L12/$L$59 -> 0.029387557 | N12: =D12*E12%/360 -> 290508.33 | O12: =K12+N12 -> 871525
A13: Министерство Финансов Республики Казахстан Купонные Облигации | B13: KZKD00001152 | C13: 250000 | D13: =C13*1000 -> 250000000 | E13: 10.65 | F13: 45673 | G13: 26.07.2032 | H13: =227969916.67/250000000*D13 -> 2.2796992e+08 | I13: =VLOOKUP(B13,'KASE за 28.07.25'!$C$5:$F$162,4,0) -> 76.778 | J13: =VLOOKUP(B13,'KASE за 28.07.25'!$C$5:$G$162,5,0) -> 76.8372 | K13: 147916.67 | L13: =D13*I13/100+K13 -> 1.9209292e+08 | M13: =L13/$L$59 -> 0.0074815574 | N13: =D13*E13%/360 -> 73958.333 | O13: =K13+N13 -> 221875
A14: Министерство Финансов Республики Казахстан купонные МЕУКАМ | B14: KZKD00000741 | C14: 1950000 | D14: 1950000000 | E14: 8.07 | F14: 45491 | G14: 12.05.2034 | H14: 1425576750 | I14: =VLOOKUP(B14,'KASE за 28.07.25'!$C$5:$F$165,4,0) -> 62.5569 | J14: =VLOOKUP(B14,'KASE за 28.07.25'!$C$5:$G$165,5,0) -> 64.2606 | K14: 33221500 | L14: =D14*I14/100+K14 -> 1253081050 | M14: =L14/$L$59 -> 0.048804495 | N14: =D14*E14%/360 -> 437125 | O14: =K14+N14 -> 33658625
A15: Министерство Финансов Республики Казахстан купонные МЕУКАМ | B15: KZKD00000832 | C15: 1950000 | D15: 1950000000 | E15: 8.07 | F15: 45491 | G15: 29.01.2035 | H15: 1449433375 | I15: =VLOOKUP(B15,'KASE за 28.07.25'!$C$5:$F$165,4,0) -> 61.1824 | J15: =VLOOKUP(B15,'KASE за 28.07.25'!$C$5:$G$165,5,0) -> 65.195 | K15: 78245375 | L15: =D15*I15/100+K15 -> 1271302175 | M15: =L15/$L$59 -> 0.049514164 | N15: =D15*E15%/360 -> 437125 | O15: =K15+N15 -> 78682500
A16: Министерство Финансов Республики Казахстан купонные МЕУКАМ | B16: KZKD00000550 | C16: =312000-1 -> 311999 | D16: =C16*1000 -> 311999000 | E16: 5.5 | F16: 45509 | G16: 48328 | H16: 2.0448962e+08 | I16: =VLOOKUP(B16,'KASE за 28.07.25'!$C$5:$F$165,4,0) -> 57.1668 | J16: =VLOOKUP(B16,'KASE за 28.07.25'!$C$5:$G$165,5,0) -> 58.6029 | K16: 4480652.3 | L16: =D16*I16/100+K16 -> 1.828405e+08 | M16: =L16/$L$59 -> 0.0071211979 | N16: =D16*E16%/360 -> 47666.514 | O16: =K16+N16 -> 4528318.8
A17: Министерство Финансов Республики Казахстан купонные МЕУКАМ | B17: KZKD00000550 | C17: 500000 | D17: 500000000 | E17: 5.5 | F17: 45532 | G17: 48328 | H17: 3.2653072e+08 | I17: =VLOOKUP(B17,'KASE за 28.07.25'!$C$5:$F$165,4,0) -> 57.1668 | J17: =VLOOKUP(B17,'KASE за 28.07.25'!$C$5:$G$165,5,0) -> 58.6029 | K17: 7180555.6 | L17: =D17*I17/100+K17 -> 2.9301456e+08 | M17: =L17/$L$59 -> 0.011412213 | N17: =D17*E17%/360 -> 76388.889 | O17: =K17+N17 -> 7256944.4
A18: Министерство Финансов Республики Казахстан купонные МЕУКАМ | B18: KZKD00000550 | C18: 500000 | D18: 500000000 | E18: 5.5 | F18: 45566 | G18: 48328 | H18: 3.3409056e+08 | I18: =VLOOKUP(B18,'KASE за 28.07.25'!$C$5:$F$165,4,0) -> 57.1668 | J18: =VLOOKUP(B18,'KASE за 28.07.25'!$C$5:$G$165,5,0) -> 58.6029 | K18: 7180555.6 | L18: =D18*I18/100+K18 -> 2.9301456e+08 | M18: =L18/$L$59 -> 0.011412213 | N18: =D18*E18%/360 -> 76388.889 | O18: =K18+N18 -> 7256944.4
A19: Министерство Финансов Республики Казахстан купонные МЕУКАМ | B19: KZKD00000550 | C19: 300000 | D19: =C19*1000 -> 300000000 | E19: 5.5 | F19: 45649 | G19: 48328 | H19: 2.0566557e+08 | I19: =VLOOKUP(B19,'KASE за 28.07.25'!$C$5:$F$165,4,0) -> 57.1668 | J19: =VLOOKUP(B19,'KASE за 28.07.25'!$C$5:$G$165,5,0) -> 58.6029 | K19: 4308333.3 | L19: =D19*I19/100+K19 -> 1.7580873e+08 | M19: =L19/$L$59 -> 0.0068473276 | N19: =D19*E19%/360 -> 45833.333 | O19: =K19+N19 -> 4354166.7
A20: Министерство Финансов Республики Казахстан купонные МЕУКАМ | B20: KZKD00000550 | C20: 300000 | D20: =C20*1000 -> 300000000 | E20: 5.5 | F20: 45677 | G20: 48328 | H20: 2.0236587e+08 | I20: =VLOOKUP(B20,'KASE за 28.07.25'!$C$5:$F$165,4,0) -> 57.1668 | J20: =VLOOKUP(B20,'KASE за 28.07.25'!$C$5:$G$165,5,0) -> 58.6029 | K20: 4308333.3 | L20: =D20*I20/100+K20 -> 1.7580873e+08 | M20: =L20/$L$59 -> 0.0068473276 | N20: =D20*E20%/360 -> 45833.333 | O20: =K20+N20 -> 4354166.7
A21: Министерство Финансов Республики Казахстан купонные МЕУКАМ | B21: KZKD00001160 | C21: 500000 | D21: =C21*1000 -> 500000000 | E21: 10.55 | F21: 45512 | G21: 28.07.2029 | H21: 4.5194078e+08 | I21: =VLOOKUP(B21,'KASE за 28.07.25'!$C$5:$F$162,4,0) -> 82.8642 | J21: =VLOOKUP(B21,'KASE за 28.07.25'!$C$5:$G$162,5,0) -> 82.8642 | K21: =52749999.9999998-52749999.9999998 -> 0 | L21: =D21*I21/100+K21 -> 414321000 | M21: =L21/$L$59 -> 0.016136807 | N21: =D21*E21%/360 -> 146527.78 | O21: =K21+N21 -> 146527.78
A22: Министерство Финансов Республики Казахстан купонные МЕУКАМ | B22: KZKD00001160 | C22: 553430 | D22: =C22*1000 -> 553430000 | E22: 10.55 | F22: 45512 | G22: 28.07.2029 | H22: 4.9999941e+08 | I22: =VLOOKUP(B22,'KASE за 28.07.25'!$C$5:$F$162,4,0) -> 82.8642 | J22: =VLOOKUP(B22,'KASE за 28.07.25'!$C$5:$G$162,5,0) -> 82.8642 | K22: =58386865.0000005-58386865.0000005 -> 0 | L22: =D22*I22/100+K22 -> 4.5859534e+08 | M22: =L22/$L$59 -> 0.017861186 | N22: =D22*E22%/360 -> 162185.74 | O22: =K22+N22 -> 162185.74
A23: Министерство Финансов Республики Казахстан МЕУКАМ | B23: KZKD00000543 | C23: 636055 | D23: =C23*1000 -> 636055000 | E23: 5 | F23: 45519 | G23: 46861 | H23: 4.9999966e+08 | I23: =VLOOKUP(B23,'KASE за 28.07.25'!$C$5:$F$162,4,0) -> 75.4422 | J23: =VLOOKUP(B23,'KASE за 28.07.25'!$C$5:$G$162,5,0) -> 76.8311 | K23: 8834097.2 | L23: =D23*I23/100+K23 -> 4.8868798e+08 | M23: =L23/$L$59 -> 0.019033222 | N23: =D23*E23%/360 -> 88340.972 | O23: =K23+N23 -> 8922438.2
A24: Министерство Финансов Республики Казахстан купонные МЕУКАМ | B24: KZKD00000774 | C24: 715927 | D24: =C24*1000 -> 715927000 | E24: 8.35 | F24: 45526 | G24: 50976 | H24: 4.9999948e+08 | I24: =VLOOKUP(B24,'KASE за 28.07.25'!$C$5:$F$165,4,0) -> 57.223 | J24: =VLOOKUP(B24,'KASE за 28.07.25'!$C$5:$G$165,5,0) -> 57.2926 | K24: 498165.87 | L24: =D24*I24/100+K24 -> 4.1017307e+08 | M24: =L24/$L$59 -> 0.015975255 | N24: =D24*E24%/360 -> 166055.29 | O24: =K24+N24 -> 664221.16
A25: Министерство Финансов Республики Казахстан купонные МЕУКАМ | B25: KZKD00000774 | C25: 284073 | D25: =C25*1000 -> 284073000 | E25: 8.35 | F25: 45617 | G25: 50976 | H25: 2.0393645e+08 | I25: =VLOOKUP(B25,'KASE за 28.07.25'!$C$5:$F$165,4,0) -> 57.223 | J25: =VLOOKUP(B25,'KASE за 28.07.25'!$C$5:$G$165,5,0) -> 57.2926 | K25: 197667.46 | L25: =D25*I25/100+K25 -> 1.6275276e+08 | M25: =L25/$L$59 -> 0.0063388288 | N25: =D25*E25%/360 -> 65889.154 | O25: =K25+N25 -> 263556.62
A26: Министерство Финансов Республики Казахстан МЕУКАМ | B26: KZKD00000840 | C26: 500000 | D26: =C26*1000 -> 500000000 | E26: 7.68 | F26: 45526 | G26: 47518 | H26: 417099000 | I26: =VLOOKUP(B26,'KASE за 28.07.25'!$C$5:$F$162,4,0) -> 72.6814 | J26: =VLOOKUP(B26,'KASE за 28.07.25'!$C$5:$G$162,5,0) -> 76.3934 | K26: 18560000 | L26: =D26*I26/100+K26 -> 3.81967e+08 | M26: =L26/$L$59 -> 0.014876697 | N26: =D26*E26%/360 -> 106666.67 | O26: =K26+N26 -> 18666667
A27: Министерство Финансов Республики Казахстан МЕУКАМ | B27: KZKD00000840 | C27: 500000 | D27: =C27*1000 -> 500000000 | E27: 7.68 | F27: 45527 | G27: 47518 | H27: 4.1494417e+08 | I27: =VLOOKUP(B27,'KASE за 28.07.25'!$C$5:$F$162,4,0) -> 72.6814 | J27: =VLOOKUP(B27,'KASE за 28.07.25'!$C$5:$G$162,5,0) -> 76.3934 | K27: 18560000 | L27: =D27*I27/100+K27 -> 3.81967e+08 | M27: =L27/$L$59 -> 0.014876697 | N27: =D27*E27%/360 -> 106666.67 | O27: =K27+N27 -> 18666667
A28: Министерство Финансов Республики Казахстан МЕУКАМ | B28: KZKD00000840 | C28: 500000 | D28: =C28*1000 -> 500000000 | E28: 7.68 | F28: 45561 | G28: 47518 | H28: 4.2179517e+08 | I28: =VLOOKUP(B28,'KASE за 28.07.25'!$C$5:$F$162,4,0) -> 72.6814 | J28: =VLOOKUP(B28,'KASE за 28.07.25'!$C$5:$G$162,5,0) -> 76.3934 | K28: 18560000 | L28: =D28*I28/100+K28 -> 3.81967e+08 | M28: =L28/$L$59 -> 0.014876697 | N28: =D28*E28%/360 -> 106666.67 | O28: =K28+N28 -> 18666667
A29: Евразийский банк развития | B29: KZ2D00011863 | C29: 1700000 | D29: =C29*1000 -> 1700000000 | E29: 14.3 | F29: 45538 | G29: 46633 | H29: 1700000000 | I29: =VLOOKUP(B29,'Риск цены за 28.07.25'!$C$4:$G$963,4,0) -> 98.971538 | J29: =VLOOKUP(B29,'Риск цены за 28.07.25'!$C$4:$G$963,5,0) -> 111.88124 | K29: 2.1946528e+08 | L29: =D29*I29/100+K29 -> 1.9019814e+09 | M29: =L29/$L$59 -> 0.074077605 | N29: =D29*E29%/360 -> 675277.78 | O29: =K29+N29 -> 2.2014056e+08
A30: Министерство Финансов Республики Казахстан МЕУКАМ | B30: KZKD00001244 | C30: 500000 | D30: =C30*1000 -> 500000000 | E30: 12 | F30: 45540 | G30: 47901 | H30: 5.0216167e+08 | I30: =VLOOKUP(B30,'KASE за 28.07.25'!$C$5:$F$162,4,0) -> 83.799 | J30: =VLOOKUP(B30,'KASE за 28.07.25'!$C$5:$G$162,5,0) -> 88.999 | K30: 26000000 | L30: =D30*I30/100+K30 -> 4.44995e+08 | M30: =L30/$L$59 -> 0.017331486 | N30: =D30*E30%/360 -> 166666.67 | O30: =K30+N30 -> 26166667
A31: Министерство Финансов Республики Казахстан МЕУКАМ | B31: KZKD00001251 | C31: 300000 | D31: =C31*1000 -> 300000000 | E31: 12 | F31: 45547 | G31: 47549 | H31: 302854400 | I31: =VLOOKUP(B31,'KASE за 28.07.25'!$C$5:$F$162,4,0) -> 85.4752 | J31: =VLOOKUP(B31,'KASE за 28.07.25'!$C$5:$G$162,5,0) -> 90.1752 | K31: 14100000 | L31: =D31*I31/100+K31 -> 270525600 | M31: =L31/$L$59 -> 0.010536322 | N31: =D31*E31%/360 -> 100000 | O31: =K31+N31 -> 14200000
A32: Министерство Финансов Республики Казахстан МЕУКАМ | B32: KZKD00001251 | C32: 288579 | D32: =C32*1000 -> 288579000 | E32: 12 | F32: 45582 | G32: 47549 | H32: 2.9999932e+08 | I32: =VLOOKUP(B32,'KASE за 28.07.25'!$C$5:$F$162,4,0) -> 85.4752 | J32: =VLOOKUP(B32,'KASE за 28.07.25'!$C$5:$G$162,5,0) -> 90.1752 | K32: 13563213 | L32: =D32*I32/100+K32 -> 2.6022669e+08 | M32: =L32/$L$59 -> 0.010135204 | N32: =D32*E32%/360 -> 96193 | O32: =K32+N32 -> 13659406
A33: АО "Национальный управляющий холдинг "Байтерек" | B33: KZ2C00012698 | C33: 300000 | D33: =C33*1000 -> 300000000 | E33: 13.89 | F33: 45624 | G33: 46109 | H33: 300000000 | I33: =VLOOKUP(B33,'Риск цены за 28.07.25'!$C$4:$G$963,4,0) -> 97.836731 | J33: =VLOOKUP(B33,'Риск цены за 28.07.25'!$C$4:$G$963,5,0) -> 100.15173 | K33: 6945000 | L33: =D33*I33/100+K33 -> 3.0045519e+08 | M33: =L33/$L$59 -> 0.011702008 | N33: =D33*E33%/360 -> 115750 | O33: =K33+N33 -> 7060750
A34: Министерство Финансов Республики Казахстан МЕУКАМ | B34: KZKD00000964 | C34: =220000-213000 -> 7000 | D34: =C34*1000 -> 7000000 | E34: 8.44 | F34: 45639 | G34: 47978 | H34: =182967986.67/220000000*D34 -> 5821708.7 | I34: =VLOOKUP(B34,'KASE за 28.07.25'!$C$5:$F$162,4,0) -> 71.0802 | J34: =VLOOKUP(B34,'KASE за 28.07.25'!$C$5:$G$162,5,0) -> 72.9089 | K34: 128006.67 | L34: =D34*I34/100+K34 -> 5103620.7 | M34: =L34/$L$59 -> 0.00019877376 | N34: =D34*E34%/360 -> 1641.1111 | O34: =K34+N34 -> 129647.78
A35: Министерство Финансов Республики Казахстан МЕУКАМ | B35: KZKD00001236 | C35: =173000-163000 -> 10000 | D35: =C35*1000 -> 10000000 | E35: 14 | F35: 45639 | G35: 48353 | H35: =188266096.67/173000000*D35 -> 10882433 | I35: =VLOOKUP(B35,'KASE за 28.07.25'!$C$5:$F$162,4,0) -> 89.9965 | J35: =VLOOKUP(B35,'KASE за 28.07.25'!$C$5:$G$162,5,0) -> 92.6798 | K35: 268333.33 | L35: =D35*I35/100+K35 -> 9267983.3 | M35: =L35/$L$59 -> 0.00036096568 | N35: =D35*E35%/360 -> 3888.8889 | O35: =K35+N35 -> 272222.22
A36: Министерство Финансов Республики Казахстан МЕУКАМ | B36: KZKD00001079 | C36: 300000 | D36: =C36*1000 -> 300000000 | E36: 8.7 | F36: 45651 | G36: 50082 | H36: 237511300 | I36: =VLOOKUP(B36,'KASE за 28.07.25'!$C$5:$F$165,4,0) -> 61.2953 | J36: =VLOOKUP(B36,'KASE за 28.07.25'!$C$5:$G$165,5,0) -> 65.3311 | K36: 12107500 | L36: =D36*I36/100+K36 -> 195993400 | M36: =L36/$L$59 -> 0.0076334719 | N36: =D36*E36%/360 -> 72500 | O36: =K36+N36 -> 12180000
A37: Министерство Финансов Республики Казахстан МЕУКАМ | B37: KZKD00001079 | C37: 200000 | D37: =C37*1000 -> 200000000 | E37: 8.7 | F37: 45680 | G37: 50082 | H37: 157353400 | I37: =VLOOKUP(B37,'KASE за 28.07.25'!$C$5:$F$165,4,0) -> 61.2953 | J37: =VLOOKUP(B37,'KASE за 28.07.25'!$C$5:$G$165,5,0) -> 65.3311 | K37: 8071666.7 | L37: =D37*I37/100+K37 -> 1.3066227e+08 | M37: =L37/$L$59 -> 0.0050889812 | N37: =D37*E37%/360 -> 48333.333 | O37: =K37+N37 -> 8120000
A38: Министерство Финансов Республики Казахстан МЕУКАМ | B38: KZKD00001202 | C38: 263000 | D38: =C38*1000 -> 263000000 | E38: 11 | F38: 45656 | G38: 47518 | H38: 2.6372196e+08 | I38: =VLOOKUP(B38,'KASE за 28.07.25'!$C$5:$F$162,4,0) -> 82.5655 | J38: =VLOOKUP(B38,'KASE за 28.07.25'!$C$5:$G$162,5,0) -> 87.8822 | K38: 13982833 | L38: =D38*I38/100+K38 -> 2.311301e+08 | M38: =L38/$L$59 -> 0.0090019618 | N38: =D38*E38%/360 -> 80361.111 | O38: =K38+N38 -> 14063194
A39: Министерство Финансов Республики Казахстан МЕУКАМ | B39: KZKD00001210 | C39: 341000 | D39: =C39*1000 -> 341000000 | E39: 15.3 | F39: 45657 | G39: 47180 | H39: 396883762 | I39: =VLOOKUP(B39,'KASE за 28.07.25'!$C$5:$F$162,4,0) -> 95.8271 | J39: =VLOOKUP(B39,'KASE за 28.07.25'!$C$5:$G$162,5,0) -> 101.9896 | K39: 21014125 | L39: =D39*I39/100+K39 -> 347784536 | M39: =L39/$L$59 -> 0.013545372 | N39: =D39*E39%/360 -> 144925 | O39: =K39+N39 -> 21159050
A40: Министерство Финансов Республики Казахстан МЕУКАМ | B40: KZKD00001095 | C40: =214727-132000 -> 82727 | D40: =C40*1000 -> 82727000 | E40: 10.47 | F40: 45673 | G40: 47053 | H40: 77053072 | I40: =VLOOKUP(B40,'KASE за 28.07.25'!$C$5:$F$162,4,0) -> 84.746 | J40: =VLOOKUP(B40,'KASE за 28.07.25'!$C$5:$G$162,5,0) -> 92.6276 | K40: 6520197.4 | L40: =D40*I40/100+K40 -> 76628021 | M40: =L40/$L$59 -> 0.0029844772 | N40: =D40*E40%/360 -> 24059.769 | O40: =K40+N40 -> 6544257.2
A41: Министерство Финансов Республики Казахстан МЕУКАМ | B41: KZKD00000790 | C41: 227500 | D41: =C41*1000 -> 227500000 | E41: 7.68 | F41: 45702 | G41: 47343 | H41: 1.8902823e+08 | I41: =VLOOKUP(B41,'KASE за 28.07.25'!$C$5:$F$162,4,0) -> 74.7474 | J41: =VLOOKUP(B41,'KASE за 28.07.25'!$C$5:$G$162,5,0) -> 82.1074 | K41: 16744000 | L41: =D41*I41/100+K41 -> 1.8679434e+08 | M41: =L41/$L$59 -> 0.0072751904 | N41: =D41*E41%/360 -> 48533.333 | O41: =K41+N41 -> 16792533
A42: Министерство Финансов Республики Казахстан | B42: KZKD00000717 | C42: 500000 | D42: =C42*1000 -> 500000000 | E42: 7.22 | F42: 45729 | G42: 47097 | H42: 3.9979333e+08 | I42: =VLOOKUP(B42,'KASE за 28.07.25'!$C$5:$F$162,4,0) -> 76.5096 | J42: =VLOOKUP(B42,'KASE за 28.07.25'!$C$5:$G$162,5,0) -> 81.0823 | K42: 22863333 | L42: =D42*I42/100+K42 -> 4.0541133e+08 | M42: =L42/$L$59 -> 0.015789797 | N42: =D42*E42%/360 -> 100277.78 | O42: =K42+N42 -> 22963611
A43: Министерство Финансов Республики Казахстан | B43: KZKD00001210 | C43: 259000 | D43: =C43*1000 -> 259000000 | E43: 15.3 | F43: 45750 | G43: 47180 | H43: 260647240 | I43: =VLOOKUP(B43,'KASE за 28.07.25'!$C$5:$F$162,4,0) -> 95.8271 | J43: =VLOOKUP(B43,'KASE за 28.07.25'!$C$5:$G$162,5,0) -> 101.9896 | K43: 15960875 | L43: =D43*I43/100+K43 -> 264153064 | M43: =L43/$L$59 -> 0.010288127 | N43: =D43*E43%/360 -> 110075 | O43: =K43+N43 -> 16070950
A44: АО "Национальный управляющий холдинг "Байтерек" | B44: KZ2C00012268 | C44: 200000 | D44: =C44*1000 -> 200000000 | E44: 16.7 | F44: 45757 | G44: 46122 | H44: 200000000 | I44: =VLOOKUP(B44,'Риск цены за 28.07.25'!$C$4:$G$963,4,0) -> 99.40283 | J44: =VLOOKUP(B44,'Риск цены за 28.07.25'!$C$4:$G$963,5,0) -> 104.41283 | K44: 10020000 | L44: =D44*I44/100+K44 -> 2.0882566e+08 | M44: =L44/$L$59 -> 0.0081332575 | N44: =D44*E44%/360 -> 92777.778 | O44: =K44+N44 -> 10112778
A45: Министерство Финансов Республики Казахстан | B45: KZKD00000477 | C45: 500000 | D45: =C45*1000 -> 500000000 | E45: 5.3 | F45: 45764 | G45: 46679 | H45: 4.1207678e+08 | I45: =VLOOKUP(B45,'KASE за 28.07.25'!$C$5:$F$162,4,0) -> 79.6212 | J45: =VLOOKUP(B45,'KASE за 28.07.25'!$C$5:$G$162,5,0) -> 83.7287 | K45: 20537500 | L45: =D45*I45/100+K45 -> 4.186435e+08 | M45: =L45/$L$59 -> 0.016305158 | N45: =D45*E45%/360 -> 73611.111 | O45: =K45+N45 -> 20611111
A46: Министерство Финансов Республики Казахстан | B46: KZKD00001202 | C46: 737000 | D46: =C46*1000 -> 737000000 | E46: 11 | F46: 45771 | G46: 47518 | H46: 6.4967099e+08 | I46: =VLOOKUP(B46,'KASE за 28.07.25'!$C$5:$F$162,4,0) -> 82.5655 | J46: =VLOOKUP(B46,'KASE за 28.07.25'!$C$5:$G$162,5,0) -> 87.8822 | K46: 39183833 | L46: =D46*I46/100+K46 -> 6.4769157e+08 | M46: =L46/$L$59 -> 0.02522603 | N46: =D46*E46%/360 -> 225194.44 | O46: =K46+N46 -> 39409028
A47: Министерство Финансов Республики Казахстан | B47: KZKD00001129 | C47: 6000 | D47: =C47*1000 -> 6000000 | E47: 10.3 | F47: 45775 | G47: 47924 | H47: 4822485.3 | I47: =VLOOKUP(B47,'KASE за 28.07.25'!$C$5:$F$162,4,0) -> 77.9074 | J47: =VLOOKUP(B47,'KASE за 28.07.25'!$C$5:$G$162,5,0) -> 81.6555 | K47: 224883.33 | L47: =D47*I47/100+K47 -> 4899327.3 | M47: =L47/$L$59 -> 0.00019081702 | N47: =D47*E47%/360 -> 1716.6667 | O47: =K47+N47 -> 226600
A48: Министерство Финансов Республики Казахстан | B48: KZKD00001129 | C48: 6000 | D48: =C48*1000 -> 6000000 | E48: 10.3 | F48: 45775 | G48: 47924 | H48: 4841157.3 | I48: =VLOOKUP(B48,'KASE за 28.07.25'!$C$5:$F$162,4,0) -> 77.9074 | J48: =VLOOKUP(B48,'KASE за 28.07.25'!$C$5:$G$162,5,0) -> 81.6555 | K48: 224883.33 | L48: =D48*I48/100+K48 -> 4899327.3 | M48: =L48/$L$59 -> 0.00019081702 | N48: =D48*E48%/360 -> 1716.6667 | O48: =K48+N48 -> 226600
A49: АО "Банк Развития Казахстана" | B49: KZ2C00010106 | C49: 500000 | D49: =C49*1000 -> 500000000 | E49: 17 | F49: 45782 | G49: 46147 | H49: 500000000 | I49: 100 | J49: 100 | K49: 19597222 | L49: =D49*I49/100+K49 -> 5.1959722e+08 | M49: =L49/$L$59 -> 0.020237063 | N49: =D49*E49%/360 -> 236111.11 | O49: =K49+N49 -> 19833333
A50: Министерство Финансов Республики Казахстан | B50: KZKD00000964 | C50: 500000 | D50: =C50*1000 -> 500000000 | E50: 8.44 | F50: 45799 | G50: 47978 | H50: 3.7223717e+08 | I50: =VLOOKUP(B50,'KASE за 28.07.25'!$C$5:$F$165,4,0) -> 71.0802 | J50: =VLOOKUP(B50,'KASE за 28.07.25'!$C$5:$G$165,5,0) -> 72.9089 | K50: 9143333.3 | L50: =D50*I50/100+K50 -> 3.6454433e+08 | M50: =L50/$L$59 -> 0.014198126 | N50: =D50*E50%/360 -> 117222.22 | O50: =K50+N50 -> 9260555.6
A51: Министерство Финансов Республики Казахстан | B51: KZKD00000790 | C51: 500000 | D51: =C51*1000 -> 500000000 | E51: 7.68 | F51: 45813 | G51: 47343 | H51: 4.0360417e+08 | I51: =VLOOKUP(B51,'KASE за 28.07.25'!$C$5:$F$165,4,0) -> 74.7474 | J51: =VLOOKUP(B51,'KASE за 28.07.25'!$C$5:$G$165,5,0) -> 82.1074 | K51: 36800000 | L51: =D51*I51/100+K51 -> 4.10537e+08 | M51: =L51/$L$59 -> 0.015989429 | N51: =D51*E51%/360 -> 106666.67 | O51: =K51+N51 -> 36906667
A52: Министерство Финансов Республики Казахстан | B52: KZKD00000543 | C52: 500000 | D52: =C52*1000 -> 500000000 | E52: 5 | F52: 45813 | G52: 46861 | H52: 3.7940239e+08 | I52: =VLOOKUP(B52,'KASE за 28.07.25'!$C$5:$F$165,4,0) -> 75.4422 | J52: =VLOOKUP(B52,'KASE за 28.07.25'!$C$5:$G$165,5,0) -> 76.8311 | K52: 6944444.4 | L52: =D52*I52/100+K52 -> 3.8415544e+08 | M52: =L52/$L$59 -> 0.014961931 | N52: =D52*E52%/360 -> 69444.444 | O52: =K52+N52 -> 7013888.9
A53: Министерство Финансов Республики Казахстан | B53: KZKD00001160 | C53: 200000 | D53: =C53*1000 -> 200000000 | E53: 10.55 | F53: 45820 | G53: 47327 | H53: 1.8266529e+08 | I53: =VLOOKUP(B53,'KASE за 28.07.25'!$C$5:$F$165,4,0) -> 82.8642 | J53: =VLOOKUP(B53,'KASE за 28.07.25'!$C$5:$G$165,5,0) -> 82.8642 | K53: =21100000-21100000 -> 0 | L53: =D53*I53/100+K53 -> 165728400 | M53: =L53/$L$59 -> 0.0064547228 | N53: =D53*E53%/360 -> 58611.111 | O53: =K53+N53 -> 58611.111
A54: Министерство Финансов Республики Казахстан | B54: KZKD00001251 | C54: 500000 | D54: =C54*1000 -> 500000000 | E54: 12 | F54: 45832 | G54: 47549 | H54: 4.4701683e+08 | I54: =VLOOKUP(B54,'KASE за 28.07.25'!$C$5:$F$165,4,0) -> 85.4752 | J54: =VLOOKUP(B54,'KASE за 28.07.25'!$C$5:$G$165,5,0) -> 90.1752 | K54: 23500000 | L54: =D54*I54/100+K54 -> 4.50876e+08 | M54: =L54/$L$59 -> 0.017560537 | N54: =D54*E54%/360 -> 166666.67 | O54: =K54+N54 -> 23666667
A55: Министерство Финансов Республики Казахстан | B55: KZKD00001251 | C55: 500000 | D55: =C55*1000 -> 500000000 | E55: 12 | F55: 45832 | G55: 47549 | H55: 4.4561733e+08 | I55: =VLOOKUP(B55,'KASE за 28.07.25'!$C$5:$F$165,4,0) -> 85.4752 | J55: =VLOOKUP(B55,'KASE за 28.07.25'!$C$5:$G$165,5,0) -> 90.1752 | K55: 23500000 | L55: =D55*I55/100+K55 -> 4.50876e+08 | M55: =L55/$L$59 -> 0.017560537 | N55: =D55*E55%/360 -> 166666.67 | O55: =K55+N55 -> 23666667
A56: Министерство Финансов Республики Казахстан | B56: KZKD00001251 | C56: 411421 | D56: =C56*1000 -> 411421000 | E56: 12 | F56: 45832 | G56: 47549 | H56: 3.6376844e+08 | I56: =VLOOKUP(B56,'KASE за 28.07.25'!$C$5:$F$165,4,0) -> 85.4752 | J56: =VLOOKUP(B56,'KASE за 28.07.25'!$C$5:$G$165,5,0) -> 90.1752 | K56: 19336787 | L56: =D56*I56/100+K56 -> 3.7099971e+08 | M56: =L56/$L$59 -> 0.014449547 | N56: =D56*E56%/360 -> 137140.33 | O56: =K56+N56 -> 19473927
A57: Министерство Финансов Республики Казахстан | B57: KZKD00001301 | C57: 500000 | D57: =C57*1000 -> 500000000 | E57: 14.45 | F57: 45848 | G57: 48735 | H57: 4.5341681e+08 | I57: =VLOOKUP(B57,'KASE за 28.07.25'!$C$5:$F$165,4,0) -> 91.3204 | J57: =VLOOKUP(B57,'KASE за 28.07.25'!$C$5:$G$165,5,0) -> 93.4478 | K57: 10636806 | L57: =D57*I57/100+K57 -> 4.6723881e+08 | M57: =L57/$L$59 -> 0.018197828 | N57: =D57*E57%/360 -> 200694.44 | O57: =K57+N57 -> 10837500
A58: Министерство Финансов Республики Казахстан | B58: KZKD00000964 | C58: 500000 | D58: =C58*1000 -> 500000000 | E58: 8.44 | F58: 45862 | G58: 47978 | H58: 3.5788194e+08 | I58: =VLOOKUP(B58,'KASE за 28.07.25'!$C$5:$F$165,4,0) -> 71.0802 | J58: =VLOOKUP(B58,'KASE за 28.07.25'!$C$5:$G$165,5,0) -> 72.9089 | K58: 9143333.3 | L58: =D58*I58/100+K58 -> 3.6454433e+08 | M58: =L58/$L$59 -> 0.014198126 | N58: =D58*E58%/360 -> 117222.22 | O58: =K58+N58 -> 9260555.6
A59: ИТОГО | C59: =SUM(C6:C58) -> 31893061 | D59: =SUM(D6:D58) -> 31893061000 | H59: =SUM(H6:H58) -> 2.7348601e+10 | K59: =SUM(K6:K58) -> 1.074127e+09 | L59: =SUM(L6:L58) -> 2.5675525e+10 | M59: =SUM(M6:M58) -> 1 | N59: 2.5675525e+10 | O59: =L59-N59 -> 0
A61: Остатки на инвест. cчетах
A62: KZT | B62: 740983.16 | C62: 740983.16 | D62: =B62-C62 -> 0
A64: Обратное репо
A65: Наименование эмитента и вид ЦБ | B65: НИН (ISIN) | C65: Количество | D65: Валюта | E65: Дата открытия | F65: Дата закрытия | G65: Цена открытия | H65: Цена закрытия | I65: Сумма открытия операции. в тг | J65: Сумма закрытия операции. в тг | K65: Ставка доходности. % | L65: Сумма начисленного вознагрждения | M65: Суммарная текущая стоимость. в тг
A66: Министерство Финансов Республики Казахстан | B66: XS2914770545 | C66: 2522960 | D66: KZT | E66: 45863 | F66: 45866 | G66: 531.9526 | H66: 532.63991 | I66: 1.3420951e+09 | J66: 1.3438292e+09 | K66: 15.72 | L66: =IF(($B$1-E66)=0,0,(J66-I66)/(F66-E66)*($B$1-E66)) -> 1734060.5 | M66: =IF((F66=$B$1),0,(I66+L66)) -> 0
A67: Национальный Банк РК | B67: KZW100014312 | C67: 80840 | D67: KZT | E67: 45863 | F67: 45866 | G67: 98.9618 | H67: 99.089664 | I67: 8000071.9 | J67: 8010408.4 | K67: 15.719998 | L67: =IF(($B$1-E67)=0,0,(J67-I67)/(F67-E67)*($B$1-E67)) -> 10336.53 | M67: =IF((F67=$B$1),0,(I67+L67)) -> 0
A68: АО "Казахстанский фонд устойчивости" | B68: KZ2C00012383 | C68: 84826 | D68: KZT | E68: 45863 | F68: 45866 | G68: 979.405 | H68: 980.66883 | I68: 83079009 | J68: 83186215 | K68: 15.7 | L68: =IF(($B$1-E68)=0,0,(J68-I68)/(F68-E68)*($B$1-E68)) -> 107206.06 | M68: =IF((F68=$B$1),0,(I68+L68)) -> 0
A69: Министерство Финансов Республики Казахстан | B69: KZKD00001095 | C69: 1540080 | D69: KZT | E69: 45866 | F69: 45867 | G69: 926.276 | H69: 926.67417 | I69: 1.4265391e+09 | J69: 1.4271524e+09 | K69: 15.6899 | L69: =IF(($B$1-E69)=0,0,(J69-I69)/(F69-E69)*($B$1-E69)) -> 0 | M69: =IF((F69=$B$1),0,(I69+L69)) -> 1.4265391e+09
A70: Министерство Финансов Республики Казахстан | B70: KZK200000737 | C70: 8910 | D70: KZT | E70: 45866 | F70: 45867 | G70: 1010.772 | H70: 1011.2065 | I70: 9005978.5 | J70: 9009849.8 | K70: 15.68989 | L70: =IF(($B$1-E70)=0,0,(J70-I70)/(F70-E70)*($B$1-E70)) -> 0 | M70: =IF((F70=$B$1),0,(I70+L70)) -> 9005978.5
A71: Министерство Финансов Республики Казахстан | B71: KZKD00001244 | C71: 393400 | D71: KZT | E71: 45866 | F71: 45867 | G71: 889.99 | H71: 890.37038 | I71: 350122066 | J71: 3.5027171e+08 | K71: 15.6002 | L71: =IF(($B$1-E71)=0,0,(J71-I71)/(F71-E71)*($B$1-E71)) -> 0 | M71: =IF((F71=$B$1),0,(I71+L71)) -> 350122066
A72: Министерство Финансов Республики Казахстан | B72: KZKD00001244 | C72: 2248 | D72: KZT | E72: 45866 | F72: 45867 | G72: 889.99 | H72: 890.37038 | I72: 2000697.5 | J72: 2001552.6 | K72: 15.600134 | L72: =IF(($B$1-E72)=0,0,(J72-I72)/(F72-E72)*($B$1-E72)) -> 0 | M72: =IF((F72=$B$1),0,(I72+L72)) -> 2000697.5
A74: ИТОГО | C74: =SUM(C66:C72) -> 4633264 | I74: =SUM(I66:I72) -> 3.2208421e+09 | J74: =SUM(J66:J72) -> 3.2234613e+09 | L74: =SUM(L66:L72) -> 1851603 | M74: =SUM(M66:M72) -> 1.7876679e+09 | N74: 1.7876679e+09 | O74: =M74-N74 -> 0
A77: Прочие активы (дебиторская задолженность. деньги в пути)
A78: № п/п | B78: Наименование | C78: Валюта | D78: Дата постановки на учет | E78: Количество | F78: Остаток в валюте | G78: Остаток в тенге
A80: ИТОГО | G80: =SUM(G79:G79) -> 0
A82: Итого активов | B82: =L59+B62+M74+G80 -> 2.7463934e+10 | C82: 2.7463934e+10 | D82: =B82-C82 -> 0
A86: 2) Кредиторская задолженность Фонда
A87: Комиссия ДУ (за управление) | B87: =4028672.96-4028672.96 -> 0
A88: Комиссия ДУ (сверхдоходность)
A89: Комиссия Кастоди | B89: =2000+3000+5000+7000+2000+4000+3000+5000+2000+3000+3000+2000+2000+24000+2000+6000+2000+2000+2000+2000+351673.18+71000+2000+6000+2000+3000+2000+3000+2000+2000+2000+2000-434673.18+2000+2000+2000+2000+2000+3000+3000+4000 -> 117000
A90: Комиссия Глобал кастоди
A91: Комиссия Центрального Депозитария | B91: =367821.53+24184.63-392006.16 -> 0
A92: Клиринговый сбор | B92: =1657.93+17471.45+833.85+38281.52+5689.78+11446.32+972.72+14750.07+2307.41+6498.23+11312.18+793.95+2780.61+11287.83+2853.64+2484.36+2483.47+2482.94+9626+3231.91+4083.63+3230.48+3265.02+12872.21+3281.52+3247.37+2574.32+7640.52+2575.08+2576.75+2575.88+2577.32+7662+2583.06+2582.99+2585.09+2053.2+6452.61+2743.63-149246.17 -> 77162.68
A93: Комиссия биржи | B93: =813.81+8735.72+373.69+128083.49+2827.48+5705.74+465.05+25613.5+1140.79+3234.71+5642.43+379.56+1378.16+5629.32+1415.42+126867.26+1228.08+1228.56+4813+1606.04+1606.55+1607.59+1608.19+6436.1+1611.94+1612.29+46613.68-327181.81+3820.27+1275.38+1275.47+1276.53+1276.5+3831+1278.62+1279.34+1280.38+36800.38+3224.64+1340.74 -> 119055.59
A94: Комиссия брокера
A95: Кредиторская задолженность (прочая комиссия)
A96: Остаток прочих обязательств на конец дня
A97: Итого | B97: =SUM(B87:B96) -> 313218.27

Sheet KASE за 28.07.25
A1: Дата оценки | B1: 45866
A3: № п/п | B3: Код | C3: ISIN | D3: Вид ценной бумаги | E3: Компания | F3: Рыночная цена | G3: Рыночная "грязная" цена | H3: Доходность до погашения, % годовых | I3: Срок до погашения | J3: Единица измерения цены
A5: 1 | B5: 1AIRA | C5: KZ1C00004050 | D5: акции | E5: Эйр Астана | F5: 742.02 | G5: – | H5: – | I5: – | J5: KZT
A6: 2 | B6: 2AIRAd | C6: US0090632078 | D6: производные ЦБ | E6: Эйр Астана | F6: 5.74 | G6: – | H6: – | I6: – | J6: USD
A7: 3 | B7: 3AKZM | C7: KZ1C00001288 | D7: акции | E7: Актюбинский завод металлоконструкций | F7: 6261.15 | G7: – | H7: – | I7: – | J7: KZT
A8: 4 | B8: 4ALMSb1 | C8: KZ2C00012953 | D8: долговые ЦБ | E8: АК Алтыналмас | F8: 100.0237 | G8: 100.7348 | H8: 7,99 | I8: 868 (2) | J8: %
A9: 5 | B9: 5ASBN | C9: KZ000A0F4546 | D9: акции | E9: ForteBank | F9: 26.18 | G9: – | H9: – | I9: – | J9: KZT
A10: 6 | B10: 6BCCI_cc | C10: KZPF00000058 | D10: ЦБ инвест. фондов | E10: BCC Invest | F10: 123.68 | G10: – | H10: – | I10: – | J10: USD
A11: 7 | B11: 7BCCIbe | C11: KZPF00000553 | D11: ЦБ инвест. фондов | E11: BCC Invest | F11: 1445.71 | G11: – | H11: – | I11: – | J11: KZT
A12: 8 | B12: 8BCCIrb | C12: KZPF00000231 | D12: ЦБ инвест. фондов | E12: BCC Invest | F12: 6.71 | G12: – | H12: – | I12: – | J12: KZT
A13: 9 | B13: 9BIGDb5 | C13: KZ2D00012861 | D13: долговые ЦБ | E13: Частная компания BI Development Ltd. | F13: 101.0937 | G13: 104.2895 | H13: 18,71 | I13: 661 (2) | J13: %
A14: 10 | B14: 10BRKZe18 | C14: XS3032932645 | D14: долговые ЦБ | E14: Банк Развития Казахстана | F14: 101.4303 | G14: 103.1647 | H14: 5,28 | I14: 1 689 (5) | J14: %
A15: 11 | B15: 11BTRKe1 | C15: XS3067899610 | D15: долговые ЦБ | E15: Национальный управляющий холдинг "Байтерек" | F15: 101.1884 | G15: 102.3995 | H15: 4,98 | I15: 1 000 (3) | J15: %
A16: 12 | B16: 12CCBN | C16: KZ0007786572 | D16: акции | E16: Банк ЦентрКредит | F16: 3704.54 | G16: – | H16: – | I16: – | J16: KZT
A17: 13 | B17: 13CCBNp | C17: KZ000A0H0930 | D17: акции | E17: Банк ЦентрКредит | F17: 5265.13 | G17: – | H17: – | I17: – | J17: KZT
A18: 14 | B18: 14CLSGb6 | C18: KZ2P00014152 | D18: долговые ЦБ | E18: Capital Leasing Group (Капитал Лизинг Груп) | F18: 99.9416 | G18: 103.4416 | H18: 21,00 | I18: 60 (0) | J18: %
A19: 15 | B19: 15CSECfe | C19: KZPF00000025 | D19: ЦБ инвест. фондов | E19: Сентрас Секьюритиз | F19: 5804336.1 | G19: – | H19: – | I19: – | J19: KZT
A20: 16 | B20: 16CSECtf | C20: KZPF00000280 | D20: ЦБ инвест. фондов | E20: Сентрас Секьюритиз | F20: 1718367.3 | G20: – | H20: – | I20: – | J20: KZT
A21: 17 | B21: 17EABRb40 | C21: KZ2D00009628 | D21: ЦБ МФО | E21: Евразийский банк развития | F21: 99.6614 | G21: 101.6952 | H21: 6,25 | I21: 232 (1) | J21: %
A22: 18 | B22: 18EABRb42 | C22: KZ2D00009222 | D22: ЦБ МФО | E22: Евразийский банк развития | F22: 100 | G22: 106.8116 | H22: 16,23 | I22: 942 (3) | J22: %
A23: 19 | B23: 19EABRb53 | C23: KZ2D00013620 | D23: ЦБ МФО | E23: Евразийский банк развития | F23: 100 | G23: 105.8973 | H23: 17,46 | I23: 973 (3) | J23: %
A24: 20 | B24: 20FFIN_or | C24: KZPF00000082 | D24: ЦБ инвест. фондов | E24: Фридом Финанс | F24: 88489.87 | G24: – | H24: – | I24: – | J24: KZT
A25: 21 | B25: 21FFINgw | C25: KZPF00000090 | D25: ЦБ инвест. фондов | E25: Фридом Финанс | F25: 5420.25 | G25: – | H25: – | I25: – | J25: KZT
A26: 22 | B26: 22FHJIag | C26: KZPF00000132 | D26: ЦБ инвест. фондов | E26: Jusan Invest | F26: 1019.88 | G26: – | H26: – | I26: – | J26: USD
A27: 23 | B27: 23FHJIpc | C27: KZPF00000140 | D27: ЦБ инвест. фондов | E27: Jusan Invest | F27: 1156.48 | G27: – | H27: – | I27: – | J27: USD
A28: 24 | B28: 24HCBNb9 | C28: KZ2C00009892 | D28: долговые ЦБ | E28: Home Credit Bank | F28: 99.9056 | G28: 107.8806 | H28: 21,60 | I28: 6 (0) | J28: %
A29: 25 | B29: 25HFINhl | C29: KZPF00000538 | D29: ЦБ инвест. фондов | E29: Halyk Finance | F29: 52947.34 | G29: – | H29: – | I29: – | J29: KZT
A30: 26 | B30: 26HFINhp | C30: KZPF00000546 | D30: ЦБ инвест. фондов | E30: Halyk Finance | F30: 73824.91 | G30: – | H30: – | I30: – | J30: KZT
A31: 27 | B31: 27HFINhs | C31: KZPF00000520 | D31: ЦБ инвест. фондов | E31: Halyk Finance | F31: 72695.53 | G31: – | H31: – | I31: – | J31: KZT
A32: 28 | B32: 28HFINhv | C32: KZPF00000041 | D32: ЦБ инвест. фондов | E32: Halyk Finance | F32: 574340.97 | G32: – | H32: – | I32: – | J32: KZT
A33: 29 | B33: 29HSBK | C33: KZ000A0LE0S4 | D33: акции | E33: Народный Банк Казахстана | F33: 347.61 | G33: – | H33: – | I33: – | J33: KZT
A34: 30 | B34: 30HSBKd | C34: US46627J3023 | D34: производные ЦБ | E34: Народный Банк Казахстана | F34: 25.05 | G34: – | H34: – | I34: – | J34: USD
A35: 31 | B35: 31IFDR | C35: KZ1C00000256 | D35: акции | E35: Teniz Capital Investment Banking | F35: 9490.25 | G35: – | H35: – | I35: – | J35: KZT
A36: 32 | B36: 32KCEL | C36: KZ1C00000876 | D36: акции | E36: Kcell | F36: 3433.38 | G36: – | H36: – | I36: – | J36: KZT
A37: 33 | B37: 33KEGC | C37: KZ1C00000959 | D37: акции | E37: KEGOC | F37: 1447.42 | G37: – | H37: – | I37: – | J37: KZT
A38: 34 | B38: 34KMGZ | C38: KZ1C00001122 | D38: акции | E38: Национальная компания "КазМунайГаз" | F38: 19969.38 | G38: – | H38: – | I38: – | J38: KZT
A39: 35 | B39: 35KMGZe12 | C39: XS1595714087 | D39: долговые ЦБ | E39: Национальная компания "КазМунайГаз" | F39: 86.4722 | G39: 88.0535 | H39: 6,97 | I39: 7 821 (22) | J39: %
A40: 36 | B40: 36KMGZe14 | C40: XS1807300105 | D40: долговые ЦБ | E40: Национальная компания "КазМунайГаз" | F40: 101.241 | G40: 102.6445 | H40: 5,08 | I40: 1 706 (5) | J40: %
A41: 37 | B41: 37KMGZe15 | C41: XS1807299331 | D41: долговые ЦБ | E41: Национальная компания "КазМунайГаз" | F41: 92.7159 | G41: 94.3805 | H41: 7,01 | I41: 8 366 (23) | J41: %
A42: 38 | B42: 38KMGZe16 | C42: XS2242422397 | D42: долговые ЦБ | E42: Национальная компания "КазМунайГаз" | F42: 87.4856 | G42: 88.4967 | H42: 5,51 | I42: 2 776 (8) | J42: %
A43: 39 | B43: 39KSPI | C43: KZ1C00001536 | D43: акции | E43: Kaspi.kz | F43: 47749 | G43: – | H43: – | I43: – | J43: KZT
A44: 40 | B44: 40KSPId | C44: US48581R2058 | D44: производные ЦБ | E44: Kaspi.kz | F44: 88.33 | G44: – | H44: – | I44: – | J44: USD
A45: 41 | B45: 41KZAP | C45: KZ1C00001619 | D45: акции | E45: Национальная атомная компания "Казатомпром" | F45: 23284.42 | G45: – | H45: – | I45: – | J45: KZT
A46: 42 | B46: 42KZTCb3 | C46: KZ2C00012961 | D46: долговые ЦБ | E46: Jusan Mobile | F46: 102.8826 | G46: 110.8882 | H46: 20,48 | I46: 949 (3) | J46: %
A47: 43 | B47: 43KZTK | C47: KZ0009093241 | D47: акции | E47: Казахтелеком | F47: 39663.93 | G47: – | H47: – | I47: – | J47: KZT
A48: 44 | B48: 44KZTKp | C48: KZ0009094645 | D48: акции | E48: Казахтелеком | F48: 33139.1 | G48: – | H48: – | I48: – | J48: KZT
A49: 45 | B49: 45KZTO | C49: KZ1C00000744 | D49: акции | E49: КазТрансОйл | F49: 810.58 | G49: – | H49: – | I49: – | J49: KZT
A50: 46 | B50: 46KZ_23_3504 | C50: XS2914770545 | D50: ГЦБ | E50: Минфин | F50: 97.5 | G50: 98.9273 | H50: 5,04 | I50: 3 491 (10) | J50: %
A51: 47 | B51: 47MFMOb10 | C51: KZ2P00012651 | D51: долговые ЦБ | E51: МФО "Mogo Kazakhstan (Мого Казахстан) | F51: 78.905 | G51: 81.4383 | H51: 32,69 | I51: 464 (1) | J51: %
A52: 48 | B52: 48MFMOb17 | C52: KZ2P00013329 | D52: долговые ЦБ | E52: МФО "Mogo Kazakhstan (Мого Казахстан) | F52: 76.05 | G52: 76.2833 | H52: 63,64 | I52: 203 (1) | J52: %
A53: 49 | B53: 49MFMOb23 | C53: KZ2P00013154 | D53: долговые ЦБ | E53: МФО "Mogo Kazakhstan (Мого Казахстан) | F53: 99.9989 | G53: 100.7322 | H53: 22,00 | I53: 648 (2) | J53: %
A54: 50 | B54: 50MFMOb28 | C54: KZ2P00013352 | D54: долговые ЦБ | E54: МФО "Mogo Kazakhstan (Мого Казахстан) | F54: 99.9899 | G54: 100.2566 | H54: 12,01 | I54: 682 (2) | J54: %
A55: 51 | B55: 51MFOKb16 | C55: KZ2C00010171 | D55: долговые ЦБ | E55: МФО ОнлайнКазФинанс | F55: 100.274 | G55: 101.1443 | H55: 21,40 | I55: 106 (0) | J55: %
A56: 52 | B56: 52MFOKb18 | C56: KZ2C00010478 | D56: долговые ЦБ | E56: МФО ОнлайнКазФинанс | F56: 97.5903 | G56: 97.7014 | H56: 23,56 | I56: 268 (1) | J56: %
A57: 53 | B57: 53MFOKb19 | C57: KZ2C00010825 | D57: долговые ЦБ | E57: МФО ОнлайнКазФинанс | F57: 96.5309 | G57: 96.8087 | H57: 12,35 | I57: 590 (2) | J57: %
A58: 54 | B58: 54MFOKb20 | C58: KZ2C00010916 | D58: долговые ЦБ | E58: МФО ОнлайнКазФинанс | F58: 100.1489 | G58: 100.9318 | H58: 21,59 | I58: 737 (2) | J58: %
A59: 55 | B59: 55MFOKb21 | C59: KZ2C00011906 | D59: долговые ЦБ | E59: МФО ОнлайнКазФинанс | F59: 97.6547 | G59: 97.6547 | H59: 20,20 | I59: 900 (2) | J59: %
A60: 56 | B60: 56MFOKb22 | C60: KZ2C00011914 | D60: долговые ЦБ | E60: МФО ОнлайнКазФинанс | F60: 96.7906 | G60: 97.16 | H60: 22,00 | I60: 443 (1) | J60: %
A61: 57 | B61: 57MFOKb24 | C61: KZ2C00013258 | D61: долговые ЦБ | E61: МФО ОнлайнКазФинанс | F61: 100.7444 | G61: 101.6777 | H61: 20,63 | I61: 944 (3) | J61: %
... A170: 166 | B170: 166TSSPb1 | C170: KZ2P00008113 | D170: долговые ЦБ | E170: ТССП Групп | F170: 91.4443 | G170: 92.3443 | H170: 22,01 | I170: 1 062 (3) | J170: %

Sheet Риск цены за 28.07.25
A1: Дата оценки | C1: 45866
A3: № п/п | B3: Торговый код | C3: ISIN | D3: Алгоритмы и параметры расчета ЦБ | E3: Краткое наименование эмитента | F3: Расчетная цена | G3: Расчетная грязная | H3: Доходность до погашения. % годовых | I3: Дней до погашения | J3: Единица измерения цены
A4: 1 | B4: AAFD | C4: KZ1C00008721 | D4: Акции | E4: АО "АзияАгроФуд" | F4: 100 | G4: 100 | H4: 0 | I4: 0 | J4: KZT
A5: 2 | B5: AAL_KZ | C5: US02376R1023 | D5: Акции | E5: American Airlines | F5: 6309.7483 | G5: 6309.7483 | H5: 0 | I5: 0 | J5: KZT
A6: 3 | B6: AAPL_KZ | C6: US0378331005 | D6: Акции | E6: Apple Inc. | F6: 117097.25 | G6: 117097.25 | H6: 0 | I6: 0 | J6: KZT
A7: 4 | B7: ABK022_210 | C7: KZMJ00002103 | D7: Облигации | E7: Акимат Актюбинской области | F7: 100 | G7: 100.8736 | H7: 4.23 | I7: 406 | J7: %
A8: 5 | B8: ABK024_183 | C8: KZMJ00001832 | D8: Облигации | E8: Акимат Актюбинской области | F8: 100 | G8: 100.0583 | H8: 0.35 | I8: 300 | J8: %
A9: 6 | B9: ABK114_193 | C9: KZMJ00001931 | D9: Облигации | E9: Акимат Актюбинской области | F9: 100 | G9: 100.0168 | H9: 0.02 | I9: 3122 | J9: %
A10: 7 | B10: ABK119_006 | C10: KZMF00000069 | D10: Облигации | E10: Акимат Актюбинской области | F10: 100 | G10: 100.5592 | H10: 6.09 | I10: 1737 | J10: %
A11: 8 | B11: ABK119_081 | C11: KZMF00000812 | D11: Облигации | E11: Акимат Актюбинской области | F11: 100 | G11: 105.3447 | H11: 7.08 | I11: 2219 | J11: %
A12: 9 | B12: ABK131_021 | C12: KZMF00000218 | D12: Облигации | E12: Акимат Актюбинской области | F12: 100 | G12: 105.8289 | H12: 6.09 | I12: 2146 | J12: %
A13: 10 | B13: ABK143_032 | C13: KZMF00000325 | D13: Облигации | E13: Акимат Актюбинской области | F13: 100 | G13: 104.6767 | H13: 6.08 | I13: 2574 | J13: %
A14: 11 | B14: ABK143_033 | C14: KZMF00000333 | D14: Облигации | E14: Акимат Актюбинской области | F14: 100 | G14: 104.6767 | H14: 6.08 | I14: 2574 | J14: %
A15: 12 | B15: ABT_KZ | C15: US0028241000 | D15: Акции | E15: Abbott Lab. | F15: 68763.436 | G15: 68763.436 | H15: 0 | I15: 0 | J15: KZT
... A1004: 1001 | B1004: ZKK143_044 | C1004: KZMF00000440 | D1004: Облигации | E1004: Акимат Западно-Казахстанской области | F1004: 100 | G1004: 104.6767 | H1004: 6.08 | I1004: 2574 | J1004: %
