Workbook

Sheet ДУ
A1: Сентрас Секьюритиз | B1: 45997
A2: 1) Активы
A4: ЦБ
A5: Наименование эмитента и вид ЦБ | B5: ISIN | C5: Количество ЦБ | D5: Номинальная стоимость. тенге | E5: Ставка | F5: Дата зачисления/приобретения | G5: Дата погашения | H5: Чистая покупная стоимоcть | I5: Расчетная цена на 06.12.25 | J5: Расчетная грязная цена 06.12.25 | K5: Накопленный купон | L5: Суммарно-текущая рыночная стоимость | M5: Вес
A6: Министерство Финансов Республики Казахстан купонные МЕУКАМ | B6: KZKD00000535 | C6: =3250000-500000-500000-500000 -> 1750000 | D6: =3250000000-500000000-500000000-500000000 -> 1750000000 | E6: 5.49 | F6: 45491 | G6: 27.03.2027 | H6: =2755458875/3250000000*D6 -> 1483708625 | I6: =VLOOKUP(B6,'KASE за 05.12.25'!$C$5:$F$183,4,0) -> 87.12 | J6: =VLOOKUP(B6,'KASE за 05.12.25'!$C$5:$G$183,5,0) -> 90.902 | K6: 66451875 | L6: =D6*I6/100+K6 -> 1591051875 | M6: =L6/$L$63 -> 0.057760612 | N6: =D6*E6%/360 -> 266875 | O6: =K6+N6 -> 66718750
A7: Министерство Финансов Республики Казахстан купонные МЕУКАМ | B7: KZKD00001137 | C7: 1950000 | D7: 1950000000 | E7: 10.4 | F7: 45491 | G7: 12.04.2028 | H7: 1838876000 | I7: =VLOOKUP(B7,'KASE за 05.12.25'!$C$5:$F$162,4,0) -> 87.8759 | J7: =VLOOKUP(B7,'KASE за 05.12.25'!$C$5:$G$162,5,0) -> 94.607 | K7: 1.3182e+08 | L7: =D7*I7/100+K7 -> 1.8454e+09 | M7: =L7/$L$63 -> 0.066994319 | N7: =D7*E7%/360 -> 563333.33 | O7: =K7+N7 -> 1.3238333e+08
A8: Министерство Финансов Республики Казахстан МЕУКАМ | B8: KZKD00001087 | C8: =1950000-202300-182000-187350 -> 1378350 | D8: =C8*1000 -> 1378350000 | E8: 11 | F8: 45491 | G8: 31.03.2029 | H8: =1855844250/1950000000*D8 -> 1.3117964e+09 | I8: =VLOOKUP(B8,'KASE за 05.12.25'!$C$5:$F$162,4,0) -> 86.089 | J8: =VLOOKUP(B8,'KASE за 05.12.25'!$C$5:$G$162,5,0) -> 93.5751 | K8: 103605975 | L8: =D8*I8/100+K8 -> 1.2902137e+09 | M8: =L8/$L$63 -> 0.04683916 | N8: =D8*E8%/360 -> 421162.5 | O8: =K8+N8 -> 1.0402714e+08
A9: Министерство Финансов Республики Казахстан купонные МЕУКАМ | B9: KZKD00001160 | C9: =1950000-225000-225000-208000-225000-225000 -> 842000 | D9: =C9*1000 -> 842000000 | E9: 10.55 | F9: 45491 | G9: 28.07.2029 | H9: =1504310166.66923/1500000000*D9 -> 8.4441944e+08 | I9: =VLOOKUP(B9,'KASE за 05.12.25'!$C$5:$F$162,4,0) -> 84.1157 | J9: =VLOOKUP(B9,'KASE за 05.12.25'!$C$5:$G$162,5,0) -> 87.8375 | K9: 31584356 | L9: =D9*I9/100+K9 -> 7.3983855e+08 | M9: =L9/$L$63 -> 0.026858664 | N9: =D9*E9%/360 -> 246752.78 | O9: =K9+N9 -> 31831108
A10: Министерство Финансов Республики Казахстан купонные МЕУКАМ | B10: KZKD00001129 | C10: 1450000 | D10: 1450000000 | E10: 10.3 | F10: 45491 | G10: 17.03.2031 | H10: 1.307499e+09 | I10: =VLOOKUP(B10,'KASE за 05.12.25'!$C$5:$F$162,4,0) -> 79.4608 | J10: =VLOOKUP(B10,'KASE за 05.12.25'!$C$5:$G$162,5,0) -> 86.8425 | K10: 1.0744903e+08 | L10: =D10*I10/100+K10 -> 1.2596306e+09 | M10: =L10/$L$63 -> 0.04572889 | N10: =D10*E10%/360 -> 414861.11 | O10: =K10+N10 -> 1.0786389e+08
A11: Министерство Финансов Республики Казахстан МЕУКАМ | B11: KZKD00000949 | C11: 1950000 | D11: 1950000000 | E11: 8.45 | F11: 45491 | G11: 16.04.2032 | H11: 1.5403351e+09 | I11: =VLOOKUP(B11,'KASE за 05.12.25'!$C$5:$F$162,4,0) -> 70.3297 | J11: =VLOOKUP(B11,'KASE за 05.12.25'!$C$5:$G$162,5,0) -> 75.7048 | K11: 1.0527292e+08 | L11: =D11*I11/100+K11 -> 1.4767021e+09 | M11: =L11/$L$63 -> 0.053609324 | N11: =D11*E11%/360 -> 457708.33 | O11: =K11+N11 -> 1.0573062e+08
A12: Министерство Финансов Республики Казахстан Купонные Облигации | B12: KZKD00001152 | C12: =1950000-250000-250000-250000-218000 -> 982000 | D12: =C12*1000 -> 982000000 | E12: 10.65 | F12: 45491 | G12: 26.07.2032 | H12: =1897171250/1950000000*D12 -> 9.5539598e+08 | I12: =VLOOKUP(B12,'KASE за 05.12.25'!$C$5:$F$162,4,0) -> 78.1297 | J12: =VLOOKUP(B12,'KASE за 05.12.25'!$C$5:$G$162,5,0) -> 81.946 | K12: 37766083 | L12: =D12*I12/100+K12 -> 8.0499974e+08 | M12: =L12/$L$63 -> 0.029224237 | N12: =D12*E12%/360 -> 290508.33 | O12: =K12+N12 -> 38056592
A13: Министерство Финансов Республики Казахстан Купонные Облигации | B13: KZKD00001152 | C13: 250000 | D13: =C13*1000 -> 250000000 | E13: 10.65 | F13: 45673 | G13: 26.07.2032 | H13: =227969916.67/250000000*D13 -> 2.2796992e+08 | I13: =VLOOKUP(B13,'KASE за 05.12.25'!$C$5:$F$162,4,0) -> 78.1297 | J13: =VLOOKUP(B13,'KASE за 05.12.25'!$C$5:$G$162,5,0) -> 81.946 | K13: 9614583.3 | L13: =D13*I13/100+K13 -> 2.0493883e+08 | M13: =L13/$L$63 -> 0.0074399789 | N13: =D13*E13%/360 -> 73958.333 | O13: =K13+N13 -> 9688541.7
A14: Министерство Финансов Республики Казахстан купонные МЕУКАМ | B14: KZKD00000741 | C14: 1950000 | D14: 1950000000 | E14: 8.07 | F14: 45491 | G14: 12.05.2034 | H14: 1425576750 | I14: =VLOOKUP(B14,'KASE за 05.12.25'!$C$5:$F$183,4,0) -> 64.2153 | J14: =VLOOKUP(B14,'KASE за 05.12.25'!$C$5:$G$183,5,0) -> 68.7659 | K14: 89173500 | L14: =D14*I14/100+K14 -> 1341371850 | M14: =L14/$L$63 -> 0.048696375 | N14: =D14*E14%/360 -> 437125 | O14: =K14+N14 -> 89610625
A15: Министерство Финансов Республики Казахстан купонные МЕУКАМ | B15: KZKD00000832 | C15: 1950000 | D15: 1950000000 | E15: 8.07 | F15: 45491 | G15: 29.01.2035 | H15: 1449433375 | I15: =VLOOKUP(B15,'KASE за 05.12.25'!$C$5:$F$183,4,0) -> 62.936 | J15: =VLOOKUP(B15,'KASE за 05.12.25'!$C$5:$G$183,5,0) -> 69.7955 | K15: 134197375 | L15: =D15*I15/100+K15 -> 1361449375 | M15: =L15/$L$63 -> 0.049425258 | N15: =D15*E15%/360 -> 437125 | O15: =K15+N15 -> 134634500
A16: Министерство Финансов Республики Казахстан купонные МЕУКАМ | B16: KZKD00000550 | C16: =312000-1 -> 311999 | D16: =C16*1000 -> 311999000 | E16: 5.5 | F16: 45509 | G16: 48328 | H16: 2.0448962e+08 | I16: =VLOOKUP(B16,'KASE за 05.12.25'!$C$5:$F$183,4,0) -> 59.1959 | J16: =VLOOKUP(B16,'KASE за 05.12.25'!$C$5:$G$183,5,0) -> 62.5723 | K16: 10581966 | L16: =D16*I16/100+K16 -> 1.9527258e+08 | M16: =L16/$L$63 -> 0.007089061 | N16: =D16*E16%/360 -> 47666.514 | O16: =K16+N16 -> 10629633
A17: Министерство Финансов Республики Казахстан купонные МЕУКАМ | B17: KZKD00000550 | C17: 500000 | D17: 500000000 | E17: 5.5 | F17: 45532 | G17: 48328 | H17: 3.2653072e+08 | I17: =VLOOKUP(B17,'KASE за 05.12.25'!$C$5:$F$183,4,0) -> 59.1959 | J17: =VLOOKUP(B17,'KASE за 05.12.25'!$C$5:$G$183,5,0) -> 62.5723 | K17: 16958333 | L17: =D17*I17/100+K17 -> 3.1293783e+08 | M17: =L17/$L$63 -> 0.011360711 | N17: =D17*E17%/360 -> 76388.889 | O17: =K17+N17 -> 17034722
A18: Министерство Финансов Республики Казахстан купонные МЕУКАМ | B18: KZKD00000550 | C18: 500000 | D18: 500000000 | E18: 5.5 | F18: 45566 | G18: 48328 | H18: 3.3409056e+08 | I18: =VLOOKUP(B18,'KASE за 05.12.25'!$C$5:$F$183,4,0) -> 59.1959 | J18: =VLOOKUP(B18,'KASE за 05.12.25'!$C$5:$G$183,5,0) -> 62.5723 | K18: 16958333 | L18: =D18*I18/100+K18 -> 3.1293783e+08 | M18: =L18/$L$63 -> 0.011360711 | N18: =D18*E18%/360 -> 76388.889 | O18: =K18+N18 -> 17034722
A19: Министерство Финансов Республики Казахстан купонные МЕУКАМ | B19: KZKD00000550 | C19: 300000 | D19: =C19*1000 -> 300000000 | E19: 5.5 | F19: 45649 | G19: 48328 | H19: 2.0566557e+08 | I19: =VLOOKUP(B19,'KASE за 05.12.25'!$C$5:$F$183,4,0) -> 59.1959 | J19: =VLOOKUP(B19,'KASE за 05.12.25'!$C$5:$G$183,5,0) -> 62.5723 | K19: 10175000 | L19: =D19*I19/100+K19 -> 187762700 | M19: =L19/$L$63 -> 0.0068164267 | N19: =D19*E19%/360 -> 45833.333 | O19: =K19+N19 -> 10220833
A20: Министерство Финансов Республики Казахстан купонные МЕУКАМ | B20: KZKD00000550 | C20: 300000 | D20: =C20*1000 -> 300000000 | E20: 5.5 | F20: 45677 | G20: 48328 | H20: 2.0236587e+08 | I20: =VLOOKUP(B20,'KASE за 05.12.25'!$C$5:$F$183,4,0) -> 59.1959 | J20: =VLOOKUP(B20,'KASE за 05.12.25'!$C$5:$G$183,5,0) -> 62.5723 | K20: 10175000 | L20: =D20*I20/100+K20 -> 187762700 | M20: =L20/$L$63 -> 0.0068164267 | N20: =D20*E20%/360 -> 45833.333 | O20: =K20+N20 -> 10220833
A21: Министерство Финансов Республики Казахстан купонные МЕУКАМ | B21: KZKD00001160 | C21: 500000 | D21: =C21*1000 -> 500000000 | E21: 10.55 | F21: 45512 | G21: 28.07.2029 | H21: 4.5194078e+08 | I21: =VLOOKUP(B21,'KASE за 05.12.25'!$C$5:$F$162,4,0) -> 84.1157 | J21: =VLOOKUP(B21,'KASE за 05.12.25'!$C$5:$G$162,5,0) -> 87.8375 | K21: 18755556 | L21: =D21*I21/100+K21 -> 4.3933406e+08 | M21: =L21/$L$63 -> 0.015949325 | N21: =D21*E21%/360 -> 146527.78 | O21: =K21+N21 -> 18902083
A22: Министерство Финансов Республики Казахстан купонные МЕУКАМ | B22: KZKD00001160 | C22: 553430 | D22: =C22*1000 -> 553430000 | E22: 10.55 | F22: 45512 | G22: 28.07.2029 | H22: 4.9999941e+08 | I22: =VLOOKUP(B22,'KASE за 05.12.25'!$C$5:$F$162,4,0) -> 84.1157 | J22: =VLOOKUP(B22,'KASE за 05.12.25'!$C$5:$G$162,5,0) -> 87.8375 | K22: 20759774 | L22: =D22*I22/100+K22 -> 4.8628129e+08 | M22: =L22/$L$63 -> 0.01765367 | N22: =D22*E22%/360 -> 162185.74 | O22: =K22+N22 -> 20921960
A23: Министерство Финансов Республики Казахстан МЕУКАМ | B23: KZKD00000543 | C23: 636055 | D23: =C23*1000 -> 636055000 | E23: 5 | F23: 45519 | G23: 46861 | H23: 4.9999966e+08 | I23: =VLOOKUP(B23,'KASE за 05.12.25'!$C$5:$F$176,4,0) -> 78.0547 | J23: =VLOOKUP(B23,'KASE за 05.12.25'!$C$5:$G$176,5,0) -> 81.2075 | K23: 20141742 | L23: =D23*I23/100+K23 -> 5.1661256e+08 | M23: =L23/$L$63 -> 0.018754799 | N23: =D23*E23%/360 -> 88340.972 | O23: =K23+N23 -> 20230083
A24: Министерство Финансов Республики Казахстан купонные МЕУКАМ | B24: KZKD00000774 | C24: =715927-16841 -> 699086 | D24: =C24*1000 -> 699086000 | E24: 8.35 | F24: 45526 | G24: 50976 | H24: 4.8823782e+08 | I24: =VLOOKUP(B24,'KASE за 05.12.25'!$C$5:$F$192,4,0) -> 58.5918 | J24: =VLOOKUP(B24,'KASE за 05.12.25'!$C$5:$G$192,5,0) -> 61.6071 | K24: 21241534 | L24: =D24*I24/100+K24 -> 4.308486e+08 | M24: =L24/$L$63 -> 0.015641275 | N24: =D24*E24%/360 -> 162149.11 | O24: =K24+N24 -> 21403683
A25: Министерство Финансов Республики Казахстан купонные МЕУКАМ | B25: KZKD00000774 | C25: 284073 | D25: =C25*1000 -> 284073000 | E25: 8.35 | F25: 45617 | G25: 50976 | H25: 2.0393645e+08 | I25: =VLOOKUP(B25,'KASE за 05.12.25'!$C$5:$F$192,4,0) -> 58.5918 | J25: =VLOOKUP(B25,'KASE за 05.12.25'!$C$5:$G$192,5,0) -> 61.6071 | K25: 8631479.2 | L25: =D25*I25/100+K25 -> 1.7507496e+08 | M25: =L25/$L$63 -> 0.0063558186 | N25: =D25*E25%/360 -> 65889.154 | O25: =K25+N25 -> 8697368.4
A26: Министерство Финансов Республики Казахстан МЕУКАМ | B26: KZKD00000840 | C26: 500000 | D26: =C26*1000 -> 500000000 | E26: 7.68 | F26: 45526 | G26: 47518 | H26: 417099000 | I26: =VLOOKUP(B26,'KASE за 05.12.25'!$C$5:$F$176,4,0) -> 74.6678 | J26: =VLOOKUP(B26,'KASE за 05.12.25'!$C$5:$G$176,5,0) -> 81.0891 | K26: 32213333 | L26: =D26*I26/100+K26 -> 4.0555233e+08 | M26: =L26/$L$63 -> 0.014722934 | N26: =D26*E26%/360 -> 106666.67 | O26: =K26+N26 -> 32320000
A27: Министерство Финансов Республики Казахстан МЕУКАМ | B27: KZKD00000840 | C27: 500000 | D27: =C27*1000 -> 500000000 | E27: 7.68 | F27: 45527 | G27: 47518 | H27: 4.1494417e+08 | I27: =VLOOKUP(B27,'KASE за 05.12.25'!$C$5:$F$176,4,0) -> 74.6678 | J27: =VLOOKUP(B27,'KASE за 05.12.25'!$C$5:$G$176,5,0) -> 81.0891 | K27: 32213333 | L27: =D27*I27/100+K27 -> 4.0555233e+08 | M27: =L27/$L$63 -> 0.014722934 | N27: =D27*E27%/360 -> 106666.67 | O27: =K27+N27 -> 32320000
A28: Министерство Финансов Республики Казахстан МЕУКАМ | B28: KZKD00000840 | C28: 500000 | D28: =C28*1000 -> 500000000 | E28: 7.68 | F28: 45561 | G28: 47518 | H28: 4.2179517e+08 | I28: =VLOOKUP(B28,'KASE за 05.12.25'!$C$5:$F$176,4,0) -> 74.6678 | J28: =VLOOKUP(B28,'KASE за 05.12.25'!$C$5:$G$176,5,0) -> 81.0891 | K28: 32213333 | L28: =D28*I28/100+K28 -> 4.0555233e+08 | M28: =L28/$L$63 -> 0.014722934 | N28: =D28*E28%/360 -> 106666.67 | O28: =K28+N28 -> 32320000
A29: Евразийский банк развития | B29: KZ2D00011863 | C29: 1700000 | D29: =C29*1000 -> 1700000000 | E29: 14.3 | F29: 45538 | G29: 46633 | H29: 1700000000 | I29: =VLOOKUP(B29,'Риск цены за 05.12.25'!$C$4:$G$963,4,0) -> 94.453082 | J29: =VLOOKUP(B29,'Риск цены за 05.12.25'!$C$4:$G$963,5,0) -> 98.107482 | K29: 62800833 | L29: =D29*I29/100+K29 -> 1.6685032e+09 | M29: =L29/$L$63 -> 0.06057236 | N29: =D29*E29%/360 -> 675277.78 | O29: =K29+N29 -> 63476111
A30: Министерство Финансов Республики Казахстан МЕУКАМ | B30: KZKD00001244 | C30: 500000 | D30: =C30*1000 -> 500000000 | E30: 12 | F30: 45540 | G30: 47901 | H30: 5.0216167e+08 | I30: =VLOOKUP(B30,'KASE за 05.12.25'!$C$5:$F$162,4,0) -> 85.1702 | J30: =VLOOKUP(B30,'KASE за 05.12.25'!$C$5:$G$162,5,0) -> 94.6035 | K30: 47333333 | L30: =D30*I30/100+K30 -> 4.7318433e+08 | M30: =L30/$L$63 -> 0.017178206 | N30: =D30*E30%/360 -> 166666.67 | O30: =K30+N30 -> 47500000
A31: Министерство Финансов Республики Казахстан МЕУКАМ | B31: KZKD00001251 | C31: 300000 | D31: =C31*1000 -> 300000000 | E31: 12 | F31: 45547 | G31: 47549 | H31: 302854400 | I31: =VLOOKUP(B31,'KASE за 05.12.25'!$C$5:$F$162,4,0) -> 86.743 | J31: =VLOOKUP(B31,'KASE за 05.12.25'!$C$5:$G$162,5,0) -> 95.6763 | K31: 26900000 | L31: =D31*I31/100+K31 -> 287129000 | M31: =L31/$L$63 -> 0.010423762 | N31: =D31*E31%/360 -> 100000 | O31: =K31+N31 -> 27000000
A32: Министерство Финансов Республики Казахстан МЕУКАМ | B32: KZKD00001251 | C32: 288579 | D32: =C32*1000 -> 288579000 | E32: 12 | F32: 45582 | G32: 47549 | H32: 2.9999932e+08 | I32: =VLOOKUP(B32,'KASE за 05.12.25'!$C$5:$F$162,4,0) -> 86.743 | J32: =VLOOKUP(B32,'KASE за 05.12.25'!$C$5:$G$162,5,0) -> 95.6763 | K32: 25875917 | L32: =D32*I32/100+K32 -> 2.76198e+08 | M32: =L32/$L$63 -> 0.01002693 | N32: =D32*E32%/360 -> 96193 | O32: =K32+N32 -> 25972110
A33: АО "Национальный управляющий холдинг "Байтерек" | B33: KZ2C00012698 | C33: 300000 | D33: =C33*1000 -> 300000000 | E33: 13.89 | F33: 45624 | G33: 46109 | H33: 300000000 | I33: =VLOOKUP(B33,'Риск цены за 05.12.25'!$C$4:$G$963,4,0) -> 98.582846 | J33: =VLOOKUP(B33,'Риск цены за 05.12.25'!$C$4:$G$963,5,0) -> 98.852946 | K33: 926000 | L33: =D33*I33/100+K33 -> 2.9667454e+08 | M33: =L33/$L$63 -> 0.010770298 | N33: =D33*E33%/360 -> 115750 | O33: =K33+N33 -> 1041750
A34: Министерство Финансов Республики Казахстан МЕУКАМ | B34: KZKD00000964 | C34: =220000-213000 -> 7000 | D34: =C34*1000 -> 7000000 | E34: 8.44 | F34: 45639 | G34: 47978 | H34: =182967986.67/220000000*D34 -> 5821708.7 | I34: =VLOOKUP(B34,'KASE за 05.12.25'!$C$5:$F$162,4,0) -> 72.8031 | J34: =VLOOKUP(B34,'KASE за 05.12.25'!$C$5:$G$162,5,0) -> 77.6092 | K34: 338068.89 | L34: =D34*I34/100+K34 -> 5434285.9 | M34: =L34/$L$63 -> 0.00019728312 | N34: =D34*E34%/360 -> 1641.1111 | O34: =K34+N34 -> 339710
A35: Министерство Финансов Республики Казахстан МЕУКАМ | B35: KZKD00001236 | C35: =173000-163000 -> 10000 | D35: =C35*1000 -> 10000000 | E35: 14 | F35: 45639 | G35: 48353 | H35: =188266096.67/173000000*D35 -> 10882433 | I35: =VLOOKUP(B35,'KASE за 05.12.25'!$C$5:$F$162,4,0) -> 91.0851 | J35: =VLOOKUP(B35,'KASE за 05.12.25'!$C$5:$G$162,5,0) -> 98.7073 | K35: 766111.11 | L35: =D35*I35/100+K35 -> 9874621.1 | M35: =L35/$L$63 -> 0.00035848244 | N35: =D35*E35%/360 -> 3888.8889 | O35: =K35+N35 -> 770000
A36: Министерство Финансов Республики Казахстан МЕУКАМ | B36: KZKD00001079 | C36: 300000 | D36: =C36*1000 -> 300000000 | E36: 8.7 | F36: 45651 | G36: 50082 | H36: 237511300 | I36: =VLOOKUP(B36,'KASE за 05.12.25'!$C$5:$F$183,4,0) -> 62.9495 | J36: =VLOOKUP(B36,'KASE за 05.12.25'!$C$5:$G$183,5,0) -> 70.0545 | K36: 21387500 | L36: =D36*I36/100+K36 -> 210236000 | M36: =L36/$L$63 -> 0.0076322842 | N36: =D36*E36%/360 -> 72500 | O36: =K36+N36 -> 21460000
A37: Министерство Финансов Республики Казахстан МЕУКАМ | B37: KZKD00001079 | C37: 200000 | D37: =C37*1000 -> 200000000 | E37: 8.7 | F37: 45680 | G37: 50082 | H37: 157353400 | I37: =VLOOKUP(B37,'KASE за 05.12.25'!$C$5:$F$183,4,0) -> 62.9495 | J37: =VLOOKUP(B37,'KASE за 05.12.25'!$C$5:$G$183,5,0) -> 70.0545 | K37: 14258333 | L37: =D37*I37/100+K37 -> 1.4015733e+08 | M37: =L37/$L$63 -> 0.0050881894 | N37: =D37*E37%/360 -> 48333.333 | O37: =K37+N37 -> 14306667
A38: Министерство Финансов Республики Казахстан МЕУКАМ | B38: KZKD00001202 | C38: 263000 | D38: =C38*1000 -> 263000000 | E38: 11 | F38: 45656 | G38: 47518 | H38: 2.6372196e+08 | I38: =VLOOKUP(B38,'KASE за 05.12.25'!$C$5:$F$162,4,0) -> 84.0377 | J38: =VLOOKUP(B38,'KASE за 05.12.25'!$C$5:$G$162,5,0) -> 93.2349 | K38: 24269056 | L38: =D38*I38/100+K38 -> 2.4528821e+08 | M38: =L38/$L$63 -> 0.0089047989 | N38: =D38*E38%/360 -> 80361.111 | O38: =K38+N38 -> 24349417
A39: Министерство Финансов Республики Казахстан МЕУКАМ | B39: KZKD00001210 | C39: 341000 | D39: =C39*1000 -> 341000000 | E39: 15.3 | F39: 45657 | G39: 47180 | H39: 396883762 | I39: =VLOOKUP(B39,'KASE за 05.12.25'!$C$5:$F$162,4,0) -> 96.3913 | J39: =VLOOKUP(B39,'KASE за 05.12.25'!$C$5:$G$162,5,0) -> 107.9513 | K39: 39564525 | L39: =D39*I39/100+K39 -> 368258858 | M39: =L39/$L$63 -> 0.013369053 | N39: =D39*E39%/360 -> 144925 | O39: =K39+N39 -> 39709450
A40: Министерство Финансов Республики Казахстан МЕУКАМ | B40: KZKD00001095 | C40: =214727-132000 -> 82727 | D40: =C40*1000 -> 82727000 | E40: 10.47 | F40: 45673 | G40: 47053 | H40: 77053072 | I40: =VLOOKUP(B40,'KASE за 05.12.25'!$C$5:$F$162,4,0) -> 86.2408 | J40: =VLOOKUP(B40,'KASE за 05.12.25'!$C$5:$G$162,5,0) -> 87.346 | K40: 938331 | L40: =D40*I40/100+K40 -> 72282758 | M40: =L40/$L$63 -> 0.0026241107 | N40: =D40*E40%/360 -> 24059.769 | O40: =K40+N40 -> 962390.77
A41: Министерство Финансов Республики Казахстан МЕУКАМ | B41: KZKD00000790 | C41: 227500 | D41: =C41*1000 -> 227500000 | E41: 7.68 | F41: 45702 | G41: 47343 | H41: 1.8902823e+08 | I41: =VLOOKUP(B41,'KASE за 05.12.25'!$C$5:$F$176,4,0) -> 76.593 | J41: =VLOOKUP(B41,'KASE за 05.12.25'!$C$5:$G$176,5,0) -> 78.9823 | K41: 5484266.7 | L41: =D41*I41/100+K41 -> 1.7973334e+08 | M41: =L41/$L$63 -> 0.0065249336 | N41: =D41*E41%/360 -> 48533.333 | O41: =K41+N41 -> 5532800
A42: Министерство Финансов Республики Казахстан | B42: KZKD00000717 | C42: 500000 | D42: =C42*1000 -> 500000000 | E42: 7.22 | F42: 45729 | G42: 47097 | H42: 3.9979333e+08 | I42: =VLOOKUP(B42,'KASE за 05.12.25'!$C$5:$F$176,4,0) -> 78.7057 | J42: =VLOOKUP(B42,'KASE за 05.12.25'!$C$5:$G$176,5,0) -> 85.8254 | K42: 35698889 | L42: =D42*I42/100+K42 -> 4.2922739e+08 | M42: =L42/$L$63 -> 0.015582419 | N42: =D42*E42%/360 -> 100277.78 | O42: =K42+N42 -> 35799167
A43: Министерство Финансов Республики Казахстан | B43: KZKD00001210 | C43: 259000 | D43: =C43*1000 -> 259000000 | E43: 15.3 | F43: 45750 | G43: 47180 | H43: 260647240 | I43: =VLOOKUP(B43,'KASE за 05.12.25'!$C$5:$F$162,4,0) -> 96.3913 | J43: =VLOOKUP(B43,'KASE за 05.12.25'!$C$5:$G$162,5,0) -> 107.9513 | K43: 30050475 | L43: =D43*I43/100+K43 -> 279703942 | M43: =L43/$L$63 -> 0.010154208 | N43: =D43*E43%/360 -> 110075 | O43: =K43+N43 -> 30160550
A44: АО "Национальный управляющий холдинг "Байтерек" | B44: KZ2C00012268 | C44: 200000 | D44: =C44*1000 -> 200000000 | E44: 16.7 | F44: 45757 | G44: 46122 | H44: 200000000 | I44: =VLOOKUP(B44,'Риск цены за 05.12.25'!$C$4:$G$963,4,0) -> 99.154777 | J44: =VLOOKUP(B44,'Риск цены за 05.12.25'!$C$4:$G$963,5,0) -> 101.70618 | K44: 5195555.6 | L44: =D44*I44/100+K44 -> 2.0350511e+08 | M44: =L44/$L$63 -> 0.0073879299 | N44: =D44*E44%/360 -> 92777.778 | O44: =K44+N44 -> 5288333.3
A45: Министерство Финансов Республики Казахстан | B45: KZKD00000477 | C45: 500000 | D45: =C45*1000 -> 500000000 | E45: 5.3 | F45: 45764 | G45: 46679 | H45: 4.1207678e+08 | I45: =VLOOKUP(B45,'KASE за 05.12.25'!$C$5:$F$176,4,0) -> 82.3082 | J45: =VLOOKUP(B45,'KASE за 05.12.25'!$C$5:$G$176,5,0) -> 82.9854 | K45: 3459722.2 | L45: =D45*I45/100+K45 -> 4.1500072e+08 | M45: =L45/$L$63 -> 0.015065942 | N45: =D45*E45%/360 -> 73611.111 | O45: =K45+N45 -> 3533333.3
A46: Министерство Финансов Республики Казахстан | B46: KZKD00001202 | C46: 737000 | D46: =C46*1000 -> 737000000 | E46: 11 | F46: 45771 | G46: 47518 | H46: 6.4967099e+08 | I46: =VLOOKUP(B46,'KASE за 05.12.25'!$C$5:$F$162,4,0) -> 84.0377 | J46: =VLOOKUP(B46,'KASE за 05.12.25'!$C$5:$G$162,5,0) -> 93.2349 | K46: 68008722 | L46: =D46*I46/100+K46 -> 6.8736657e+08 | M46: =L46/$L$63 -> 0.024953752 | N46: =D46*E46%/360 -> 225194.44 | O46: =K46+N46 -> 68233917
A47: Министерство Финансов Республики Казахстан | B47: KZKD00001129 | C47: 6000 | D47: =C47*1000 -> 6000000 | E47: 10.3 | F47: 45775 | G47: 47924 | H47: 4822485.3 | I47: =VLOOKUP(B47,'KASE за 05.12.25'!$C$5:$F$162,4,0) -> 79.4608 | J47: =VLOOKUP(B47,'KASE за 05.12.25'!$C$5:$G$162,5,0) -> 86.8425 | K47: 444616.67 | L47: =D47*I47/100+K47 -> 5212264.7 | M47: =L47/$L$63 -> 0.00018922299 | N47: =D47*E47%/360 -> 1716.6667 | O47: =K47+N47 -> 446333.33
A48: Министерство Финансов Республики Казахстан | B48: KZKD00001129 | C48: 6000 | D48: =C48*1000 -> 6000000 | E48: 10.3 | F48: 45775 | G48: 47924 | H48: 4841157.3 | I48: =VLOOKUP(B48,'KASE за 05.12.25'!$C$5:$F$162,4,0) -> 79.4608 | J48: =VLOOKUP(B48,'KASE за 05.12.25'!$C$5:$G$162,5,0) -> 86.8425 | K48: 444616.67 | L48: =D48*I48/100+K48 -> 5212264.7 | M48: =L48/$L$63 -> 0.00018922299 | N48: =D48*E48%/360 -> 1716.6667 | O48: =K48+N48 -> 446333.33
A49: АО "Банк Развития Казахстана" | B49: KZ2C00010106 | C49: 500000 | D49: =C49*1000 -> 500000000 | E49: 17 | F49: 45782 | G49: 46147 | H49: 500000000 | I49: 100 | J49: 100 | K49: 7319444.4 | L49: =D49*I49/100+K49 -> 5.0731944e+08 | M49: =L49/$L$63 -> 0.018417427 | N49: =D49*E49%/360 -> 236111.11 | O49: =K49+N49 -> 7555555.6
A50: Министерство Финансов Республики Казахстан | B50: KZKD00000964 | C50: 500000 | D50: =C50*1000 -> 500000000 | E50: 8.44 | F50: 45799 | G50: 47978 | H50: 3.7223717e+08 | I50: =VLOOKUP(B50,'KASE за 05.12.25'!$C$5:$F$165,4,0) -> 72.8031 | J50: =VLOOKUP(B50,'KASE за 05.12.25'!$C$5:$G$165,5,0) -> 77.6092 | K50: 24147778 | L50: =D50*I50/100+K50 -> 3.8816328e+08 | M50: =L50/$L$63 -> 0.014091651 | N50: =D50*E50%/360 -> 117222.22 | O50: =K50+N50 -> 24265000
A51: Министерство Финансов Республики Казахстан | B51: KZKD00000790 | C51: 500000 | D51: =C51*1000 -> 500000000 | E51: 7.68 | F51: 45813 | G51: 47343 | H51: 4.0360417e+08 | I51: =VLOOKUP(B51,'KASE за 05.12.25'!$C$5:$F$176,4,0) -> 76.593 | J51: =VLOOKUP(B51,'KASE за 05.12.25'!$C$5:$G$176,5,0) -> 78.9823 | K51: 12053333 | L51: =D51*I51/100+K51 -> 3.9501833e+08 | M51: =L51/$L$63 -> 0.014340513 | N51: =D51*E51%/360 -> 106666.67 | O51: =K51+N51 -> 12160000
A52: Министерство Финансов Республики Казахстан | B52: KZKD00000543 | C52: 500000 | D52: =C52*1000 -> 500000000 | E52: 5 | F52: 45813 | G52: 46861 | H52: 3.7940239e+08 | I52: =VLOOKUP(B52,'KASE за 05.12.25'!$C$5:$F$176,4,0) -> 78.0547 | J52: =VLOOKUP(B52,'KASE за 05.12.25'!$C$5:$G$176,5,0) -> 81.2075 | K52: 15833333 | L52: =D52*I52/100+K52 -> 4.0610683e+08 | M52: =L52/$L$63 -> 0.014743064 | N52: =D52*E52%/360 -> 69444.444 | O52: =K52+N52 -> 15902778
A53: Министерство Финансов Республики Казахстан | B53: KZKD00001160 | C53: 200000 | D53: =C53*1000 -> 200000000 | E53: 10.55 | F53: 45820 | G53: 47327 | H53: 1.8266529e+08 | I53: =VLOOKUP(B53,'KASE за 05.12.25'!$C$5:$F$165,4,0) -> 84.1157 | J53: =VLOOKUP(B53,'KASE за 05.12.25'!$C$5:$G$165,5,0) -> 87.8375 | K53: 7502222.2 | L53: =D53*I53/100+K53 -> 1.7573362e+08 | M53: =L53/$L$63 -> 0.0063797301 | N53: =D53*E53%/360 -> 58611.111 | O53: =K53+N53 -> 7560833.3
A54: Министерство Финансов Республики Казахстан | B54: KZKD00001251 | C54: 500000 | D54: =C54*1000 -> 500000000 | E54: 12 | F54: 45832 | G54: 47549 | H54: 4.4701683e+08 | I54: =VLOOKUP(B54,'KASE за 05.12.25'!$C$5:$F$165,4,0) -> 86.743 | J54: =VLOOKUP(B54,'KASE за 05.12.25'!$C$5:$G$165,5,0) -> 95.6763 | K54: 44833333 | L54: =D54*I54/100+K54 -> 4.7854833e+08 | M54: =L54/$L$63 -> 0.017372937 | N54: =D54*E54%/360 -> 166666.67 | O54: =K54+N54 -> 45000000
A55: Министерство Финансов Республики Казахстан | B55: KZKD00001251 | C55: 500000 | D55: =C55*1000 -> 500000000 | E55: 12 | F55: 45832 | G55: 47549 | H55: 4.4561733e+08 | I55: =VLOOKUP(B55,'KASE за 05.12.25'!$C$5:$F$165,4,0) -> 86.743 | J55: =VLOOKUP(B55,'KASE за 05.12.25'!$C$5:$G$165,5,0) -> 95.6763 | K55: 44833333 | L55: =D55*I55/100+K55 -> 4.7854833e+08 | M55: =L55/$L$63 -> 0.017372937 | N55: =D55*E55%/360 -> 166666.67 | O55: =K55+N55 -> 45000000
A56: Министерство Финансов Республики Казахстан | B56: KZKD00001251 | C56: 411421 | D56: =C56*1000 -> 411421000 | E56: 12 | F56: 45832 | G56: 47549 | H56: 3.6376844e+08 | I56: =VLOOKUP(B56,'KASE за 05.12.25'!$C$5:$F$165,4,0) -> 86.743 | J56: =VLOOKUP(B56,'KASE за 05.12.25'!$C$5:$G$165,5,0) -> 95.6763 | K56: 36890750 | L56: =D56*I56/100+K56 -> 3.9376967e+08 | M56: =L56/$L$63 -> 0.014295183 | N56: =D56*E56%/360 -> 137140.33 | O56: =K56+N56 -> 37027890
A57: Министерство Финансов Республики Казахстан | B57: KZKD00001301 | C57: =500000-271261 -> 228739 | D57: =C57*1000 -> 228739000 | E57: 14.45 | F57: 45848 | G57: 48735 | H57: 2.0742821e+08 | I57: =VLOOKUP(B57,'KASE за 05.12.25'!$C$5:$F$170,4,0) -> 92.4443 | J57: =VLOOKUP(B57,'KASE за 05.12.25'!$C$5:$G$170,5,0) -> 99.6693 | K57: 16618206 | L57: =D57*I57/100+K57 -> 2.2807437e+08 | M57: =L57/$L$63 -> 0.008279878 | N57: =D57*E57%/360 -> 91813.293 | O57: =K57+N57 -> 16710019
A58: Министерство Финансов Республики Казахстан | B58: KZKD00000964 | C58: 500000 | D58: =C58*1000 -> 500000000 | E58: 8.44 | F58: 45862 | G58: 47978 | H58: 3.5788194e+08 | I58: =VLOOKUP(B58,'KASE за 05.12.25'!$C$5:$F$170,4,0) -> 72.8031 | J58: =VLOOKUP(B58,'KASE за 05.12.25'!$C$5:$G$170,5,0) -> 77.6092 | K58: 24147778 | L58: =D58*I58/100+K58 -> 3.8816328e+08 | M58: =L58/$L$63 -> 0.014091651 | N58: =D58*E58%/360 -> 117222.22 | O58: =K58+N58 -> 24265000
A59: Министерство Финансов Республики Казахстан | B59: KZKD00001301 | C59: 500000 | D59: =C59*1000 -> 500000000 | E59: 14.45 | F59: 45883 | G59: 48735 | H59: 4.6018642e+08 | I59: =VLOOKUP(B59,'KASE за 05.12.25'!$C$5:$F$170,4,0) -> 92.4443 | J59: =VLOOKUP(B59,'KASE за 05.12.25'!$C$5:$G$170,5,0) -> 99.6693 | K59: 36325694 | L59: =D59*I59/100+K59 -> 4.9854719e+08 | M59: =L59/$L$63 -> 0.018098964 | N59: =D59*E59%/360 -> 200694.44 | O59: =K59+N59 -> 36526389
A60: Министерство Финансов Республики Казахстан | B60: KZKD00000774 | C60: 16841 | D60: =C60*1000 -> 16841000 | E60: 8.35 | F60: 45890 | G60: 50976 | H60: 9465392.4 | I60: =VLOOKUP(B60,'KASE за 05.12.25'!$C$5:$F$192,4,0) -> 58.5918 | J60: =VLOOKUP(B60,'KASE за 05.12.25'!$C$5:$G$192,5,0) -> 61.6071 | K60: 511709.11 | L60: =D60*I60/100+K60 -> 10379154 | M60: =L60/$L$63 -> 0.00037679871 | N60: =D60*E60%/360 -> 3906.1764 | O60: =K60+N60 -> 515615.28
A61: АО "Казахстанская Жилищная Компания" | B61: KZ2C00014744 | C61: 500000 | D61: =C61*1000 -> 500000000 | E61: 18.7 | F61: 45896 | G61: 46992 | H61: 500000000 | I61: =VLOOKUP(B61,'Риск цены за 05.12.25'!$C$4:$G$963,4,0) -> 97.325884 | J61: =VLOOKUP(B61,'Риск цены за 05.12.25'!$C$4:$G$963,5,0) -> 102.41648 | K61: 25712500 | L61: =D61*I61/100+K61 -> 5.1234192e+08 | M61: =L61/$L$63 -> 0.01859976 | N61: =D61*E61%/360 -> 259722.22 | O61: =K61+N61 -> 25972222
A62: Министерство Финансов Республики Казахстан | B62: KZKD00001160 | C62: 56500 | D62: =C62*1000 -> 56500000 | E62: 10.55 | F62: 45982 | G62: 47327 | H62: 48467241 | I62: =VLOOKUP(B62,'KASE за 05.12.25'!$C$5:$F$183,4,0) -> 84.1157 | J62: =VLOOKUP(B62,'KASE за 05.12.25'!$C$5:$G$183,5,0) -> 87.8375 | K62: 2119377.8 | L62: =D62*I62/100+K62 -> 49644748 | M62: =L62/$L$63 -> 0.0018022738 | N62: =D62*E62%/360 -> 16557.639 | O62: =K62+N62 -> 2135935.4
A63: ИТОГО | C63: =SUM(C6:C62) -> 32678300 | D63: =SUM(D6:D62) -> 32678300000 | H63: =SUM(H6:H62) -> 2.8108969e+10 | K63: =SUM(K6:K62) -> 1.7809481e+09 | L63: =SUM(L6:L62) -> 2.754562e+10 | M63: =SUM(M6:M62) -> 1 | N63: 2.754562e+10 | O63: =L63-N63 -> 0
A65: Остатки на инвест. cчетах
A66: KZT | B66: 198997.2 | C66: 198997.2 | D66: =B66-C66 -> 0
A68: Обратное репо
A69: Наименование эмитента и вид ЦБ | B69: НИН (ISIN) | C69: Количество | D69: Валюта | E69: Дата открытия | F69: Дата закрытия | G69: Цена открытия | H69: Цена закрытия | I69: Сумма открытия операции. в тг | J69: Сумма закрытия операции. в тг | K69: Ставка доходности. % | L69: Сумма начисленного вознагрждения | M69: Суммарная текущая стоимость. в тг
A70: АО "Казахстанский фонд устойчивости" | B70: KZ2C00011989 | C70: 71856 | D70: KZT | E70: 45996 | F70: 45999 | G70: 1002.904 | H70: 1004.3136 | I70: 72064670 | J70: 72165955 | K70: 17.1 | L70: =IF(($B$1-E70)=0,0,(J70-I70)/(F70-E70)*($B$1-E70)) -> 33761.803 | M70: =IF((F70=$B$1),0,(I70+L70)) -> 72098432
A71: Министерство Финансов Республики Казахстан | B71: XS1263139856 | C71: 158067 | D71: KZT | E71: 45996 | F71: 45999 | G71: 575.8379 | H71: 576.64723 | I71: 91020969 | J71: 91148897 | K71: 17.1 | L71: =IF(($B$1-E71)=0,0,(J71-I71)/(F71-E71)*($B$1-E71)) -> 42642.7 | M71: =IF((F71=$B$1),0,(I71+L71)) -> 91063612
A72: АО "Казахстанский фонд устойчивости" | B72: KZ2C00011989 | C72: 170658 | D72: KZT | E72: 45996 | F72: 45999 | G72: 1002.904 | H72: 1004.3136 | I72: 1.7115359e+08 | J72: 1.7139414e+08 | K72: 17.1 | L72: =IF(($B$1-E72)=0,0,(J72-I72)/(F72-E72)*($B$1-E72)) -> 80184.287 | M72: =IF((F72=$B$1),0,(I72+L72)) -> 1.7123378e+08
A73: АО "Казахстанский фонд устойчивости" | B73: KZ2C00011989 | C73: 291416 | D73: KZT | E73: 45996 | F73: 45999 | G73: 1002.904 | H73: 1004.3136 | I73: 2.9226227e+08 | J73: 2.9267304e+08 | K73: 17.1 | L73: =IF(($B$1-E73)=0,0,(J73-I73)/(F73-E73)*($B$1-E73)) -> 136922.87 | M73: =IF((F73=$B$1),0,(I73+L73)) -> 2.9239919e+08
A74: АО "Казахстанский фонд устойчивости" | B74: KZ2C00011989 | C74: 207584 | D74: KZT | E74: 45996 | F74: 45999 | G74: 1002.904 | H74: 1004.3136 | I74: 2.0818682e+08 | J74: 2.0847943e+08 | K74: 17.1 | L74: =IF(($B$1-E74)=0,0,(J74-I74)/(F74-E74)*($B$1-E74)) -> 97534.1 | M74: =IF((F74=$B$1),0,(I74+L74)) -> 2.0828436e+08
A75: Министерство Финансов Республики Казахстан | B75: KZK100000373 | C75: 6856093 | D75: KZT | E75: 45996 | F75: 45999 | G75: 97.2889 | H75: 97.425638 | I75: 6.6702175e+08 | J75: 6.6795923e+08 | K75: 17.1 | L75: =IF(($B$1-E75)=0,0,(J75-I75)/(F75-E75)*($B$1-E75)) -> 312495.12 | M75: =IF((F75=$B$1),0,(I75+L75)) -> 6.6733424e+08
A76: Министерство Финансов Республики Казахстан | B76: XS2914770545 | C76: 17955 | D76: KZT | E76: 45996 | F76: 45999 | G76: 501.3416 | H76: 502.04623 | I76: 9001588.4 | J76: 9014240.1 | K76: 17.100098 | L76: =IF(($B$1-E76)=0,0,(J76-I76)/(F76-E76)*($B$1-E76)) -> 4217.2067 | M76: =IF((F76=$B$1),0,(I76+L76)) -> 9005805.6
A78: ИТОГО | C78: =SUM(C70:C76) -> 7773629 | I78: =SUM(I70:I76) -> 1.5107117e+09 | J78: =SUM(J70:J76) -> 1.5128349e+09 | L78: =SUM(L70:L76) -> 707758.09 | M78: =SUM(M70:M76) -> 1.5114194e+09 | N78: 1.5114194e+09 | O78: =M78-N78 -> 0
A81: Прочие активы (дебиторская задолженность. деньги в пути)
A82: № п/п | B82: Наименование | C82: Валюта | D82: Дата постановки на учет | E82: Количество | F82: Остаток в валюте | G82: Остаток в тенге
A83: 1 | B83: KZ2C00012698 | C83: KZT | D83: 45989 | E83: 300000 | F83: 20835000 | G83: 20835000 | H83: 20835000 | I83: =G83-H83 -> 0
A84: ИТОГО | G84: =SUM(G83:G83) -> 20835000
A86: Итого активов | B86: =L63+B66+M78+G84 -> 2.9078073e+10 | C86: 2.9078073e+10 | D86: =B86-C86 -> 0
A90: 2) Кредиторская задолженность Фонда
A91: Комиссия ДУ (за управление) | B91: 4030988.5
A92: Комиссия ДУ (сверхдоходность)
A93: Комиссия Кастоди | B93: =3000+3000+4000+2000+5000+2000+3000+2000+2000+2000+2000+3000+2000+3000+3000+2000+4000+5000+8000+2000+360738.18+3000+2000+2000+2000+7000 -> 438738.18
A94: Комиссия Глобал кастоди
A95: Комиссия Центрального Депозитария | B95: 370131.49
A96: Клиринговый сбор | B96: =2265.92+2268.65+2332.23+2331.42+6921.84+2335.92+2338.46+2339.56+2339.53+6945.87+2343.36+2361.9+2347.47+2346.57+9173.89+2279.02+2280.32+2281.66+2283.42+6772.91+2325.69+2286.36+2289.27+2291.14+6798.2 -> 82880.58
A97: Комиссия биржи | B97: =1120.05+1120.68+1153.21+1153.55+3459.26+1155.8+1156.32+1156.88+1157.6+3472.94+1159.53+1160.39+1160.82+1161.12+8221.98+1126.6+1127.25+1127.93+1128.81+3386.45+1131.03+1131.02+1131.73+1131.91+3399.11 -> 44791.97
A98: Комиссия брокера
A99: Кредиторская задолженность (прочая комиссия)
A100: Остаток прочих обязательств на конец дня
A101: Итого | B101: =SUM(B91:B100) -> 4967530.7

Sheet KASE за 05.12.25
A1: Дата оценки | B1: 45996
A3: № п/п | B3: Код | C3: ISIN | D3: Вид ценной бумаги | E3: Компания | F3: Рыночная цена | G3: Рыночная "грязная" цена | H3: Доходность до погашения. % годовых | I3: Срок до погашения | J3: Единица измерения цены
A5: 1 | B5: 1AIRA | C5: KZ1C00004050 | D5: акции | E5: Эйр Астана | F5: 866.71 | G5: – | H5: – | I5: – | J5: KZT
A6: 2 | B6: 2AIRAd | C6: US0090632078 | D6: производные ЦБ | E6: Эйр Астана | F6: 6.85 | G6: – | H6: – | I6: – | J6: USD
A7: 3 | B7: 3AKZM | C7: KZ1C00001288 | D7: акции | E7: Актюбинский завод металлоконструкций | F7: 6301.35 | G7: – | H7: – | I7: – | J7: KZT
A8: 4 | B8: 4ALMSb1 | C8: KZ2C00012953 | D8: долговые ЦБ | E8: АК Алтыналмас | F8: 100.0172 | G8: 101.5505 | H8: 7,99 | I8: 741 (2) | J8: %
A9: 5 | B9: 5ASKQb1 | C9: KZ2C00010155 | D9: долговые ЦБ | E9: ALTYN SAMRUK QAZAQSTAN | F9: 95.0863 | G9: 95.1863 | H9: 14,51 | I9: 356 (1) | J9: %
A10: 6 | B10: 6BCCI_cc | C10: KZPF00000058 | D10: ЦБ инвест. фондов | E10: BCC Invest | F10: 131.19 | G10: – | H10: – | I10: – | J10: USD
A11: 7 | B11: 7BCCIbe | C11: KZPF00000553 | D11: ЦБ инвест. фондов | E11: BCC Invest | F11: 1526.49 | G11: – | H11: – | I11: – | J11: KZT
A12: 8 | B12: 8BCCIrb | C12: KZPF00000231 | D12: ЦБ инвест. фондов | E12: BCC Invest | F12: 7.21 | G12: – | H12: – | I12: – | J12: KZT
A13: 9 | B13: 9BIGDb1 | C13: KZ2D00012457 | D13: долговые ЦБ | E13: Частная компания BI Development Ltd. | F13: 98.5507 | G13: 100.2278 | H13: 19,00 | I13: 326 (1) | J13: %
A14: 10 | B14: 10BIGDb5 | C14: KZ2D00012861 | D14: долговые ЦБ | E14: Частная компания BI Development Ltd. | F14: 99.9979 | G14: 100.3229 | H14: 19,49 | I14: 534 (1) | J14: %
A15: 11 | B15: 11BIGDb6 | C15: KZ2D00015328 | D15: долговые ЦБ | E15: Частная компания BI Development Ltd. | F15: 101.2288 | G15: 105.6135 | H15: 19,57 | I15: 643 (2) | J15: %
A16: 12 | B16: 12BRKZe12 | C16: XS2337670694 | D16: долговые ЦБ | E16: Банк Развития Казахстана | F16: 87.2323 | G16: 87.4699 | H16: 5,72 | I16: 1 951 (5) | J16: %
A17: 13 | B17: 13BRKZe16 | C17: XS2917067204 | D17: долговые ЦБ | E17: Банк Развития Казахстана | F17: 100.1744 | G17: 100.7869 | H17: 5,20 | I17: 1 398 (4) | J17: %
A18: 14 | B18: 14BRKZe18 | C18: XS3032932645 | D18: долговые ЦБ | E18: Банк Развития Казахстана | F18: 103.487 | G18: 104.3933 | H18: 4,73 | I18: 1 562 (4) | J18: %
A19: 15 | B19: 15BRKZe21 | C19: HK0001185674 | D19: долговые ЦБ | E19: Банк Развития Казахстана | F19: 100.7085 | G19: 101.5804 | H19: 3,07 | I19: 1 001 (3) | J19: %
A20: 16 | B20: 16BRKZe22 | C20: XS3204113354 | D20: долговые ЦБ | E20: Банк Развития Казахстана | F20: 99.0544 | G20: 99.6805 | H20: 4,81 | I20: 1 856 (5) | J20: %
A21: 17 | B21: 17BRKZe4 | C21: XS0248160102 | D21: долговые ЦБ | E21: Банк Развития Казахстана | F21: 100.1597 | G21: 101.3597 | H21: 5,42 | I21: 108 (0) | J21: %
A22: 18 | B22: 18BTRKe1 | C22: XS3067899610 | D22: долговые ЦБ | E22: Национальный управляющий холдинг "Байтерек" | F22: 102.0035 | G22: 102.4123 | H22: 4,57 | I22: 873 (2) | J22: %
A23: 19 | B23: 19BTRKe2 | C23: XS3189694345 | D23: долговые ЦБ | E23: Национальный управляющий холдинг "Байтерек" | F23: 101.0923 | G23: 101.919 | H23: 4,40 | I23: 1 736 (5) | J23: %
A24: 20 | B24: 20CCBN | C24: KZ0007786572 | D24: акции | E24: Банк ЦентрКредит | F24: 4583.81 | G24: – | H24: – | I24: – | J24: KZT
A25: 21 | B25: 21CCBNp | C25: KZ000A0H0930 | D25: акции | E25: Банк ЦентрКредит | F25: 8952.3 | G25: – | H25: – | I25: – | J25: KZT
A26: 22 | B26: 22CLSGb3 | C26: KZ2P00010192 | D26: долговые ЦБ | E26: Capital Leasing Group (Капитал Лизинг Груп) | F26: 98.1249 | G26: 100.2152 | H26: 23,82 | I26: 326 (1) | J26: %
A27: 23 | B27: 23CSECfe | C27: KZPF00000025 | D27: ЦБ инвест. фондов | E27: Сентрас Секьюритиз | F27: 5800671.4 | G27: – | H27: – | I27: – | J27: KZT
A28: 24 | B28: 24CSECtf | C28: KZPF00000280 | D28: ЦБ инвест. фондов | E28: Сентрас Секьюритиз | F28: 1851562.3 | G28: – | H28: – | I28: – | J28: KZT
A29: 25 | B29: 25EABRb40 | C29: KZ2D00009628 | D29: ЦБ МФО | E29: Евразийский банк развития | F29: 99.9106 | G29: 101.1023 | H29: 6,00 | I29: 105 (0) | J29: %
A30: 26 | B30: 26EABRb42 | C30: KZ2D00009222 | D30: ЦБ МФО | E30: Евразийский банк развития | F30: 100 | G30: 105.3096 | H30: 18,94 | I30: 812 (2) | J30: %
A31: 27 | B31: 27EABRb53 | C31: KZ2D00013620 | D31: ЦБ МФО | E31: Евразийский банк развития | F31: 100 | G31: 103.5918 | H31: 18,94 | I31: 843 (2) | J31: %
A32: 28 | B32: 28FFIN_or | C32: KZPF00000082 | D32: ЦБ инвест. фондов | E32: Фридом Финанс | F32: 168.28 | G32: – | H32: – | I32: – | J32: USD
A33: 29 | B33: 29FFINgw | C33: KZPF00000090 | D33: ЦБ инвест. фондов | E33: Фридом Финанс | F33: 5617.35 | G33: – | H33: – | I33: – | J33: KZT
A34: 30 | B34: 30FHJIag | C34: KZPF00000132 | D34: ЦБ инвест. фондов | E34: Alatau City Invest | F34: 1087.37 | G34: – | H34: – | I34: – | J34: USD
A35: 31 | B35: 31FPSTb5 | C35: KZ2P00011778 | D35: долговые ЦБ | E35: BASS Gold | F35: 99.9403 | G35: 102.7209 | H35: 11,03 | I35: 269 (1) | J35: %
A36: 32 | B36: 32FPSTb6 | C36: KZ2P00013592 | D36: долговые ЦБ | E36: BASS Gold | F36: 98 | G36: 100.2917 | H36: 18,13 | I36: 105 (0) | J36: %
A37: 33 | B37: 33HCBNb11 | C37: KZ2C00009926 | D37: долговые ЦБ | E37: Home Credit Bank | F37: 96.858 | G37: 102.2205 | H37: 17,99 | I37: 963 (3) | J37: %
A38: 34 | B38: 34HCBNb13 | C38: KZ2C00011195 | D38: долговые ЦБ | E38: Home Credit Bank | F38: 96.7041 | G38: 101.6449 | H38: 19,99 | I38: 802 (2) | J38: %
A39: 35 | B39: 35HCBNb15 | C39: KZ2C00011401 | D39: долговые ЦБ | E39: Home Credit Bank | F39: 98.0534 | G39: 105.2409 | H39: 17,99 | I39: 1 290 (4) | J39: %
A40: 36 | B40: 36HCBNb17 | C40: KZ2C00014066 | D40: долговые ЦБ | E40: Home Credit Bank | F40: 102.5654 | G40: 110.0462 | H40: 18,23 | I40: 1 659 (5) | J40: %
A41: 37 | B41: 37HCBNb19 | C41: KZ2C00014124 | D41: долговые ЦБ | E41: Home Credit Bank | F41: 100.5282 | G41: 108.6025 | H41: 18,80 | I41: 569 (2) | J41: %
A42: 38 | B42: 38HFINhl | C42: KZPF00000538 | D42: ЦБ инвест. фондов | E42: Halyk Finance | F42: 50885.07 | G42: – | H42: – | I42: – | J42: KZT
A43: 39 | B43: 39HFINhp | C43: KZPF00000546 | D43: ЦБ инвест. фондов | E43: Halyk Finance | F43: 71918.8 | G43: – | H43: – | I43: – | J43: KZT
A44: 40 | B44: 40HFINhs | C44: KZPF00000520 | D44: ЦБ инвест. фондов | E44: Halyk Finance | F44: 71307.85 | G44: – | H44: – | I44: – | J44: KZT
A45: 41 | B45: 41HFINhv | C45: KZPF00000041 | D45: ЦБ инвест. фондов | E45: Halyk Finance | F45: 562842.19 | G45: – | H45: – | I45: – | J45: KZT
A46: 42 | B46: 42HSBK | C46: KZ000A0LE0S4 | D46: акции | E46: Народный Банк Казахстана | F46: 322.39 | G46: – | H46: – | I46: – | J46: KZT
A47: 43 | B47: 43HSBKb22 | C47: KZ2C00012482 | D47: долговые ЦБ | E47: Народный Банк Казахстана | F47: 100.0169 | G47: 100.1189 | H47: 18,61 | I47: 728 (2) | J47: %
A48: 44 | B48: 44HSBKd | C48: US46627J3023 | D48: производные ЦБ | E48: Народный Банк Казахстана | F48: 25.39 | G48: – | H48: – | I48: – | J48: USD
A49: 45 | B49: 45IDFRb4 | C49: KZ2C00008217 | D49: долговые ЦБ | E49: Фонд развития промышленности | F49: 87.641 | G49: 88.4332 | H49: 17,99 | I49: 1 057 (3) | J49: %
A50: 46 | B50: 46IFDR | C50: KZ1C00000256 | D50: акции | E50: Teniz Capital Investment Banking | F50: 9490.25 | G50: – | H50: – | I50: – | J50: KZT
A51: 47 | B51: 47KAFIb16 | C51: KZ2C00015535 | D51: долговые ЦБ | E51: КазАгроФинанс | F51: 101.0608 | G51: 104.1219 | H51: 18,63 | I51: 1 742 (5) | J51: %
A52: 48 | B52: 48KAFIb17 | C52: KZ2C00015543 | D52: долговые ЦБ | E52: КазАгроФинанс | F52: 101.0608 | G52: 104.1219 | H52: 18,63 | I52: 1 742 (5) | J52: %
A53: 49 | B53: 49KASAb1 | C53: KZ2C00013753 | D53: долговые ЦБ | E53: Казахстанский электролизный завод | F53: 101.0107 | G53: 101.101 | H53: 6,06 | I53: 895 (2) | J53: %
A54: 50 | B54: 50KCEL | C54: KZ1C00000876 | D54: акции | E54: Kcell | F54: 3358.25 | G54: – | H54: – | I54: – | J54: KZT
A55: 51 | B55: 51KEGC | C55: KZ1C00000959 | D55: акции | E55: KEGOC | F55: 1398.4 | G55: – | H55: – | I55: – | J55: KZT
A56: 52 | B56: 52KFUSb48 | C56: KZ2C00008944 | D56: долговые ЦБ | E56: Казахстанский фонд устойчивости | F56: 103.9129 | G56: 111.2666 | H56: 18,04 | I56: 1 507 (4) | J56: %
A57: 53 | B57: 53KFUSb49 | C57: KZ2C00008951 | D57: долговые ЦБ | E57: Казахстанский фонд устойчивости | F57: 104.9709 | G57: 105.5134 | H57: 17,99 | I57: 1 451 (4) | J57: %
A58: 54 | B58: 54KMGZ | C58: KZ1C00001122 | D58: акции | E58: Национальная компания "КазМунайГаз" | F58: 21879.44 | G58: – | H58: – | I58: – | J58: KZT
A59: 55 | B59: 55KMGZe14 | C59: XS1807300105 | D59: долговые ЦБ | E59: Национальная компания "КазМунайГаз" | F59: 100.949 | G59: 101.5612 | H59: 5,13 | I59: 1 579 (4) | J59: %
A60: 56 | B60: 56KMGZe16 | C60: XS2242422397 | D60: долговые ЦБ | E60: Национальная компания "КазМунайГаз" | F60: 90.5923 | G60: 91.0881 | H60: 5,05 | I60: 2 649 (7) | J60: %
A61: 57 | B61: 57KSPI | C61: KZ1C00001536 | D61: акции | E61: Kaspi.kz | F61: 40060.69 | G61: – | H61: – | I61: – | J61: KZT
A62: 58 | B62: 58KSPId | C62: US48581R2058 | D62: производные ЦБ | E62: Kaspi.kz | F62: 77.88 | G62: – | H62: – | I62: – | J62: USD
A63: 59 | B63: 59KZAP | C63: KZ1C00001619 | D63: акции | E63: Национальная атомная компания "Казатомпром" | F63: 28693.83 | G63: – | H63: – | I63: – | J63: KZT
A64: 60 | B64: 60KZTCb3 | C64: KZ2C00012961 | D64: долговые ЦБ | E64: Jusan Mobile | F64: 106.2139 | G64: 110.9806 | H64: 18,48 | I64: 822 (2) | J64: %
A65: 61 | B65: 61KZTK | C65: KZ0009093241 | D65: акции | E65: Казахтелеком | F65: 40411.4 | G65: – | H65: – | I65: – | J65: KZT
A66: 62 | B66: 62KZTKp | C66: KZ0009094645 | D66: акции | E66: Казахтелеком | F66: 27652.79 | G66: – | H66: – | I66: – | J66: KZT
A67: 63 | B67: 63KZTO | C67: KZ1C00000744 | D67: акции | E67: КазТрансОйл | F67: 851.16 | G67: – | H67: – | I67: – | J67: KZT
A68: 64 | B68: 64KZ_23_3504 | C68: XS2914770545 | D68: ГЦБ | E68: Минфин | F68: 98.625 | G68: 99.3583 | H68: 4,90 | I68: 3 364 (9) | J68: %
A69: 65 | B69: 65MFMCb2 | C69: KZ2P00011968 | D69: долговые ЦБ | E69: МФО MyCar Finance | F69: 98.7191 | G69: 99.7399 | H69: 19,00 | I69: 339 (1) | J69: %
A70: 66 | B70: 66MFMOb15 | C70: KZ2P00013295 | D70: долговые ЦБ | E70: МФО "Mogo Kazakhstan (Мого Казахстан) | F70: 99.1328 | G70: 100.1717 | H70: 23,02 | I70: 343 (1) | J70: %
A71: 67 | B71: 67MFMOb23 | C71: KZ2P00013154 | D71: долговые ЦБ | E71: МФО "Mogo Kazakhstan (Мого Казахстан) | F71: 99.4554 | G71: 100.6165 | H71: 22,44 | I71: 521 (1) | J71: %
A72: 68 | B72: 68MFMOb24 | C72: KZ2P00013212 | D72: долговые ЦБ | E72: МФО "Mogo Kazakhstan (Мого Казахстан) | F72: 98.6749 | G72: 98.8582 | H72: 23,01 | I72: 567 (2) | J72: %
A73: 69 | B73: 69MFMOb25 | C73: KZ2P00013220 | D73: долговые ЦБ | E73: МФО "Mogo Kazakhstan (Мого Казахстан) | F73: 99.2594 | G73: 100.7261 | H73: 22,53 | I73: 606 (2) | J73: %
A74: 70 | B74: 70MFMOb29 | C74: KZ2P00014459 | D74: долговые ЦБ | E74: МФО "Mogo Kazakhstan (Мого Казахстан) | F74: 99.9425 | G74: 101.7147 | H74: 22,04 | I74: 661 (2) | J74: %
A75: 71 | B75: 71MFMOb33 | C75: KZ2P00014608 | D75: долговые ЦБ | E75: МФО "Mogo Kazakhstan (Мого Казахстан) | F75: 100 | G75: 100.4889 | H75: 11,00 | I75: 704 (2) | J75: %
A76: 72 | B76: 72MFOKb18 | C76: KZ2C00010478 | D76: долговые ЦБ | E76: МФО ОнлайнКазФинанс | F76: 99.4266 | G76: 99.9266 | H76: 21,53 | I76: 141 (0) | J76: %
A77: 73 | B77: 73MFOKb19 | C77: KZ2C00010825 | D77: долговые ЦБ | E77: МФО ОнлайнКазФинанс | F77: 98.6629 | G77: 99.1351 | H77: 11,12 | I77: 463 (1) | J77: %
A78: 74 | B78: 74MFOKb20 | C78: KZ2C00010916 | D78: долговые ЦБ | E78: МФО ОнлайнКазФинанс | F78: 100 | G78: 101.2194 | H78: 21,95 | I78: 610 (2) | J78: %
A79: 75 | B79: 75MFOKb21 | C79: KZ2C00011906 | D79: долговые ЦБ | E79: МФО ОнлайнКазФинанс | F79: 96.0719 | G79: 96.4413 | H79: 21,29 | I79: 773 (2) | J79: %
... A192: 188 | B192: 188UZPAb1 | C192: KZ2C00013811 | D192: долговые ЦБ | E192: Усть-Каменогорский завод промышленной арматуры | F192: 96.4857 | G192: 96.5454 | H192: 23,40 | I192: 899 (2) | J192: %

Sheet Риск цены за 05.12.25
A1: Дата оценки | B1: 45996
A3: № п/п | B3: Торговый код | C3: ISIN | D3: Алгоритмы и параметры расчета ЦБ | E3: Краткое наименование эмитента | F3: Расчетная цена | G3: Расчетная грязная | H3: Доходность до погашения. % годовых | I3: Дней до погашения | J3: Единица измерения цены
A4: 1 | B4: AAFD | C4: KZ1C00008721 | D4: Акции | E4: АО "АзияАгроФуд" | F4: 100 | G4: 100 | H4: 0 | I4: 0 | J4: KZT
A5: 2 | B5: AAL_KZ | C5: US02376R1023 | D5: Акции | E5: American Airlines | F5: 7369.8291 | G5: 7369.8291 | H5: 0 | I5: 0 | J5: KZT
A6: 3 | B6: AAPL_KZ | C6: US0378331005 | D6: Акции | E6: Apple Inc. | F6: 143480.81 | G6: 143480.81 | H6: 0 | I6: 0 | J6: KZT
A7: 4 | B7: ABK022_210 | C7: KZMJ00002103 | D7: Облигации | E7: Акимат Актюбинской области | F7: 100 | G7: 100.2479 | H7: 4.24 | I7: 279 | J7: %
A8: 5 | B8: ABK024_183 | C8: KZMJ00001832 | D8: Облигации | E8: Акимат Актюбинской области | F8: 100 | G8: 100.0068 | H8: 0.35 | I8: 173 | J8: %
A9: 6 | B9: ABK114_193 | C9: KZMJ00001931 | D9: Облигации | E9: Акимат Актюбинской области | F9: 100 | G9: 100.0038 | H9: 0.02 | I9: 2995 | J9: %
A10: 7 | B10: ABK119_006 | C10: KZMF00000069 | D10: Облигации | E10: Акимат Актюбинской области | F10: 100 | G10: 102.7111 | H10: 6.08 | I10: 1610 | J10: %
A11: 8 | B11: ABK119_081 | C11: KZMF00000812 | D11: Облигации | E11: Акимат Актюбинской области | F11: 100 | G11: 100.7494 | H11: 7.08 | I11: 2092 | J11: %
A12: 9 | B12: ABK120_283 | C12: KZMJ00002830 | D12: Облигации | E12: Акимат Актюбинской области | F12: 96.661159 | G12: 98.498659 | H12: 19.66 | I12: 3565 | J12: %
A13: 10 | B13: ABK131_021 | C13: KZMF00000218 | D13: Облигации | E13: Акимат Актюбинской области | F13: 100 | G13: 101.8808 | H13: 6.08 | I13: 2019 | J13: %
A14: 11 | B14: ABK143_032 | C14: KZMF00000325 | D14: Облигации | E14: Акимат Актюбинской области | F14: 100 | G14: 100.7286 | H14: 6.09 | I14: 2447 | J14: %
A15: 12 | B15: ABK143_033 | C15: KZMF00000333 | D15: Облигации | E15: Акимат Актюбинской области | F15: 100 | G15: 100.7286 | H15: 6.09 | I15: 2447 | J15: %
... A1085: 1082 | B1085: ZKK180_259 | C1085: KZMJ00002590 | D1085: Облигации | E1085: Акимат Западно-Казахстанской области | F1085: 96.458098 | G1085: 101.2881 | H1085: 19.58 | I1085: 5308 | J1085: %
