Workbook

Sheet ДУ
A1: Сентрас Секьюритиз | B1: 45946
A2: 1) Активы
A4: ЦБ
A5: Наименование эмитента и вид ЦБ | B5: ISIN | C5: Количество ЦБ | D5: Номинальная стоимость. тенге | E5: Ставка | F5: Дата зачисления/приобретения | G5: Дата погашения | H5: Чистая покупная стоимоcть | I5: Расчетная цена на 16.10.25 | J5: Расчетная грязная цена 16.10.25 | K5: Накопленный купон | L5: Суммарно-текущая рыночная стоимость | M5: Вес
A6: Министерство Финансов Республики Казахстан купонные МЕУКАМ | B6: KZKD00000535 | C6: =3250000-500000-500000-500000 -> 1750000 | D6: =3250000000-500000000-500000000-500000000 -> 1750000000 | E6: 5.49 | F6: 45491 | G6: 27.03.2027 | H6: =2755458875/3250000000*D6 -> 1483708625 | I6: =VLOOKUP(B6,'KASE за 16.10.25'!$C$5:$F$162,4,0) -> 86.2007 | J6: =VLOOKUP(B6,'KASE за 16.10.25'!$C$5:$G$162,5,0) -> 89.2355 | K6: 53108125 | L6: =D6*I6/100+K6 -> 1561620375 | M6: =L6/$L$62 -> 0.05885997 | N6: =D6*E6%/360 -> 266875 | O6: =K6+N6 -> 53375000
A7: Министерство Финансов Республики Казахстан купонные МЕУКАМ | B7: KZKD00001137 | C7: 1950000 | D7: 1950000000 | E7: 10.4 | F7: 45491 | G7: 12.04.2028 | H7: 1838876000 | I7: =VLOOKUP(B7,'KASE за 16.10.25'!$C$5:$F$162,4,0) -> 87.2293 | J7: =VLOOKUP(B7,'KASE за 16.10.25'!$C$5:$G$162,5,0) -> 92.5449 | K7: 1.0365333e+08 | L7: =D7*I7/100+K7 -> 1.8046247e+09 | M7: =L7/$L$62 -> 0.068019192 | N7: =D7*E7%/360 -> 563333.33 | O7: =K7+N7 -> 1.0421667e+08
A8: Министерство Финансов Республики Казахстан МЕУКАМ | B8: KZKD00001087 | C8: =1950000-202300-182000-187350 -> 1378350 | D8: =C8*1000 -> 1378350000 | E8: 11 | F8: 45491 | G8: 31.03.2029 | H8: =1855844250/1950000000*D8 -> 1.3117964e+09 | I8: =VLOOKUP(B8,'KASE за 16.10.25'!$C$5:$F$162,4,0) -> 84.9553 | J8: =VLOOKUP(B8,'KASE за 16.10.25'!$C$5:$G$162,5,0) -> 90.9442 | K8: 82547850 | L8: =D8*I8/100+K8 -> 1.2535292e+09 | M8: =L8/$L$62 -> 0.047247522 | N8: =D8*E8%/360 -> 421162.5 | O8: =K8+N8 -> 82969012
A9: Министерство Финансов Республики Казахстан купонные МЕУКАМ | B9: KZKD00001160 | C9: =1950000-225000-225000-208000-225000-225000 -> 842000 | D9: =C9*1000 -> 842000000 | E9: 10.55 | F9: 45491 | G9: 28.07.2029 | H9: =1504310166.66923/1500000000*D9 -> 8.4441944e+08 | I9: =VLOOKUP(B9,'KASE за 16.10.25'!$C$5:$F$162,4,0) -> 82.8274 | J9: =VLOOKUP(B9,'KASE за 16.10.25'!$C$5:$G$162,5,0) -> 85.1132 | K9: 19246717 | L9: =D9*I9/100+K9 -> 7.1665342e+08 | M9: =L9/$L$62 -> 0.027011814 | N9: =D9*E9%/360 -> 246752.78 | O9: =K9+N9 -> 19493469
A10: Министерство Финансов Республики Казахстан купонные МЕУКАМ | B10: KZKD00001129 | C10: 1450000 | D10: 1450000000 | E10: 10.3 | F10: 45491 | G10: 17.03.2031 | H10: 1.307499e+09 | I10: =VLOOKUP(B10,'KASE за 16.10.25'!$C$5:$F$162,4,0) -> 77.1189 | J10: =VLOOKUP(B10,'KASE за 16.10.25'!$C$5:$G$162,5,0) -> 83.0986 | K10: 86705972 | L10: =D10*I10/100+K10 -> 1.20493e+09 | M10: =L10/$L$62 -> 0.04541574 | N10: =D10*E10%/360 -> 414861.11 | O10: =K10+N10 -> 87120833
A11: Министерство Финансов Республики Казахстан МЕУКАМ | B11: KZKD00000949 | C11: 1950000 | D11: 1950000000 | E11: 8.45 | F11: 45491 | G11: 16.04.2032 | H11: 1.5403351e+09 | I11: =VLOOKUP(B11,'KASE за 16.10.25'!$C$5:$F$162,4,0) -> 67.4955 | J11: =VLOOKUP(B11,'KASE за 16.10.25'!$C$5:$G$162,5,0) -> 71.7205 | K11: 82387500 | L11: =D11*I11/100+K11 -> 1.3985498e+09 | M11: =L11/$L$62 -> 0.052713578 | N11: =D11*E11%/360 -> 457708.33 | O11: =K11+N11 -> 82845208
A12: Министерство Финансов Республики Казахстан Купонные Облигации | B12: KZKD00001152 | C12: =1950000-250000-250000-250000-218000 -> 982000 | D12: =C12*1000 -> 982000000 | E12: 10.65 | F12: 45491 | G12: 26.07.2032 | H12: =1897171250/1950000000*D12 -> 9.5539598e+08 | I12: =VLOOKUP(B12,'KASE за 16.10.25'!$C$5:$F$162,4,0) -> 75.2202 | J12: =VLOOKUP(B12,'KASE за 16.10.25'!$C$5:$G$162,5,0) -> 77.5869 | K12: 23240667 | L12: =D12*I12/100+K12 -> 7.6190303e+08 | M12: =L12/$L$62 -> 0.028717344 | N12: =D12*E12%/360 -> 290508.33 | O12: =K12+N12 -> 23531175
A13: Министерство Финансов Республики Казахстан Купонные Облигации | B13: KZKD00001152 | C13: 250000 | D13: =C13*1000 -> 250000000 | E13: 10.65 | F13: 45673 | G13: 26.07.2032 | H13: =227969916.67/250000000*D13 -> 2.2796992e+08 | I13: =VLOOKUP(B13,'KASE за 16.10.25'!$C$5:$F$162,4,0) -> 75.2202 | J13: =VLOOKUP(B13,'KASE за 16.10.25'!$C$5:$G$162,5,0) -> 77.5869 | K13: 5916666.7 | L13: =D13*I13/100+K13 -> 1.9396717e+08 | M13: =L13/$L$62 -> 0.0073109328 | N13: =D13*E13%/360 -> 73958.333 | O13: =K13+N13 -> 5990625
A14: Министерство Финансов Республики Казахстан купонные МЕУКАМ | B14: KZKD00000741 | C14: 1950000 | D14: 1950000000 | E14: 8.07 | F14: 45491 | G14: 12.05.2034 | H14: 1425576750 | I14: =VLOOKUP(B14,'KASE за 16.10.25'!$C$5:$F$177,4,0) -> 60.7893 | J14: =VLOOKUP(B14,'KASE за 16.10.25'!$C$5:$G$177,5,0) -> 64.2415 | K14: 67317250 | L14: =D14*I14/100+K14 -> 1252708600 | M14: =L14/$L$62 -> 0.047216591 | N14: =D14*E14%/360 -> 437125 | O14: =K14+N14 -> 67754375
A15: Министерство Финансов Республики Казахстан купонные МЕУКАМ | B15: KZKD00000832 | C15: 1950000 | D15: 1950000000 | E15: 8.07 | F15: 45491 | G15: 29.01.2035 | H15: 1449433375 | I15: =VLOOKUP(B15,'KASE за 16.10.25'!$C$5:$F$177,4,0) -> 59.3166 | J15: =VLOOKUP(B15,'KASE за 16.10.25'!$C$5:$G$177,5,0) -> 65.0777 | K15: 112341125 | L15: =D15*I15/100+K15 -> 1269014825 | M15: =L15/$L$62 -> 0.047831199 | N15: =D15*E15%/360 -> 437125 | O15: =K15+N15 -> 112778250
A16: Министерство Финансов Республики Казахстан купонные МЕУКАМ | B16: KZKD00000550 | C16: =312000-1 -> 311999 | D16: =C16*1000 -> 311999000 | E16: 5.5 | F16: 45509 | G16: 48328 | H16: 2.0448962e+08 | I16: =VLOOKUP(B16,'KASE за 16.10.25'!$C$5:$F$177,4,0) -> 56.3819 | J16: =VLOOKUP(B16,'KASE за 16.10.25'!$C$5:$G$177,5,0) -> 59.0097 | K16: 8198640.4 | L16: =D16*I16/100+K16 -> 1.841096e+08 | M16: =L16/$L$62 -> 0.0069393856 | N16: =D16*E16%/360 -> 47666.514 | O16: =K16+N16 -> 8246306.9
A17: Министерство Финансов Республики Казахстан купонные МЕУКАМ | B17: KZKD00000550 | C17: 500000 | D17: 500000000 | E17: 5.5 | F17: 45532 | G17: 48328 | H17: 3.2653072e+08 | I17: =VLOOKUP(B17,'KASE за 16.10.25'!$C$5:$F$177,4,0) -> 56.3819 | J17: =VLOOKUP(B17,'KASE за 16.10.25'!$C$5:$G$177,5,0) -> 59.0097 | K17: 13138889 | L17: =D17*I17/100+K17 -> 2.9504839e+08 | M17: =L17/$L$62 -> 0.011120846 | N17: =D17*E17%/360 -> 76388.889 | O17: =K17+N17 -> 13215278
A18: Министерство Финансов Республики Казахстан купонные МЕУКАМ | B18: KZKD00000550 | C18: 500000 | D18: 500000000 | E18: 5.5 | F18: 45566 | G18: 48328 | H18: 3.3409056e+08 | I18: =VLOOKUP(B18,'KASE за 16.10.25'!$C$5:$F$177,4,0) -> 56.3819 | J18: =VLOOKUP(B18,'KASE за 16.10.25'!$C$5:$G$177,5,0) -> 59.0097 | K18: 13138889 | L18: =D18*I18/100+K18 -> 2.9504839e+08 | M18: =L18/$L$62 -> 0.011120846 | N18: =D18*E18%/360 -> 76388.889 | O18: =K18+N18 -> 13215278
A19: Министерство Финансов Республики Казахстан купонные МЕУКАМ | B19: KZKD00000550 | C19: 300000 | D19: =C19*1000 -> 300000000 | E19: 5.5 | F19: 45649 | G19: 48328 | H19: 2.0566557e+08 | I19: =VLOOKUP(B19,'KASE за 16.10.25'!$C$5:$F$177,4,0) -> 56.3819 | J19: =VLOOKUP(B19,'KASE за 16.10.25'!$C$5:$G$177,5,0) -> 59.0097 | K19: 7883333.3 | L19: =D19*I19/100+K19 -> 1.7702903e+08 | M19: =L19/$L$62 -> 0.0066725075 | N19: =D19*E19%/360 -> 45833.333 | O19: =K19+N19 -> 7929166.7
A20: Министерство Финансов Республики Казахстан купонные МЕУКАМ | B20: KZKD00000550 | C20: 300000 | D20: =C20*1000 -> 300000000 | E20: 5.5 | F20: 45677 | G20: 48328 | H20: 2.0236587e+08 | I20: =VLOOKUP(B20,'KASE за 16.10.25'!$C$5:$F$177,4,0) -> 56.3819 | J20: =VLOOKUP(B20,'KASE за 16.10.25'!$C$5:$G$177,5,0) -> 59.0097 | K20: 7883333.3 | L20: =D20*I20/100+K20 -> 1.7702903e+08 | M20: =L20/$L$62 -> 0.0066725075 | N20: =D20*E20%/360 -> 45833.333 | O20: =K20+N20 -> 7929166.7
A21: Министерство Финансов Республики Казахстан купонные МЕУКАМ | B21: KZKD00001160 | C21: 500000 | D21: =C21*1000 -> 500000000 | E21: 10.55 | F21: 45512 | G21: 28.07.2029 | H21: 4.5194078e+08 | I21: =VLOOKUP(B21,'KASE за 16.10.25'!$C$5:$F$162,4,0) -> 82.8274 | J21: =VLOOKUP(B21,'KASE за 16.10.25'!$C$5:$G$162,5,0) -> 85.1132 | K21: 11429167 | L21: =D21*I21/100+K21 -> 4.2556617e+08 | M21: =L21/$L$62 -> 0.01604027 | N21: =D21*E21%/360 -> 146527.78 | O21: =K21+N21 -> 11575694
A22: Министерство Финансов Республики Казахстан купонные МЕУКАМ | B22: KZKD00001160 | C22: 553430 | D22: =C22*1000 -> 553430000 | E22: 10.55 | F22: 45512 | G22: 28.07.2029 | H22: 4.9999941e+08 | I22: =VLOOKUP(B22,'KASE за 16.10.25'!$C$5:$F$162,4,0) -> 82.8274 | J22: =VLOOKUP(B22,'KASE за 16.10.25'!$C$5:$G$162,5,0) -> 85.1132 | K22: 12650487 | L22: =D22*I22/100+K22 -> 4.7104217e+08 | M22: =L22/$L$62 -> 0.017754333 | N22: =D22*E22%/360 -> 162185.74 | O22: =K22+N22 -> 12812673
A23: Министерство Финансов Республики Казахстан МЕУКАМ | B23: KZKD00000543 | C23: 636055 | D23: =C23*1000 -> 636055000 | E23: 5 | F23: 45519 | G23: 46861 | H23: 4.9999966e+08 | I23: =VLOOKUP(B23,'KASE за 16.10.25'!$C$5:$F$170,4,0) -> 76.9359 | J23: =VLOOKUP(B23,'KASE за 16.10.25'!$C$5:$G$170,5,0) -> 79.4081 | K23: 15724693 | L23: =D23*I23/100+K23 -> 5.0507933e+08 | M23: =L23/$L$62 -> 0.019037248 | N23: =D23*E23%/360 -> 88340.972 | O23: =K23+N23 -> 15813034
A24: Министерство Финансов Республики Казахстан купонные МЕУКАМ | B24: KZKD00000774 | C24: =715927-16841 -> 699086 | D24: =C24*1000 -> 699086000 | E24: 8.35 | F24: 45526 | G24: 50976 | H24: 4.8823782e+08 | I24: =VLOOKUP(B24,'KASE за 16.10.25'!$C$5:$F$177,4,0) -> 54.6101 | J24: =VLOOKUP(B24,'KASE за 16.10.25'!$C$5:$G$177,5,0) -> 56.4889 | K24: 13134078 | L24: =D24*I24/100+K24 -> 3.9490564e+08 | M24: =L24/$L$62 -> 0.014884625 | N24: =D24*E24%/360 -> 162149.11 | O24: =K24+N24 -> 13296227
A25: Министерство Финансов Республики Казахстан купонные МЕУКАМ | B25: KZKD00000774 | C25: 284073 | D25: =C25*1000 -> 284073000 | E25: 8.35 | F25: 45617 | G25: 50976 | H25: 2.0393645e+08 | I25: =VLOOKUP(B25,'KASE за 16.10.25'!$C$5:$F$177,4,0) -> 54.6101 | J25: =VLOOKUP(B25,'KASE за 16.10.25'!$C$5:$G$177,5,0) -> 56.4889 | K25: 5337021.5 | L25: =D25*I25/100+K25 -> 1.6046957e+08 | M25: =L25/$L$62 -> 0.0060483549 | N25: =D25*E25%/360 -> 65889.154 | O25: =K25+N25 -> 5402910.6
A26: Министерство Финансов Республики Казахстан МЕУКАМ | B26: KZKD00000840 | C26: 500000 | D26: =C26*1000 -> 500000000 | E26: 7.68 | F26: 45526 | G26: 47518 | H26: 417099000 | I26: =VLOOKUP(B26,'KASE за 16.10.25'!$C$5:$F$177,4,0) -> 72.8163 | J26: =VLOOKUP(B26,'KASE за 16.10.25'!$C$5:$G$177,5,0) -> 78.1923 | K26: 26880000 | L26: =D26*I26/100+K26 -> 3.909615e+08 | M26: =L26/$L$62 -> 0.014735964 | N26: =D26*E26%/360 -> 106666.67 | O26: =K26+N26 -> 26986667
A27: Министерство Финансов Республики Казахстан МЕУКАМ | B27: KZKD00000840 | C27: 500000 | D27: =C27*1000 -> 500000000 | E27: 7.68 | F27: 45527 | G27: 47518 | H27: 4.1494417e+08 | I27: =VLOOKUP(B27,'KASE за 16.10.25'!$C$5:$F$177,4,0) -> 72.8163 | J27: =VLOOKUP(B27,'KASE за 16.10.25'!$C$5:$G$177,5,0) -> 78.1923 | K27: 26880000 | L27: =D27*I27/100+K27 -> 3.909615e+08 | M27: =L27/$L$62 -> 0.014735964 | N27: =D27*E27%/360 -> 106666.67 | O27: =K27+N27 -> 26986667
A28: Министерство Финансов Республики Казахстан МЕУКАМ | B28: KZKD00000840 | C28: 500000 | D28: =C28*1000 -> 500000000 | E28: 7.68 | F28: 45561 | G28: 47518 | H28: 4.2179517e+08 | I28: =VLOOKUP(B28,'KASE за 16.10.25'!$C$5:$F$177,4,0) -> 72.8163 | J28: =VLOOKUP(B28,'KASE за 16.10.25'!$C$5:$G$177,5,0) -> 78.1923 | K28: 26880000 | L28: =D28*I28/100+K28 -> 3.909615e+08 | M28: =L28/$L$62 -> 0.014735964 | N28: =D28*E28%/360 -> 106666.67 | O28: =K28+N28 -> 26986667
A29: Евразийский банк развития | B29: KZ2D00011863 | C29: 1700000 | D29: =C29*1000 -> 1700000000 | E29: 14.3 | F29: 45538 | G29: 46633 | H29: 1700000000 | I29: =VLOOKUP(B29,'Риск цены за 16.10.25'!$C$4:$G$963,4,0) -> 94.637105 | J29: =VLOOKUP(B29,'Риск цены за 16.10.25'!$C$4:$G$963,5,0) -> 96.345205 | K29: 29036944 | L29: =D29*I29/100+K29 -> 1.6378677e+09 | M29: =L29/$L$62 -> 0.061733855 | N29: =D29*E29%/360 -> 675277.78 | O29: =K29+N29 -> 29712222
A30: Министерство Финансов Республики Казахстан МЕУКАМ | B30: KZKD00001244 | C30: 500000 | D30: =C30*1000 -> 500000000 | E30: 12 | F30: 45540 | G30: 47901 | H30: 5.0216167e+08 | I30: =VLOOKUP(B30,'KASE за 16.10.25'!$C$5:$F$162,4,0) -> 82.8811 | J30: =VLOOKUP(B30,'KASE за 16.10.25'!$C$5:$G$162,5,0) -> 90.6811 | K30: 39000000 | L30: =D30*I30/100+K30 -> 4.534055e+08 | M30: =L30/$L$62 -> 0.017089579 | N30: =D30*E30%/360 -> 166666.67 | O30: =K30+N30 -> 39166667
A31: Министерство Финансов Республики Казахстан МЕУКАМ | B31: KZKD00001251 | C31: 300000 | D31: =C31*1000 -> 300000000 | E31: 12 | F31: 45547 | G31: 47549 | H31: 302854400 | I31: =VLOOKUP(B31,'KASE за 16.10.25'!$C$5:$F$162,4,0) -> 85.0565 | J31: =VLOOKUP(B31,'KASE за 16.10.25'!$C$5:$G$162,5,0) -> 92.3565 | K31: 21900000 | L31: =D31*I31/100+K31 -> 277069500 | M31: =L31/$L$62 -> 0.010443193 | N31: =D31*E31%/360 -> 100000 | O31: =K31+N31 -> 22000000
A32: Министерство Финансов Республики Казахстан МЕУКАМ | B32: KZKD00001251 | C32: 288579 | D32: =C32*1000 -> 288579000 | E32: 12 | F32: 45582 | G32: 47549 | H32: 2.9999932e+08 | I32: =VLOOKUP(B32,'KASE за 16.10.25'!$C$5:$F$162,4,0) -> 85.0565 | J32: =VLOOKUP(B32,'KASE за 16.10.25'!$C$5:$G$162,5,0) -> 92.3565 | K32: 21066267 | L32: =D32*I32/100+K32 -> 2.6652146e+08 | M32: =L32/$L$62 -> 0.01004562 | N32: =D32*E32%/360 -> 96193 | O32: =K32+N32 -> 21162460
A33: АО "Национальный управляющий холдинг "Байтерек" | B33: KZ2C00012698 | C33: 300000 | D33: =C33*1000 -> 300000000 | E33: 13.89 | F33: 45624 | G33: 46109 | H33: 300000000 | I33: =VLOOKUP(B33,'Риск цены за 16.10.25'!$C$4:$G$963,4,0) -> 98.483593 | J33: =VLOOKUP(B33,'Риск цены за 16.10.25'!$C$4:$G$963,5,0) -> 103.80809 | K33: 15973500 | L33: =D33*I33/100+K33 -> 3.1142428e+08 | M33: =L33/$L$62 -> 0.011738079 | N33: =D33*E33%/360 -> 115750 | O33: =K33+N33 -> 16089250
A34: Министерство Финансов Республики Казахстан МЕУКАМ | B34: KZKD00000964 | C34: =220000-213000 -> 7000 | D34: =C34*1000 -> 7000000 | E34: 8.44 | F34: 45639 | G34: 47978 | H34: =182967986.67/220000000*D34 -> 5821708.7 | I34: =VLOOKUP(B34,'KASE за 16.10.25'!$C$5:$F$162,4,0) -> 70.382 | J34: =VLOOKUP(B34,'KASE за 16.10.25'!$C$5:$G$162,5,0) -> 74.0393 | K34: 256013.33 | L34: =D34*I34/100+K34 -> 5182753.3 | M34: =L34/$L$62 -> 0.00019534627 | N34: =D34*E34%/360 -> 1641.1111 | O34: =K34+N34 -> 257654.44
A35: Министерство Финансов Республики Казахстан МЕУКАМ | B35: KZKD00001236 | C35: =173000-163000 -> 10000 | D35: =C35*1000 -> 10000000 | E35: 14 | F35: 45639 | G35: 48353 | H35: =188266096.67/173000000*D35 -> 10882433 | I35: =VLOOKUP(B35,'KASE за 16.10.25'!$C$5:$F$162,4,0) -> 88.1849 | J35: =VLOOKUP(B35,'KASE за 16.10.25'!$C$5:$G$162,5,0) -> 93.9016 | K35: 571666.67 | L35: =D35*I35/100+K35 -> 9390156.7 | M35: =L35/$L$62 -> 0.00035393003 | N35: =D35*E35%/360 -> 3888.8889 | O35: =K35+N35 -> 575555.56
A36: Министерство Финансов Республики Казахстан МЕУКАМ | B36: KZKD00001079 | C36: 300000 | D36: =C36*1000 -> 300000000 | E36: 8.7 | F36: 45651 | G36: 50082 | H36: 237511300 | I36: =VLOOKUP(B36,'KASE за 16.10.25'!$C$5:$F$177,4,0) -> 58.9811 | J36: =VLOOKUP(B36,'KASE за 16.10.25'!$C$5:$G$177,5,0) -> 64.9019 | K36: 17762500 | L36: =D36*I36/100+K36 -> 194705800 | M36: =L36/$L$62 -> 0.0073387731 | N36: =D36*E36%/360 -> 72500 | O36: =K36+N36 -> 17835000
A37: Министерство Финансов Республики Казахстан МЕУКАМ | B37: KZKD00001079 | C37: 200000 | D37: =C37*1000 -> 200000000 | E37: 8.7 | F37: 45680 | G37: 50082 | H37: 157353400 | I37: =VLOOKUP(B37,'KASE за 16.10.25'!$C$5:$F$177,4,0) -> 58.9811 | J37: =VLOOKUP(B37,'KASE за 16.10.25'!$C$5:$G$177,5,0) -> 64.9019 | K37: 11841667 | L37: =D37*I37/100+K37 -> 1.2980387e+08 | M37: =L37/$L$62 -> 0.0048925154 | N37: =D37*E37%/360 -> 48333.333 | O37: =K37+N37 -> 11890000
A38: Министерство Финансов Республики Казахстан МЕУКАМ | B38: KZKD00001202 | C38: 263000 | D38: =C38*1000 -> 263000000 | E38: 11 | F38: 45656 | G38: 47518 | H38: 2.6372196e+08 | I38: =VLOOKUP(B38,'KASE за 16.10.25'!$C$5:$F$162,4,0) -> 82.3369 | J38: =VLOOKUP(B38,'KASE за 16.10.25'!$C$5:$G$162,5,0) -> 90.0369 | K38: 20251000 | L38: =D38*I38/100+K38 -> 2.3679705e+08 | M38: =L38/$L$62 -> 0.0089252596 | N38: =D38*E38%/360 -> 80361.111 | O38: =K38+N38 -> 20331361
A39: Министерство Финансов Республики Казахстан МЕУКАМ | B39: KZKD00001210 | C39: 341000 | D39: =C39*1000 -> 341000000 | E39: 15.3 | F39: 45657 | G39: 47180 | H39: 396883762 | I39: =VLOOKUP(B39,'KASE за 16.10.25'!$C$5:$F$162,4,0) -> 95.5757 | J39: =VLOOKUP(B39,'KASE за 16.10.25'!$C$5:$G$162,5,0) -> 105.0532 | K39: 32318275 | L39: =D39*I39/100+K39 -> 358231412 | M39: =L39/$L$62 -> 0.013502315 | N39: =D39*E39%/360 -> 144925 | O39: =K39+N39 -> 32463200
A40: Министерство Финансов Республики Казахстан МЕУКАМ | B40: KZKD00001095 | C40: =214727-132000 -> 82727 | D40: =C40*1000 -> 82727000 | E40: 10.47 | F40: 45673 | G40: 47053 | H40: 77053072 | I40: =VLOOKUP(B40,'KASE за 16.10.25'!$C$5:$F$162,4,0) -> 85.3947 | J40: =VLOOKUP(B40,'KASE за 16.10.25'!$C$5:$G$162,5,0) -> 95.5448 | K40: 8396859.4 | L40: =D40*I40/100+K40 -> 79041333 | M40: =L40/$L$62 -> 0.0029791943 | N40: =D40*E40%/360 -> 24059.769 | O40: =K40+N40 -> 8420919.2
A41: Министерство Финансов Республики Казахстан МЕУКАМ | B41: KZKD00000790 | C41: 227500 | D41: =C41*1000 -> 227500000 | E41: 7.68 | F41: 45702 | G41: 47343 | H41: 1.8902823e+08 | I41: =VLOOKUP(B41,'KASE за 16.10.25'!$C$5:$F$177,4,0) -> 75.0924 | J41: =VLOOKUP(B41,'KASE за 16.10.25'!$C$5:$G$177,5,0) -> 76.4364 | K41: 3057600 | L41: =D41*I41/100+K41 -> 173892810 | M41: =L41/$L$62 -> 0.0065542982 | N41: =D41*E41%/360 -> 48533.333 | O41: =K41+N41 -> 3106133.3
A42: Министерство Финансов Республики Казахстан | B42: KZKD00000717 | C42: 500000 | D42: =C42*1000 -> 500000000 | E42: 7.22 | F42: 45729 | G42: 47097 | H42: 3.9979333e+08 | I42: =VLOOKUP(B42,'KASE за 16.10.25'!$C$5:$F$162,4,0) -> 77.4245 | J42: =VLOOKUP(B42,'KASE за 16.10.25'!$C$5:$G$162,5,0) -> 83.5615 | K42: 30685000 | L42: =D42*I42/100+K42 -> 4.178075e+08 | M42: =L42/$L$62 -> 0.015747833 | N42: =D42*E42%/360 -> 100277.78 | O42: =K42+N42 -> 30785278
A43: Министерство Финансов Республики Казахстан | B43: KZKD00001210 | C43: 259000 | D43: =C43*1000 -> 259000000 | E43: 15.3 | F43: 45750 | G43: 47180 | H43: 260647240 | I43: =VLOOKUP(B43,'KASE за 16.10.25'!$C$5:$F$162,4,0) -> 95.5757 | J43: =VLOOKUP(B43,'KASE за 16.10.25'!$C$5:$G$162,5,0) -> 105.0532 | K43: 24546725 | L43: =D43*I43/100+K43 -> 272087788 | M43: =L43/$L$62 -> 0.010255424 | N43: =D43*E43%/360 -> 110075 | O43: =K43+N43 -> 24656800
A44: АО "Национальный управляющий холдинг "Байтерек" | B44: KZ2C00012268 | C44: 200000 | D44: =C44*1000 -> 200000000 | E44: 16.7 | F44: 45757 | G44: 46122 | H44: 200000000 | I44: =VLOOKUP(B44,'Риск цены за 16.10.25'!$C$4:$G$963,4,0) -> 99.577343 | J44: =VLOOKUP(B44,'Риск цены за 16.10.25'!$C$4:$G$963,5,0) -> 99.855643 | K44: 556666.67 | L44: =D44*I44/100+K44 -> 1.9971135e+08 | M44: =L44/$L$62 -> 0.0075274404 | N44: =D44*E44%/360 -> 92777.778 | O44: =K44+N44 -> 649444.44
A45: Министерство Финансов Республики Казахстан | B45: KZKD00000477 | C45: 500000 | D45: =C45*1000 -> 500000000 | E45: 5.3 | F45: 45764 | G45: 46679 | H45: 4.1207678e+08 | I45: =VLOOKUP(B45,'KASE за 16.10.25'!$C$5:$F$177,4,0) -> 81.4017 | J45: =VLOOKUP(B45,'KASE за 16.10.25'!$C$5:$G$177,5,0) -> 86.6575 | K45: 26279167 | L45: =D45*I45/100+K45 -> 4.3328767e+08 | M45: =L45/$L$62 -> 0.016331305 | N45: =D45*E45%/360 -> 73611.111 | O45: =K45+N45 -> 26352778
A46: Министерство Финансов Республики Казахстан | B46: KZKD00001202 | C46: 737000 | D46: =C46*1000 -> 737000000 | E46: 11 | F46: 45771 | G46: 47518 | H46: 6.4967099e+08 | I46: =VLOOKUP(B46,'KASE за 16.10.25'!$C$5:$F$162,4,0) -> 82.3369 | J46: =VLOOKUP(B46,'KASE за 16.10.25'!$C$5:$G$162,5,0) -> 90.0369 | K46: 56749000 | L46: =D46*I46/100+K46 -> 6.6357195e+08 | M46: =L46/$L$62 -> 0.025011089 | N46: =D46*E46%/360 -> 225194.44 | O46: =K46+N46 -> 56974194
A47: Министерство Финансов Республики Казахстан | B47: KZKD00001129 | C47: 6000 | D47: =C47*1000 -> 6000000 | E47: 10.3 | F47: 45775 | G47: 47924 | H47: 4822485.3 | I47: =VLOOKUP(B47,'KASE за 16.10.25'!$C$5:$F$162,4,0) -> 77.1189 | J47: =VLOOKUP(B47,'KASE за 16.10.25'!$C$5:$G$162,5,0) -> 83.0986 | K47: 358783.33 | L47: =D47*I47/100+K47 -> 4985917.3 | M47: =L47/$L$62 -> 0.0001879272 | N47: =D47*E47%/360 -> 1716.6667 | O47: =K47+N47 -> 360500
A48: Министерство Финансов Республики Казахстан | B48: KZKD00001129 | C48: 6000 | D48: =C48*1000 -> 6000000 | E48: 10.3 | F48: 45775 | G48: 47924 | H48: 4841157.3 | I48: =VLOOKUP(B48,'KASE за 16.10.25'!$C$5:$F$162,4,0) -> 77.1189 | J48: =VLOOKUP(B48,'KASE за 16.10.25'!$C$5:$G$162,5,0) -> 83.0986 | K48: 358783.33 | L48: =D48*I48/100+K48 -> 4985917.3 | M48: =L48/$L$62 -> 0.0001879272 | N48: =D48*E48%/360 -> 1716.6667 | O48: =K48+N48 -> 360500
A49: АО "Банк Развития Казахстана" | B49: KZ2C00010106 | C49: 500000 | D49: =C49*1000 -> 500000000 | E49: 17 | F49: 45782 | G49: 46147 | H49: 500000000 | I49: 100 | J49: 100 | K49: 38013889 | L49: =D49*I49/100+K49 -> 5.3801389e+08 | M49: =L49/$L$62 -> 0.020278604 | N49: =D49*E49%/360 -> 236111.11 | O49: =K49+N49 -> 38250000
A50: Министерство Финансов Республики Казахстан | B50: KZKD00000964 | C50: 500000 | D50: =C50*1000 -> 500000000 | E50: 8.44 | F50: 45799 | G50: 47978 | H50: 3.7223717e+08 | I50: =VLOOKUP(B50,'KASE за 16.10.25'!$C$5:$F$165,4,0) -> 70.382 | J50: =VLOOKUP(B50,'KASE за 16.10.25'!$C$5:$G$165,5,0) -> 74.0393 | K50: 18286667 | L50: =D50*I50/100+K50 -> 3.7019667e+08 | M50: =L50/$L$62 -> 0.013953305 | N50: =D50*E50%/360 -> 117222.22 | O50: =K50+N50 -> 18403889
A51: Министерство Финансов Республики Казахстан | B51: KZKD00000790 | C51: 500000 | D51: =C51*1000 -> 500000000 | E51: 7.68 | F51: 45813 | G51: 47343 | H51: 4.0360417e+08 | I51: =VLOOKUP(B51,'KASE за 16.10.25'!$C$5:$F$165,4,0) -> 75.0924 | J51: =VLOOKUP(B51,'KASE за 16.10.25'!$C$5:$G$165,5,0) -> 76.4364 | K51: 6720000 | L51: =D51*I51/100+K51 -> 382182000 | M51: =L51/$L$62 -> 0.014405051 | N51: =D51*E51%/360 -> 106666.67 | O51: =K51+N51 -> 6826666.7
A52: Министерство Финансов Республики Казахстан | B52: KZKD00000543 | C52: 500000 | D52: =C52*1000 -> 500000000 | E52: 5 | F52: 45813 | G52: 46861 | H52: 3.7940239e+08 | I52: =VLOOKUP(B52,'KASE за 16.10.25'!$C$5:$F$177,4,0) -> 76.9359 | J52: =VLOOKUP(B52,'KASE за 16.10.25'!$C$5:$G$177,5,0) -> 79.4081 | K52: 12361111 | L52: =D52*I52/100+K52 -> 3.9704061e+08 | M52: =L52/$L$62 -> 0.014965096 | N52: =D52*E52%/360 -> 69444.444 | O52: =K52+N52 -> 12430556
A53: Министерство Финансов Республики Казахстан | B53: KZKD00001160 | C53: 200000 | D53: =C53*1000 -> 200000000 | E53: 10.55 | F53: 45820 | G53: 47327 | H53: 1.8266529e+08 | I53: =VLOOKUP(B53,'KASE за 16.10.25'!$C$5:$F$165,4,0) -> 82.8274 | J53: =VLOOKUP(B53,'KASE за 16.10.25'!$C$5:$G$165,5,0) -> 85.1132 | K53: 4571666.7 | L53: =D53*I53/100+K53 -> 1.7022647e+08 | M53: =L53/$L$62 -> 0.0064161079 | N53: =D53*E53%/360 -> 58611.111 | O53: =K53+N53 -> 4630277.8
A54: Министерство Финансов Республики Казахстан | B54: KZKD00001251 | C54: 500000 | D54: =C54*1000 -> 500000000 | E54: 12 | F54: 45832 | G54: 47549 | H54: 4.4701683e+08 | I54: =VLOOKUP(B54,'KASE за 16.10.25'!$C$5:$F$165,4,0) -> 85.0565 | J54: =VLOOKUP(B54,'KASE за 16.10.25'!$C$5:$G$165,5,0) -> 92.3565 | K54: 36500000 | L54: =D54*I54/100+K54 -> 4.617825e+08 | M54: =L54/$L$62 -> 0.017405321 | N54: =D54*E54%/360 -> 166666.67 | O54: =K54+N54 -> 36666667
A55: Министерство Финансов Республики Казахстан | B55: KZKD00001251 | C55: 500000 | D55: =C55*1000 -> 500000000 | E55: 12 | F55: 45832 | G55: 47549 | H55: 4.4561733e+08 | I55: =VLOOKUP(B55,'KASE за 16.10.25'!$C$5:$F$165,4,0) -> 85.0565 | J55: =VLOOKUP(B55,'KASE за 16.10.25'!$C$5:$G$165,5,0) -> 92.3565 | K55: 36500000 | L55: =D55*I55/100+K55 -> 4.617825e+08 | M55: =L55/$L$62 -> 0.017405321 | N55: =D55*E55%/360 -> 166666.67 | O55: =K55+N55 -> 36666667
A56: Министерство Финансов Республики Казахстан | B56: KZKD00001251 | C56: 411421 | D56: =C56*1000 -> 411421000 | E56: 12 | F56: 45832 | G56: 47549 | H56: 3.6376844e+08 | I56: =VLOOKUP(B56,'KASE за 16.10.25'!$C$5:$F$165,4,0) -> 85.0565 | J56: =VLOOKUP(B56,'KASE за 16.10.25'!$C$5:$G$165,5,0) -> 92.3565 | K56: 30033733 | L56: =D56*I56/100+K56 -> 3.7997404e+08 | M56: =L56/$L$62 -> 0.014321829 | N56: =D56*E56%/360 -> 137140.33 | O56: =K56+N56 -> 30170873
A57: Министерство Финансов Республики Казахстан | B57: KZKD00001301 | C57: =500000-271261 -> 228739 | D57: =C57*1000 -> 228739000 | E57: 14.45 | F57: 45848 | G57: 48735 | H57: 2.0742821e+08 | I57: =VLOOKUP(B57,'KASE за 16.10.25'!$C$5:$F$170,4,0) -> 89.0227 | J57: =VLOOKUP(B57,'KASE за 16.10.25'!$C$5:$G$170,5,0) -> 94.2809 | K57: 12027541 | L57: =D57*I57/100+K57 -> 2.1565718e+08 | M57: =L57/$L$62 -> 0.008128464 | N57: =D57*E57%/360 -> 91813.293 | O57: =K57+N57 -> 12119355
A58: Министерство Финансов Республики Казахстан | B58: KZKD00000964 | C58: 500000 | D58: =C58*1000 -> 500000000 | E58: 8.44 | F58: 45862 | G58: 47978 | H58: 3.5788194e+08 | I58: =VLOOKUP(B58,'KASE за 16.10.25'!$C$5:$F$170,4,0) -> 70.382 | J58: =VLOOKUP(B58,'KASE за 16.10.25'!$C$5:$G$170,5,0) -> 74.0393 | K58: 18286667 | L58: =D58*I58/100+K58 -> 3.7019667e+08 | M58: =L58/$L$62 -> 0.013953305 | N58: =D58*E58%/360 -> 117222.22 | O58: =K58+N58 -> 18403889
A59: Министерство Финансов Республики Казахстан | B59: KZKD00001301 | C59: 500000 | D59: =C59*1000 -> 500000000 | E59: 14.45 | F59: 45883 | G59: 48735 | H59: 4.6018642e+08 | I59: =VLOOKUP(B59,'KASE за 16.10.25'!$C$5:$F$170,4,0) -> 89.0227 | J59: =VLOOKUP(B59,'KASE за 16.10.25'!$C$5:$G$170,5,0) -> 94.2809 | K59: 26290972 | L59: =D59*I59/100+K59 -> 4.7140447e+08 | M59: =L59/$L$62 -> 0.017767989 | N59: =D59*E59%/360 -> 200694.44 | O59: =K59+N59 -> 26491667
A60: Министерство Финансов Республики Казахстан | B60: KZKD00000774 | C60: 16841 | D60: =C60*1000 -> 16841000 | E60: 8.35 | F60: 45890 | G60: 50976 | H60: 9465392.4 | I60: =VLOOKUP(B60,'KASE за 16.10.25'!$C$5:$F$177,4,0) -> 54.6101 | J60: =VLOOKUP(B60,'KASE за 16.10.25'!$C$5:$G$177,5,0) -> 56.4889 | K60: 316400.29 | L60: =D60*I60/100+K60 -> 9513287.2 | M60: =L60/$L$62 -> 0.00035857102 | N60: =D60*E60%/360 -> 3906.1764 | O60: =K60+N60 -> 320306.46
A61: АО "Казахстанская Жилищная Компания" | B61: KZ2C00014744 | C61: 500000 | D61: =C61*1000 -> 500000000 | E61: 18.7 | F61: 45896 | G61: 46992 | H61: 500000000 | I61: =VLOOKUP(B61,'Риск цены за 16.10.25'!$C$4:$G$963,4,0) -> 96.985818 | J61: =VLOOKUP(B61,'Риск цены за 16.10.25'!$C$4:$G$963,5,0) -> 99.531118 | K61: 12726389 | L61: =D61*I61/100+K61 -> 4.9765548e+08 | M61: =L61/$L$62 -> 0.018757431 | N61: =D61*E61%/360 -> 259722.22 | O61: =K61+N61 -> 12986111
A62: ИТОГО | C62: =SUM(C6:C61) -> 32621800 | D62: =SUM(D6:D61) -> 32621800000 | H62: =SUM(H6:H61) -> 2.8060502e+10 | K62: =SUM(K6:K61) -> 1.4392252e+09 | L62: =SUM(L6:L61) -> 2.653111e+10 | M62: =SUM(M6:M61) -> 1 | N62: 2.653111e+10 | O62: =L62-N62 -> 0
A64: Остатки на инвест. cчетах
A65: KZT | B65: 692831.45 | C65: 692831.45 | D65: =B65-C65 -> 0
A67: Обратное репо
A68: Наименование эмитента и вид ЦБ | B68: НИН (ISIN) | C68: Количество | D68: Валюта | E68: Дата открытия | F68: Дата закрытия | G68: Цена открытия | H68: Цена закрытия | I68: Сумма открытия операции. в тг | J68: Сумма закрытия операции. в тг | K68: Ставка доходности. % | L68: Сумма начисленного вознагрждения | M68: Суммарная текущая стоимость. в тг
A69: АО "Казахстанский фонд устойчивости" | B69: KZ2C00006906 | C69: 38080 | D69: KZT | E69: 45943 | F69: 45950 | G69: 919.15 | H69: 922.14668 | I69: 35001232 | J69: 35115346 | K69: 17.000001 | L69: =IF(($B$1-E69)=0,0,(J69-I69)/(F69-E69)*($B$1-E69)) -> 48905.833 | M69: =IF((F69=$B$1),0,(I69+L69)) -> 35050138
A70: Евразийский Банк Развития | B70: KZ2D00009628 | C70: 2552096 | D70: KZT | E70: 45945 | F70: 45946 | G70: 542.4641 | H70: 542.71676 | I70: 1.3844205e+09 | J70: 1.3850653e+09 | K70: 17.0001 | L70: =IF(($B$1-E70)=0,0,(J70-I70)/(F70-E70)*($B$1-E70)) -> 644802.36 | M70: =IF((F70=$B$1),0,(I70+L70)) -> 0
A71: Евразийский Банк Развития | B71: KZ2D00009628 | C71: 16596 | D71: KZT | E71: 45945 | F71: 45946 | G71: 542.4641 | H71: 542.71676 | I71: 9002734.2 | J71: 9006927.3 | K71: 17.000104 | L71: =IF(($B$1-E71)=0,0,(J71-I71)/(F71-E71)*($B$1-E71)) -> 4193.08 | M71: =IF((F71=$B$1),0,(I71+L71)) -> 0
A72: Министерство Финансов Республики Казахстан | B72: KZK100000373 | C72: 14182798 | D72: KZT | E72: 45946 | F72: 45947 | G72: 95.2566 | H72: 95.301097 | I72: 1.3510051e+09 | J72: 1.3516362e+09 | K72: 17.05 | L72: =IF(($B$1-E72)=0,0,(J72-I72)/(F72-E72)*($B$1-E72)) -> 0 | M72: =IF((F72=$B$1),0,(I72+L72)) -> 1.3510051e+09
A73: Евразийский Банк Развития | B73: KZX000001433 | C73: 58616 | D73: KZT | E73: 45946 | F73: 45947 | G73: 580.2248 | H73: 580.49584 | I73: 34010457 | J73: 34026344 | K73: 17.050004 | L73: =IF(($B$1-E73)=0,0,(J73-I73)/(F73-E73)*($B$1-E73)) -> 0 | M73: =IF((F73=$B$1),0,(I73+L73)) -> 34010457
A74: Министерство Финансов Республики Казахстан | B74: XS2914770545 | C74: 16794 | D74: KZT | E74: 45946 | F74: 45947 | G74: 536.1551 | H74: 536.40482 | I74: 9004188.8 | J74: 9008382.5 | K74: 16.999993 | L74: =IF(($B$1-E74)=0,0,(J74-I74)/(F74-E74)*($B$1-E74)) -> 0 | M74: =IF((F74=$B$1),0,(I74+L74)) -> 9004188.8
A76: ИТОГО | C76: =SUM(C69:C74) -> 16864980 | I76: =SUM(I69:I74) -> 2.8224442e+09 | J76: =SUM(J69:J74) -> 2.8238585e+09 | L76: =SUM(L69:L74) -> 697901.27 | M76: =SUM(M69:M74) -> 1.4290699e+09 | N76: 1.4290699e+09 | O76: =M76-N76 -> 0
A79: Прочие активы (дебиторская задолженность. деньги в пути)
A80: № п/п | B80: Наименование | C80: Валюта | D80: Дата постановки на учет | E80: Количество | F80: Остаток в валюте | G80: Остаток в тенге
A81: 1 | B81: KZ2C00012268 | C81: KZT | D81: 45757 | E81: 200000 | F81: 16700000 | G81: 16700000 | H81: 16700000 | I81: =G81-H81 -> 0
A82: ИТОГО | G82: =SUM(G81:G81) -> 16700000
A84: Итого активов | B84: =L62+B65+M76+G82 -> 2.7977573e+10 | C84: 2.7977573e+10 | D84: =B84-C84 -> 0
A88: 2) Кредиторская задолженность Фонда
A89: Комиссия ДУ (за управление) | B89: =4006269.97-4006269.97 -> 0
A90: Комиссия ДУ (сверхдоходность)
A91: Комиссия Кастоди | B91: =2000+2000+2000+2000+2000+2000+4000+3000+8000+2000+2000+2000+2000+2000+17000+2000+2000+14000+7000+2000+3000+348823.86+2000+2000+3000+4000+4000+2000+2000+6000+2000+2000+2000+3000 -> 466823.86
A92: Комиссия Глобал кастоди
A93: Комиссия Центрального Депозитария | B93: 366267.13
A94: Клиринговый сбор | B94: =1768.92+1769.54+1770.81+5232.79+1773.41+1773.37+1775.6+2138.39+6381.64+2141.98+2143.21+2142.8+2144.88+6362.15+2171.93+2150.01+2150.85+2166.16+6573.12+2154.53+2155.1+2155.97+2155.82+6398.74+2160.71+2167.14+2162.69+2163.62+6411.25+2456.13+2116.43+2115.95+2116.85 -> 93422.49
A95: Комиссия биржи | B95: =870.05+870.36+871+2612.49+872.3+872.27+872.63+1055.53+3169.53+1057.33+1057.95+1058.49+1058.78+3177.16+1060.9+1061.35+1061.76+1061.76+3186.6+1063.61+1064.65+1065.07+1065+3197.71+1067.45+1067.66+1068.44+1068.91-29036.5+3205.63+1228.07+1044.55+1045.07+1045.51 -> 17169.07
A96: Комиссия брокера
A97: Кредиторская задолженность (прочая комиссия)
A98: Остаток прочих обязательств на конец дня
A99: Итого | B99: =SUM(B89:B98) -> 943682.55

Sheet KASE за 16.10.25
A1: Дата оценки | B1: 45946
A3: № п/п | B3: Код | C3: ISIN | D3: Вид ценной бумаги | E3: Компания | F3: Рыночная цена | G3: Рыночная "грязная" цена | H3: Доходность до погашения, % годовых | I3: Срок до погашения | J3: Единица измерения цены
A5: 1 | B5: 1AIRA | C5: KZ1C00004050 | D5: акции | E5: Эйр Астана | F5: 818.8 | G5: – | H5: – | I5: – | J5: KZT
A6: 2 | B6: 2AKZM | C6: KZ1C00001288 | D6: акции | E6: Актюбинский завод металлоконструкций | F6: 6301.35 | G6: – | H6: – | I6: – | J6: KZT
A7: 3 | B7: 3ALMSb1 | C7: KZ2C00012953 | D7: долговые ЦБ | E7: АК Алтыналмас | F7: 100.0201 | G7: 100.4645 | H7: 7,99 | I7: 790 (2) | J7: %
A8: 4 | B8: 4BCCI_cc | C8: KZPF00000058 | D8: ЦБ инвест. фондов | E8: BCC Invest | F8: 130.74 | G8: – | H8: – | I8: – | J8: USD
A9: 5 | B9: 5BCCIbe | C9: KZPF00000553 | D9: ЦБ инвест. фондов | E9: BCC Invest | F9: 1497.03 | G9: – | H9: – | I9: – | J9: KZT
A10: 6 | B10: 6BCCIrb | C10: KZPF00000231 | D10: ЦБ инвест. фондов | E10: BCC Invest | F10: 7.2 | G10: – | H10: – | I10: – | J10: KZT
A11: 7 | B11: 7BCCIwah | C11: KZPF00000900 | D11: ЦБ инвест. фондов | E11: BCC Invest | F11: 100.76 | G11: – | H11: – | I11: – | J11: USD
A12: 8 | B12: 8BIGDb2 | C12: KZ2D00012531 | D12: долговые ЦБ | E12: Частная компания BI Development Ltd. | F12: 101.9999 | G12: 105.4582 | H12: 5,49 | I12: 375 (1) | J12: %
A13: 9 | B13: 9BIGDb5 | C13: KZ2D00012861 | D13: долговые ЦБ | E13: Частная компания BI Development Ltd. | F13: 100.4648 | G13: 107.8856 | H13: 19,09 | I13: 583 (2) | J13: %
A14: 10 | B14: 10BIGDb6 | C14: KZ2D00015328 | D14: долговые ЦБ | E14: Частная компания BI Development Ltd. | F14: 100.3437 | G14: 101.9381 | H14: 20,23 | I14: 692 (2) | J14: %
A15: 11 | B15: 11BKBTb1 | C15: KZ2P00010317 | D15: долговые ЦБ | E15: Black Biotechnology (Блэк Биотехнолоджи) | F15: 99.3 | G15: 108.1986 | H15: 22,17 | I15: 391 (1) | J15: %
A16: 12 | B16: 12BRKZe12 | C16: XS2337670694 | D16: долговые ЦБ | E16: Банк Развития Казахстана | F16: 86.9627 | G16: 88.2738 | H16: 5,72 | I16: 2 000 (6) | J16: %
A17: 13 | B17: 13BRKZe16 | C17: XS2917067204 | D17: долговые ЦБ | E17: Банк Развития Казахстана | F17: 100.1849 | G17: 102.7078 | H17: 5,20 | I17: 1 447 (4) | J17: %
A18: 14 | B18: 14BRKZe21 | C18: HK0001185674 | D18: долговые ЦБ | E18: Банк Развития Казахстана | F18: 100.7273 | G18: 101.1403 | H18: 3,08 | I18: 1 051 (3) | J18: %
A19: 15 | B19: 15BTRKe1 | C19: XS3067899610 | D19: долговые ЦБ | E19: Национальный управляющий холдинг "Байтерек" | F19: 101.6757 | G19: 104.0676 | H19: 4,75 | I19: 922 (3) | J19: %
A20: 16 | B20: 16CCBN | C20: KZ0007786572 | D20: акции | E20: Банк ЦентрКредит | F20: 4821.56 | G20: – | H20: – | I20: – | J20: KZT
A21: 17 | B21: 17CCBNp | C21: KZ000A0H0930 | D21: акции | E21: Банк ЦентрКредит | F21: 7831.81 | G21: – | H21: – | I21: – | J21: KZT
A22: 18 | B22: 18CSECfe | C22: KZPF00000025 | D22: ЦБ инвест. фондов | E22: Сентрас Секьюритиз | F22: 6065105 | G22: – | H22: – | I22: – | J22: KZT
A23: 19 | B23: 19CSECtf | C23: KZPF00000280 | D23: ЦБ инвест. фондов | E23: Сентрас Секьюритиз | F23: 1788232.6 | G23: – | H23: – | I23: – | J23: KZT
A24: 20 | B24: 20EABRb40 | C24: KZ2D00009628 | D24: ЦБ МФО | E24: Евразийский банк развития | F24: 99.7004 | G24: 100.1135 | H24: 6,43 | I24: 154 (0) | J24: %
A25: 21 | B25: 21EABRb42 | C25: KZ2D00009222 | D25: ЦБ МФО | E25: Евразийский банк развития | F25: 100 | G25: 102.3151 | H25: 16,22 | I25: 862 (2) | J25: %
A26: 22 | B26: 22EABRb53 | C26: KZ2D00013620 | D26: ЦБ МФО | E26: Евразийский банк развития | F26: 100 | G26: 100.911 | H26: 17,48 | I26: 893 (2) | J26: %
A27: 23 | B27: 23FFIN_or | C27: KZPF00000082 | D27: ЦБ инвест. фондов | E27: Фридом Финанс | F27: 168.53 | G27: – | H27: – | I27: – | J27: USD
A28: 24 | B28: 24FFINgw | C28: KZPF00000090 | D28: ЦБ инвест. фондов | E28: Фридом Финанс | F28: 5523.73 | G28: – | H28: – | I28: – | J28: KZT
A29: 25 | B29: 25HCBNb13 | C29: KZ2C00011195 | D29: долговые ЦБ | E29: Home Credit Bank | F29: 99.7446 | G29: 102.215 | H29: 18,25 | I29: 851 (2) | J29: %
A30: 26 | B30: 26HFINhl | C30: KZPF00000538 | D30: ЦБ инвест. фондов | E30: Halyk Finance | F30: 53628.79 | G30: – | H30: – | I30: – | J30: KZT
A31: 27 | B31: 27HFINhp | C31: KZPF00000546 | D31: ЦБ инвест. фондов | E31: Halyk Finance | F31: 75161.85 | G31: – | H31: – | I31: – | J31: KZT
A32: 28 | B32: 28HFINhs | C32: KZPF00000520 | D32: ЦБ инвест. фондов | E32: Halyk Finance | F32: 74280.29 | G32: – | H32: – | I32: – | J32: KZT
A33: 29 | B33: 29HFINhv | C33: KZPF00000041 | D33: ЦБ инвест. фондов | E33: Halyk Finance | F33: 591846.63 | G33: – | H33: – | I33: – | J33: KZT
A34: 30 | B34: 30HSBK | C34: KZ000A0LE0S4 | D34: акции | E34: Народный Банк Казахстана | F34: 356 | G34: – | H34: – | I34: – | J34: KZT
A35: 31 | B35: 31HSBKb22 | C35: KZ2C00012482 | D35: долговые ЦБ | E35: Народный Банк Казахстана | F35: 98.6457 | G35: 105.0517 | H35: 18,07 | I35: 778 (2) | J35: %
A36: 32 | B36: 32HSBKd | C36: US46627J3023 | D36: производные ЦБ | E36: Народный Банк Казахстана | F36: 26.82 | G36: – | H36: – | I36: – | J36: USD
A37: 33 | B37: 33IFDR | C37: KZ1C00000256 | D37: акции | E37: Teniz Capital Investment Banking | F37: 9490.25 | G37: – | H37: – | I37: – | J37: KZT
A38: 34 | B38: 34KASAb1 | C38: KZ2C00013753 | D38: долговые ЦБ | E38: Казахстанский электролизный завод | F38: 100.9808 | G38: 103.4364 | H38: 6,09 | I38: 944 (3) | J38: %
A39: 35 | B39: 35KCEL | C39: KZ1C00000876 | D39: акции | E39: Kcell | F39: 3335.45 | G39: – | H39: – | I39: – | J39: KZT
A40: 36 | B40: 36KEGC | C40: KZ1C00000959 | D40: акции | E40: KEGOC | F40: 1478.92 | G40: – | H40: – | I40: – | J40: KZT
A41: 37 | B41: 37KMGZ | C41: KZ1C00001122 | D41: акции | E41: Национальная компания "КазМунайГаз" | F41: 21989.76 | G41: – | H41: – | I41: – | J41: KZT
A42: 38 | B42: 38KMGZe12 | C42: XS1595714087 | D42: долговые ЦБ | E42: Национальная компания "КазМунайГаз" | F42: 93.8438 | G42: 96.6709 | H42: 6,28 | I42: 7 743 (22) | J42: %
A43: 39 | B43: 39KMGZe15 | C43: XS1807299331 | D43: долговые ЦБ | E43: Национальная компания "КазМунайГаз" | F43: 99.9728 | G43: 103.0186 | H43: 6,38 | I43: 8 288 (23) | J43: %
A44: 40 | B44: 40KSPI | C44: KZ1C00001536 | D44: акции | E44: Kaspi.kz | F44: 43264.77 | G44: – | H44: – | I44: – | J44: KZT
A45: 41 | B45: 41KSPId | C45: US48581R2058 | D45: производные ЦБ | E45: Kaspi.kz | F45: 77.56 | G45: – | H45: – | I45: – | J45: USD
A46: 42 | B46: 42KZAP | C46: KZ1C00001619 | D46: акции | E46: Национальная атомная компания "Казатомпром" | F46: 29950.54 | G46: – | H46: – | I46: – | J46: KZT
A47: 43 | B47: 43KZTCb3 | C47: KZ2C00012961 | D47: долговые ЦБ | E47: Jusan Mobile | F47: 106.5783 | G47: 108.3505 | H47: 18,47 | I47: 871 (2) | J47: %
A48: 44 | B48: 44KZTK | C48: KZ0009093241 | D48: акции | E48: Казахтелеком | F48: 39541.67 | G48: – | H48: – | I48: – | J48: KZT
A49: 45 | B49: 45KZTKp | C49: KZ0009094645 | D49: акции | E49: Казахтелеком | F49: 30763.81 | G49: – | H49: – | I49: – | J49: KZT
A50: 46 | B50: 46KZTO | C50: KZ1C00000744 | D50: акции | E50: КазТрансОйл | F50: 853.77 | G50: – | H50: – | I50: – | J50: KZT
A51: 47 | B51: 47KZ_23_3504 | C51: XS2914770545 | D51: ГЦБ | E51: Минфин | F51: 98.625 | G51: 98.7167 | H51: 4,90 | I51: 3 413 (9) | J51: %
A52: 48 | B52: 48MFDFb1 | C52: KZ2P00010457 | D52: долговые ЦБ | E52: МФО "ФинТехЛаб" | F52: 99.9863 | G52: 104.9432 | H52: 21,51 | I52: 97 (0) | J52: %
A53: 49 | B53: 49MFDFb3 | C53: KZ2P00013840 | D53: долговые ЦБ | E53: МФО "ФинТехЛаб" | F53: 98.5802 | G53: 99.7469 | H53: 22,01 | I53: 610 (2) | J53: %
A54: 50 | B54: 50MFDGb1 | C54: KZ2P00012677 | D54: долговые ЦБ | E54: МФО "Деньги говорят" | F54: 99.0075 | G54: 102.4908 | H54: 23,02 | I54: 393 (1) | J54: %
A55: 51 | B55: 51MFMCb2 | C55: KZ2P00011968 | D55: долговые ЦБ | E55: МФО MyCar Finance | F55: 98.6556 | G55: 106.0445 | H55: 18,88 | I55: 388 (1) | J55: %
A56: 52 | B56: 52MFMOb23 | C56: KZ2P00013154 | D56: долговые ЦБ | E56: МФО "Mogo Kazakhstan (Мого Казахстан) | F56: 82.549 | G56: 82.549 | H56: 36,69 | I56: 570 (2) | J56: %
A57: 53 | B57: 53MFMOb24 | C57: KZ2P00013212 | D57: долговые ЦБ | E57: МФО "Mogo Kazakhstan (Мого Казахстан) | F57: 99.2495 | G57: 100.1051 | H57: 22,53 | I57: 616 (2) | J57: %
A58: 54 | B58: 54MFMOb25 | C58: KZ2P00013220 | D58: долговые ЦБ | E58: МФО "Mogo Kazakhstan (Мого Казахстан) | F58: 99.3671 | G58: 99.6727 | H58: 22,43 | I58: 655 (2) | J58: %
A59: 55 | B59: 55MFMOb27 | C59: KZ2P00013345 | D59: долговые ЦБ | E59: МФО "Mogo Kazakhstan (Мого Казахстан) | F59: 99.9989 | G59: 100.4322 | H59: 12,00 | I59: 617 (2) | J59: %
A60: 56 | B60: 56MFOKb16 | C60: KZ2C00010171 | D60: долговые ЦБ | E60: МФО ОнлайнКазФинанс | F60: 99.7368 | G60: 99.8662 | H60: 26,74 | I60: 28 (0) | J60: %
A61: 57 | B61: 57MFOKb18 | C61: KZ2C00010478 | D61: долговые ЦБ | E61: МФО ОнлайнКазФинанс | F61: 98.9547 | G61: 100.0658 | H61: 22,11 | I61: 190 (1) | J61: %
A62: 58 | B62: 58MFOKb20 | C62: KZ2C00010916 | D62: долговые ЦБ | E62: МФО ОнлайнКазФинанс | F62: 99.9243 | G62: 99.9872 | H62: 22,68 | I62: 659 (2) | J62: %
... A177: 173 | B177: 173SKKZe1 | C177: XS2399149694 | D177: долговые ЦБ | E177: Фонд национального благосостояния "Самрук-Қазына | F177: 97.0136 | G177: 97.9469 | H177: 5,00 | I177: 372 (1) | J177: %

Sheet Риск цены за 16.10.25
A1: Дата оценки | B1: 45946
A3: № п/п | B3: Торговый код | C3: ISIN | D3: Алгоритмы и параметры расчета ЦБ | E3: Краткое наименование эмитента | F3: Расчетная цена | G3: Расчетная грязная | H3: Доходность до погашения. % годовых | I3: Дней до погашения | J3: Единица измерения цены
A4: 1 | B4: AAFD | C4: KZ1C00008721 | D4: Акции | E4: АО "АзияАгроФуд" | F4: 100 | G4: 100 | H4: 0 | I4: 0 | J4: KZT
A5: 2 | B5: AAL_KZ | C5: US02376R1023 | D5: Акции | E5: American Airlines | F5: 6629.5649 | G5: 6629.5649 | H5: 0 | I5: 0 | J5: KZT
A6: 3 | B6: AAPL_KZ | C6: US0378331005 | D6: Акции | E6: Apple Inc. | F6: 135398.29 | G6: 135398.29 | H6: 0 | I6: 0 | J6: KZT
A7: 4 | B7: ABK022_210 | C7: KZMJ00002103 | D7: Облигации | E7: Акимат Актюбинской области | F7: 100 | G7: 101.7944 | H7: 4.24 | I7: 328 | J7: %
A8: 5 | B8: ABK024_183 | C8: KZMJ00001832 | D8: Облигации | E8: Акимат Актюбинской области | F8: 100 | G8: 100.1342 | H8: 0.35 | I8: 222 | J8: %
A9: 6 | B9: ABK114_193 | C9: KZMJ00001931 | D9: Облигации | E9: Акимат Актюбинской области | F9: 100 | G9: 100.0011 | H9: 0.02 | I9: 3044 | J9: %
A10: 7 | B10: ABK119_006 | C10: KZMF00000069 | D10: Облигации | E10: Акимат Актюбинской области | F10: 100 | G10: 101.8808 | H10: 6.08 | I10: 1659 | J10: %
A11: 8 | B11: ABK119_081 | C11: KZMF00000812 | D11: Облигации | E11: Акимат Актюбинской области | F11: 100 | G11: 106.8831 | H11: 7.08 | I11: 2141 | J11: %
A12: 9 | B12: ABK131_021 | C12: KZMF00000218 | D12: Облигации | E12: Акимат Актюбинской области | F12: 100 | G12: 101.0506 | H12: 6.08 | I12: 2068 | J12: %
A13: 10 | B13: ABK143_032 | C13: KZMF00000325 | D13: Облигации | E13: Акимат Актюбинской области | F13: 100 | G13: 105.9983 | H13: 6.09 | I13: 2496 | J13: %
A14: 11 | B14: ABK143_033 | C14: KZMF00000333 | D14: Облигации | E14: Акимат Актюбинской области | F14: 100 | G14: 105.9983 | H14: 6.09 | I14: 2496 | J14: %
A15: 12 | B15: ABT_KZ | C15: US0028241000 | D15: Акции | E15: Abbott Lab. | F15: 69595.615 | G15: 69595.615 | H15: 0 | I15: 0 | J15: KZT
... A1059: 1056 | B1059: ZKK180_259 | C1059: KZMJ00002590 | D1059: Облигации | E1059: Акимат Западно-Казахстанской области | F1059: 92.084711 | G1059: 94.342211 | H1059: 20.6 | I1059: 5357 | J1059: %
