Workbook

Sheet ДУ
A1: Сентрас Секьюритиз | B1: 45876
A2: 1) Активы
A4: ЦБ
A5: Наименование эмитента и вид ЦБ | B5: ISIN | C5: Количество ЦБ | D5: Номинальная стоимость. тенге | E5: Ставка | F5: Дата зачисления/приобретения | G5: Дата погашения | H5: Чистая покупная стоимоcть | I5: Расчетная цена на 07.08.25 | J5: Расчетная грязная цена на 07.08.25 | K5: Накопленный купон | L5: Суммарно-текущая рыночная стоимость | M5: Вес
A6: Министерство Финансов Республики Казахстан купонные МЕУКАМ | B6: KZKD00000535 | C6: =3250000-500000-500000-500000 -> 1750000 | D6: =3250000000-500000000-500000000-500000000 -> 1750000000 | E6: 5.49 | F6: 45491 | G6: 27.03.2027 | H6: =2755458875/3250000000*D6 -> 1483708625 | I6: =VLOOKUP(B6,'KASE за 07.08.25'!$C$5:$F$162,4,0) -> 84.7249 | J6: =VLOOKUP(B6,'KASE за 07.08.25'!$C$5:$G$162,5,0) -> 86.7074 | K6: 34693750 | L6: =D6*I6/100+K6 -> 1517379500 | M6: =L6/$L$59 -> 0.059179174 | N6: =D6*E6%/360 -> 266875 | O6: =K6+N6 -> 34960625
A7: Министерство Финансов Республики Казахстан купонные МЕУКАМ | B7: KZKD00001137 | C7: 1950000 | D7: 1950000000 | E7: 10.4 | F7: 45491 | G7: 12.04.2028 | H7: 1838876000 | I7: =VLOOKUP(B7,'KASE за 07.08.25'!$C$5:$F$162,4,0) -> 86.9332 | J7: =VLOOKUP(B7,'KASE за 07.08.25'!$C$5:$G$162,5,0) -> 90.2554 | K7: 64783333 | L7: =D7*I7/100+K7 -> 1.7599807e+09 | M7: =L7/$L$59 -> 0.068640842 | N7: =D7*E7%/360 -> 563333.33 | O7: =K7+N7 -> 65346667
A8: Министерство Финансов Республики Казахстан МЕУКАМ | B8: KZKD00001087 | C8: =1950000-202300-182000-187350 -> 1378350 | D8: =C8*1000 -> 1378350000 | E8: 11 | F8: 45491 | G8: 31.03.2029 | H8: =1855844250/1950000000*D8 -> 1.3117964e+09 | I8: =VLOOKUP(B8,'KASE за 07.08.25'!$C$5:$F$162,4,0) -> 85.109 | J8: =VLOOKUP(B8,'KASE за 07.08.25'!$C$5:$G$162,5,0) -> 88.9896 | K8: 53487638 | L8: =D8*I8/100+K8 -> 1226587539 | M8: =L8/$L$59 -> 0.047838024 | N8: =D8*E8%/360 -> 421162.5 | O8: =K8+N8 -> 53908800
A9: Министерство Финансов Республики Казахстан купонные МЕУКАМ | B9: KZKD00001160 | C9: =1950000-225000-225000-208000-225000-225000 -> 842000 | D9: =C9*1000 -> 842000000 | E9: 10.55 | F9: 45491 | G9: 28.07.2029 | H9: =1504310166.66923/1500000000*D9 -> 8.4441944e+08 | I9: =VLOOKUP(B9,'KASE за 07.08.25'!$C$5:$F$162,4,0) -> 83.1474 | J9: =VLOOKUP(B9,'KASE за 07.08.25'!$C$5:$G$162,5,0) -> 83.4112 | K9: 2220775 | L9: =D9*I9/100+K9 -> 702321883 | M9: =L9/$L$59 -> 0.027391189 | N9: =D9*E9%/360 -> 246752.78 | O9: =K9+N9 -> 2467527.8
A10: Министерство Финансов Республики Казахстан купонные МЕУКАМ | B10: KZKD00001129 | C10: 1450000 | D10: 1450000000 | E10: 10.3 | F10: 45491 | G10: 17.03.2031 | H10: 1.307499e+09 | I10: =VLOOKUP(B10,'KASE за 07.08.25'!$C$5:$F$162,4,0) -> 77.8037 | J10: =VLOOKUP(B10,'KASE за 07.08.25'!$C$5:$G$162,5,0) -> 81.8093 | K10: 58080556 | L10: =D10*I10/100+K10 -> 1.1862342e+09 | M10: =L10/$L$59 -> 0.046264208 | N10: =D10*E10%/360 -> 414861.11 | O10: =K10+N10 -> 58495417
A11: Министерство Финансов Республики Казахстан МЕУКАМ | B11: KZKD00000949 | C11: 1950000 | D11: 1950000000 | E11: 8.45 | F11: 45491 | G11: 16.04.2032 | H11: 1.5403351e+09 | I11: =VLOOKUP(B11,'KASE за 07.08.25'!$C$5:$F$162,4,0) -> 68.2679 | J11: =VLOOKUP(B11,'KASE за 07.08.25'!$C$5:$G$162,5,0) -> 70.8733 | K11: 50805625 | L11: =D11*I11/100+K11 -> 1382029675 | M11: =L11/$L$59 -> 0.053900408 | N11: =D11*E11%/360 -> 457708.33 | O11: =K11+N11 -> 51263333
A12: Министерство Финансов Республики Казахстан Купонные Облигации | B12: KZKD00001152 | C12: =1950000-250000-250000-250000-218000 -> 982000 | D12: =C12*1000 -> 982000000 | E12: 10.65 | F12: 45491 | G12: 26.07.2032 | H12: =1897171250/1950000000*D12 -> 9.5539598e+08 | I12: =VLOOKUP(B12,'KASE за 07.08.25'!$C$5:$F$162,4,0) -> 76.3623 | J12: =VLOOKUP(B12,'KASE за 07.08.25'!$C$5:$G$162,5,0) -> 76.6877 | K12: 3195591.7 | L12: =D12*I12/100+K12 -> 7.5307338e+08 | M12: =L12/$L$59 -> 0.029370543 | N12: =D12*E12%/360 -> 290508.33 | O12: =K12+N12 -> 3486100
A13: Министерство Финансов Республики Казахстан Купонные Облигации | B13: KZKD00001152 | C13: 250000 | D13: =C13*1000 -> 250000000 | E13: 10.65 | F13: 45673 | G13: 26.07.2032 | H13: =227969916.67/250000000*D13 -> 2.2796992e+08 | I13: =VLOOKUP(B13,'KASE за 07.08.25'!$C$5:$F$162,4,0) -> 76.3623 | J13: =VLOOKUP(B13,'KASE за 07.08.25'!$C$5:$G$162,5,0) -> 76.6877 | K13: 813541.67 | L13: =D13*I13/100+K13 -> 1.9171929e+08 | M13: =L13/$L$59 -> 0.0074772259 | N13: =D13*E13%/360 -> 73958.333 | O13: =K13+N13 -> 887500
A14: Министерство Финансов Республики Казахстан купонные МЕУКАМ | B14: KZKD00000741 | C14: 1950000 | D14: 1950000000 | E14: 8.07 | F14: 45491 | G14: 12.05.2034 | H14: 1425576750 | I14: =VLOOKUP(B14,'KASE за 07.08.25'!$C$5:$F$173,4,0) -> 61.8847 | J14: =VLOOKUP(B14,'KASE за 07.08.25'!$C$5:$G$173,5,0) -> 63.7901 | K14: 37155625 | L14: =D14*I14/100+K14 -> 1243907275 | M14: =L14/$L$59 -> 0.04851351 | N14: =D14*E14%/360 -> 437125 | O14: =K14+N14 -> 37592750
A15: Министерство Финансов Республики Казахстан купонные МЕУКАМ | B15: KZKD00000832 | C15: 1950000 | D15: 1950000000 | E15: 8.07 | F15: 45491 | G15: 29.01.2035 | H15: 1449433375 | I15: =VLOOKUP(B15,'KASE за 07.08.25'!$C$5:$F$173,4,0) -> 60.4318 | J15: =VLOOKUP(B15,'KASE за 07.08.25'!$C$5:$G$173,5,0) -> 64.6461 | K15: 82179500 | L15: =D15*I15/100+K15 -> 1260599600 | M15: =L15/$L$59 -> 0.049164526 | N15: =D15*E15%/360 -> 437125 | O15: =K15+N15 -> 82616625
A16: Министерство Финансов Республики Казахстан купонные МЕУКАМ | B16: KZKD00000550 | C16: =312000-1 -> 311999 | D16: =C16*1000 -> 311999000 | E16: 5.5 | F16: 45509 | G16: 48328 | H16: 2.0448962e+08 | I16: =VLOOKUP(B16,'KASE за 07.08.25'!$C$5:$F$165,4,0) -> 56.8564 | J16: =VLOOKUP(B16,'KASE за 07.08.25'!$C$5:$G$165,5,0) -> 58.43 | K16: 4909650.9 | L16: =D16*I16/100+K16 -> 1.8230105e+08 | M16: =L16/$L$59 -> 0.007109906 | N16: =D16*E16%/360 -> 47666.514 | O16: =K16+N16 -> 4957317.4
A17: Министерство Финансов Республики Казахстан купонные МЕУКАМ | B17: KZKD00000550 | C17: 500000 | D17: 500000000 | E17: 5.5 | F17: 45532 | G17: 48328 | H17: 3.2653072e+08 | I17: =VLOOKUP(B17,'KASE за 07.08.25'!$C$5:$F$165,4,0) -> 56.8564 | J17: =VLOOKUP(B17,'KASE за 07.08.25'!$C$5:$G$165,5,0) -> 58.43 | K17: 7868055.6 | L17: =D17*I17/100+K17 -> 2.9215006e+08 | M17: =L17/$L$59 -> 0.011394117 | N17: =D17*E17%/360 -> 76388.889 | O17: =K17+N17 -> 7944444.4
A18: Министерство Финансов Республики Казахстан купонные МЕУКАМ | B18: KZKD00000550 | C18: 500000 | D18: 500000000 | E18: 5.5 | F18: 45566 | G18: 48328 | H18: 3.3409056e+08 | I18: =VLOOKUP(B18,'KASE за 07.08.25'!$C$5:$F$165,4,0) -> 56.8564 | J18: =VLOOKUP(B18,'KASE за 07.08.25'!$C$5:$G$165,5,0) -> 58.43 | K18: 7868055.6 | L18: =D18*I18/100+K18 -> 2.9215006e+08 | M18: =L18/$L$59 -> 0.011394117 | N18: =D18*E18%/360 -> 76388.889 | O18: =K18+N18 -> 7944444.4
A19: Министерство Финансов Республики Казахстан купонные МЕУКАМ | B19: KZKD00000550 | C19: 300000 | D19: =C19*1000 -> 300000000 | E19: 5.5 | F19: 45649 | G19: 48328 | H19: 2.0566557e+08 | I19: =VLOOKUP(B19,'KASE за 07.08.25'!$C$5:$F$165,4,0) -> 56.8564 | J19: =VLOOKUP(B19,'KASE за 07.08.25'!$C$5:$G$165,5,0) -> 58.43 | K19: 4720833.3 | L19: =D19*I19/100+K19 -> 1.7529003e+08 | M19: =L19/$L$59 -> 0.00683647 | N19: =D19*E19%/360 -> 45833.333 | O19: =K19+N19 -> 4766666.7
A20: Министерство Финансов Республики Казахстан купонные МЕУКАМ | B20: KZKD00000550 | C20: 300000 | D20: =C20*1000 -> 300000000 | E20: 5.5 | F20: 45677 | G20: 48328 | H20: 2.0236587e+08 | I20: =VLOOKUP(B20,'KASE за 07.08.25'!$C$5:$F$165,4,0) -> 56.8564 | J20: =VLOOKUP(B20,'KASE за 07.08.25'!$C$5:$G$165,5,0) -> 58.43 | K20: 4720833.3 | L20: =D20*I20/100+K20 -> 1.7529003e+08 | M20: =L20/$L$59 -> 0.00683647 | N20: =D20*E20%/360 -> 45833.333 | O20: =K20+N20 -> 4766666.7
A21: Министерство Финансов Республики Казахстан купонные МЕУКАМ | B21: KZKD00001160 | C21: 500000 | D21: =C21*1000 -> 500000000 | E21: 10.55 | F21: 45512 | G21: 28.07.2029 | H21: 4.5194078e+08 | I21: =VLOOKUP(B21,'KASE за 07.08.25'!$C$5:$F$162,4,0) -> 83.1474 | J21: =VLOOKUP(B21,'KASE за 07.08.25'!$C$5:$G$162,5,0) -> 83.4112 | K21: 1318750 | L21: =D21*I21/100+K21 -> 417055750 | M21: =L21/$L$59 -> 0.016265552 | N21: =D21*E21%/360 -> 146527.78 | O21: =K21+N21 -> 1465277.8
A22: Министерство Финансов Республики Казахстан купонные МЕУКАМ | B22: KZKD00001160 | C22: 553430 | D22: =C22*1000 -> 553430000 | E22: 10.55 | F22: 45512 | G22: 28.07.2029 | H22: 4.9999941e+08 | I22: =VLOOKUP(B22,'KASE за 07.08.25'!$C$5:$F$162,4,0) -> 83.1474 | J22: =VLOOKUP(B22,'KASE за 07.08.25'!$C$5:$G$162,5,0) -> 83.4112 | K22: 1459671.6 | L22: =D22*I22/100+K22 -> 4.6162233e+08 | M22: =L22/$L$59 -> 0.018003689 | N22: =D22*E22%/360 -> 162185.74 | O22: =K22+N22 -> 1621857.4
A23: Министерство Финансов Республики Казахстан МЕУКАМ | B23: KZKD00000543 | C23: 636055 | D23: =C23*1000 -> 636055000 | E23: 5 | F23: 45519 | G23: 46861 | H23: 4.9999966e+08 | I23: =VLOOKUP(B23,'KASE за 07.08.25'!$C$5:$F$162,4,0) -> 75.9721 | J23: =VLOOKUP(B23,'KASE за 07.08.25'!$C$5:$G$162,5,0) -> 77.486 | K23: 9629166 | L23: =D23*I23/100+K23 -> 4.9285351e+08 | M23: =L23/$L$59 -> 0.019221733 | N23: =D23*E23%/360 -> 88340.972 | O23: =K23+N23 -> 9717506.9
A24: Министерство Финансов Республики Казахстан купонные МЕУКАМ | B24: KZKD00000774 | C24: 715927 | D24: =C24*1000 -> 715927000 | E24: 8.35 | F24: 45526 | G24: 50976 | H24: 4.9999948e+08 | I24: =VLOOKUP(B24,'KASE за 07.08.25'!$C$5:$F$173,4,0) -> 56.1603 | J24: =VLOOKUP(B24,'KASE за 07.08.25'!$C$5:$G$173,5,0) -> 56.4386 | K24: 1992663.5 | L24: =D24*I24/100+K24 -> 4.0405941e+08 | M24: =L24/$L$59 -> 0.015758683 | N24: =D24*E24%/360 -> 166055.29 | O24: =K24+N24 -> 2158718.8
A25: Министерство Финансов Республики Казахстан купонные МЕУКАМ | B25: KZKD00000774 | C25: 284073 | D25: =C25*1000 -> 284073000 | E25: 8.35 | F25: 45617 | G25: 50976 | H25: 2.0393645e+08 | I25: =VLOOKUP(B25,'KASE за 07.08.25'!$C$5:$F$173,4,0) -> 56.1603 | J25: =VLOOKUP(B25,'KASE за 07.08.25'!$C$5:$G$173,5,0) -> 56.4386 | K25: 790669.85 | L25: =D25*I25/100+K25 -> 1.6032692e+08 | M25: =L25/$L$59 -> 0.006252895 | N25: =D25*E25%/360 -> 65889.154 | O25: =K25+N25 -> 856559
A26: Министерство Финансов Республики Казахстан МЕУКАМ | B26: KZKD00000840 | C26: 500000 | D26: =C26*1000 -> 500000000 | E26: 7.68 | F26: 45526 | G26: 47518 | H26: 417099000 | I26: =VLOOKUP(B26,'KASE за 07.08.25'!$C$5:$F$162,4,0) -> 72.8713 | J26: =VLOOKUP(B26,'KASE за 07.08.25'!$C$5:$G$162,5,0) -> 76.7753 | K26: 19520000 | L26: =D26*I26/100+K26 -> 3.838765e+08 | M26: =L26/$L$59 -> 0.014971531 | N26: =D26*E26%/360 -> 106666.67 | O26: =K26+N26 -> 19626667
A27: Министерство Финансов Республики Казахстан МЕУКАМ | B27: KZKD00000840 | C27: 500000 | D27: =C27*1000 -> 500000000 | E27: 7.68 | F27: 45527 | G27: 47518 | H27: 4.1494417e+08 | I27: =VLOOKUP(B27,'KASE за 07.08.25'!$C$5:$F$162,4,0) -> 72.8713 | J27: =VLOOKUP(B27,'KASE за 07.08.25'!$C$5:$G$162,5,0) -> 76.7753 | K27: 19520000 | L27: =D27*I27/100+K27 -> 3.838765e+08 | M27: =L27/$L$59 -> 0.014971531 | N27: =D27*E27%/360 -> 106666.67 | O27: =K27+N27 -> 19626667
A28: Министерство Финансов Республики Казахстан МЕУКАМ | B28: KZKD00000840 | C28: 500000 | D28: =C28*1000 -> 500000000 | E28: 7.68 | F28: 45561 | G28: 47518 | H28: 4.2179517e+08 | I28: =VLOOKUP(B28,'KASE за 07.08.25'!$C$5:$F$162,4,0) -> 72.8713 | J28: =VLOOKUP(B28,'KASE за 07.08.25'!$C$5:$G$162,5,0) -> 76.7753 | K28: 19520000 | L28: =D28*I28/100+K28 -> 3.838765e+08 | M28: =L28/$L$59 -> 0.014971531 | N28: =D28*E28%/360 -> 106666.67 | O28: =K28+N28 -> 19626667
A29: Евразийский банк развития | B29: KZ2D00011863 | C29: 1700000 | D29: =C29*1000 -> 1700000000 | E29: 14.3 | F29: 45538 | G29: 46633 | H29: 1700000000 | I29: =VLOOKUP(B29,'Риск цены за 07.08.25'!$C$4:$G$963,4,0) -> 93.519746 | J29: =VLOOKUP(B29,'Риск цены за 07.08.25'!$C$4:$G$963,5,0) -> 106.78695 | K29: 2.2554278e+08 | L29: =D29*I29/100+K29 -> 1.8153785e+09 | M29: =L29/$L$59 -> 0.070801404 | N29: =D29*E29%/360 -> 675277.78 | O29: =K29+N29 -> 2.2621806e+08
A30: Министерство Финансов Республики Казахстан МЕУКАМ | B30: KZKD00001244 | C30: 500000 | D30: =C30*1000 -> 500000000 | E30: 12 | F30: 45540 | G30: 47901 | H30: 5.0216167e+08 | I30: =VLOOKUP(B30,'KASE за 07.08.25'!$C$5:$F$162,4,0) -> 83.7023 | J30: =VLOOKUP(B30,'KASE за 07.08.25'!$C$5:$G$162,5,0) -> 89.2023 | K30: 27500000 | L30: =D30*I30/100+K30 -> 4.460115e+08 | M30: =L30/$L$59 -> 0.017394852 | N30: =D30*E30%/360 -> 166666.67 | O30: =K30+N30 -> 27666667
A31: Министерство Финансов Республики Казахстан МЕУКАМ | B31: KZKD00001251 | C31: 300000 | D31: =C31*1000 -> 300000000 | E31: 12 | F31: 45547 | G31: 47549 | H31: 302854400 | I31: =VLOOKUP(B31,'KASE за 07.08.25'!$C$5:$F$162,4,0) -> 85.6151 | J31: =VLOOKUP(B31,'KASE за 07.08.25'!$C$5:$G$162,5,0) -> 90.6151 | K31: 15000000 | L31: =D31*I31/100+K31 -> 271845300 | M31: =L31/$L$59 -> 0.010602213 | N31: =D31*E31%/360 -> 100000 | O31: =K31+N31 -> 15100000
A32: Министерство Финансов Республики Казахстан МЕУКАМ | B32: KZKD00001251 | C32: 288579 | D32: =C32*1000 -> 288579000 | E32: 12 | F32: 45582 | G32: 47549 | H32: 2.9999932e+08 | I32: =VLOOKUP(B32,'KASE за 07.08.25'!$C$5:$F$162,4,0) -> 85.6151 | J32: =VLOOKUP(B32,'KASE за 07.08.25'!$C$5:$G$162,5,0) -> 90.6151 | K32: 14428950 | L32: =D32*I32/100+K32 -> 2.6149615e+08 | M32: =L32/$L$59 -> 0.010198587 | N32: =D32*E32%/360 -> 96193 | O32: =K32+N32 -> 14525143
A33: АО "Национальный управляющий холдинг "Байтерек" | B33: KZ2C00012698 | C33: 300000 | D33: =C33*1000 -> 300000000 | E33: 13.89 | F33: 45624 | G33: 46109 | H33: 300000000 | I33: =VLOOKUP(B33,'Риск цены за 07.08.25'!$C$4:$G$963,4,0) -> 97.812198 | J33: =VLOOKUP(B33,'Риск цены за 07.08.25'!$C$4:$G$963,5,0) -> 100.4745 | K33: 7986750 | L33: =D33*I33/100+K33 -> 3.0142334e+08 | M33: =L33/$L$59 -> 0.011755783 | N33: =D33*E33%/360 -> 115750 | O33: =K33+N33 -> 8102500
A34: Министерство Финансов Республики Казахстан МЕУКАМ | B34: KZKD00000964 | C34: =220000-213000 -> 7000 | D34: =C34*1000 -> 7000000 | E34: 8.44 | F34: 45639 | G34: 47978 | H34: =182967986.67/220000000*D34 -> 5821708.7 | I34: =VLOOKUP(B34,'KASE за 07.08.25'!$C$5:$F$162,4,0) -> 70.9505 | J34: =VLOOKUP(B34,'KASE за 07.08.25'!$C$5:$G$162,5,0) -> 72.9902 | K34: 142776.67 | L34: =D34*I34/100+K34 -> 5109311.7 | M34: =L34/$L$59 -> 0.00019926778 | N34: =D34*E34%/360 -> 1641.1111 | O34: =K34+N34 -> 144417.78
A35: Министерство Финансов Республики Казахстан МЕУКАМ | B35: KZKD00001236 | C35: =173000-163000 -> 10000 | D35: =C35*1000 -> 10000000 | E35: 14 | F35: 45639 | G35: 48353 | H35: =188266096.67/173000000*D35 -> 10882433 | I35: =VLOOKUP(B35,'KASE за 07.08.25'!$C$5:$F$162,4,0) -> 89.5882 | J35: =VLOOKUP(B35,'KASE за 07.08.25'!$C$5:$G$162,5,0) -> 92.6215 | K35: 303333.33 | L35: =D35*I35/100+K35 -> 9262153.3 | M35: =L35/$L$59 -> 0.00036123236 | N35: =D35*E35%/360 -> 3888.8889 | O35: =K35+N35 -> 307222.22
A36: Министерство Финансов Республики Казахстан МЕУКАМ | B36: KZKD00001079 | C36: 300000 | D36: =C36*1000 -> 300000000 | E36: 8.7 | F36: 45651 | G36: 50082 | H36: 237511300 | I36: =VLOOKUP(B36,'KASE за 07.08.25'!$C$5:$F$165,4,0) -> 60.3468 | J36: =VLOOKUP(B36,'KASE за 07.08.25'!$C$5:$G$165,5,0) -> 64.6001 | K36: 12760000 | L36: =D36*I36/100+K36 -> 193800400 | M36: =L36/$L$59 -> 0.007558391 | N36: =D36*E36%/360 -> 72500 | O36: =K36+N36 -> 12832500
A37: Министерство Финансов Республики Казахстан МЕУКАМ | B37: KZKD00001079 | C37: 200000 | D37: =C37*1000 -> 200000000 | E37: 8.7 | F37: 45680 | G37: 50082 | H37: 157353400 | I37: =VLOOKUP(B37,'KASE за 07.08.25'!$C$5:$F$165,4,0) -> 60.3468 | J37: =VLOOKUP(B37,'KASE за 07.08.25'!$C$5:$G$165,5,0) -> 64.6001 | K37: 8506666.7 | L37: =D37*I37/100+K37 -> 1.2920027e+08 | M37: =L37/$L$59 -> 0.0050389274 | N37: =D37*E37%/360 -> 48333.333 | O37: =K37+N37 -> 8555000
A38: Министерство Финансов Республики Казахстан МЕУКАМ | B38: KZKD00001202 | C38: 263000 | D38: =C38*1000 -> 263000000 | E38: 11 | F38: 45656 | G38: 47518 | H38: 2.6372196e+08 | I38: =VLOOKUP(B38,'KASE за 07.08.25'!$C$5:$F$162,4,0) -> 82.7361 | J38: =VLOOKUP(B38,'KASE за 07.08.25'!$C$5:$G$162,5,0) -> 88.3278 | K38: 14706083 | L38: =D38*I38/100+K38 -> 2.3230203e+08 | M38: =L38/$L$59 -> 0.0090599893 | N38: =D38*E38%/360 -> 80361.111 | O38: =K38+N38 -> 14786444
A39: Министерство Финансов Республики Казахстан МЕУКАМ | B39: KZKD00001210 | C39: 341000 | D39: =C39*1000 -> 341000000 | E39: 15.3 | F39: 45657 | G39: 47180 | H39: 396883762 | I39: =VLOOKUP(B39,'KASE за 07.08.25'!$C$5:$F$162,4,0) -> 96.1608 | J39: =VLOOKUP(B39,'KASE за 07.08.25'!$C$5:$G$162,5,0) -> 102.7058 | K39: 22318450 | L39: =D39*I39/100+K39 -> 350226778 | M39: =L39/$L$59 -> 0.013659161 | N39: =D39*E39%/360 -> 144925 | O39: =K39+N39 -> 22463375
A40: Министерство Финансов Республики Казахстан МЕУКАМ | B40: KZKD00001095 | C40: =214727-132000 -> 82727 | D40: =C40*1000 -> 82727000 | E40: 10.47 | F40: 45673 | G40: 47053 | H40: 77053072 | I40: =VLOOKUP(B40,'KASE за 07.08.25'!$C$5:$F$162,4,0) -> 85.1951 | J40: =VLOOKUP(B40,'KASE за 07.08.25'!$C$5:$G$162,5,0) -> 93.3384 | K40: 6736735.4 | L40: =D40*I40/100+K40 -> 77216086 | M40: =L40/$L$59 -> 0.0030114972 | N40: =D40*E40%/360 -> 24059.769 | O40: =K40+N40 -> 6760795.1
A41: Министерство Финансов Республики Казахстан МЕУКАМ | B41: KZKD00000790 | C41: 227500 | D41: =C41*1000 -> 227500000 | E41: 7.68 | F41: 45702 | G41: 47343 | H41: 1.8902823e+08 | I41: =VLOOKUP(B41,'KASE за 07.08.25'!$C$5:$F$162,4,0) -> 75.0736 | J41: =VLOOKUP(B41,'KASE за 07.08.25'!$C$5:$G$162,5,0) -> 82.6256 | K41: 17180800 | L41: =D41*I41/100+K41 -> 1.8797324e+08 | M41: =L41/$L$59 -> 0.0073311265 | N41: =D41*E41%/360 -> 48533.333 | O41: =K41+N41 -> 17229333
A42: Министерство Финансов Республики Казахстан | B42: KZKD00000717 | C42: 500000 | D42: =C42*1000 -> 500000000 | E42: 7.22 | F42: 45729 | G42: 47097 | H42: 3.9979333e+08 | I42: =VLOOKUP(B42,'KASE за 07.08.25'!$C$5:$F$162,4,0) -> 76.9583 | J42: =VLOOKUP(B42,'KASE за 07.08.25'!$C$5:$G$162,5,0) -> 81.7115 | K42: 23765833 | L42: =D42*I42/100+K42 -> 4.0855733e+08 | M42: =L42/$L$59 -> 0.015934106 | N42: =D42*E42%/360 -> 100277.78 | O42: =K42+N42 -> 23866111
A43: Министерство Финансов Республики Казахстан | B43: KZKD00001210 | C43: 259000 | D43: =C43*1000 -> 259000000 | E43: 15.3 | F43: 45750 | G43: 47180 | H43: 260647240 | I43: =VLOOKUP(B43,'KASE за 07.08.25'!$C$5:$F$162,4,0) -> 96.1608 | J43: =VLOOKUP(B43,'KASE за 07.08.25'!$C$5:$G$162,5,0) -> 102.7058 | K43: 16951550 | L43: =D43*I43/100+K43 -> 266008022 | M43: =L43/$L$59 -> 0.010374554 | N43: =D43*E43%/360 -> 110075 | O43: =K43+N43 -> 17061625
A44: АО "Национальный управляющий холдинг "Байтерек" | B44: KZ2C00012268 | C44: 200000 | D44: =C44*1000 -> 200000000 | E44: 16.7 | F44: 45757 | G44: 46122 | H44: 200000000 | I44: =VLOOKUP(B44,'Риск цены за 07.08.25'!$C$4:$G$963,4,0) -> 99.320933 | J44: =VLOOKUP(B44,'Риск цены за 07.08.25'!$C$4:$G$963,5,0) -> 104.74843 | K44: 10855000 | L44: =D44*I44/100+K44 -> 2.0949687e+08 | M44: =L44/$L$59 -> 0.0081705674 | N44: =D44*E44%/360 -> 92777.778 | O44: =K44+N44 -> 10947778
A45: Министерство Финансов Республики Казахстан | B45: KZKD00000477 | C45: 500000 | D45: =C45*1000 -> 500000000 | E45: 5.3 | F45: 45764 | G45: 46679 | H45: 4.1207678e+08 | I45: =VLOOKUP(B45,'KASE за 07.08.25'!$C$5:$F$162,4,0) -> 80.1411 | J45: =VLOOKUP(B45,'KASE за 07.08.25'!$C$5:$G$162,5,0) -> 84.3811 | K45: 21200000 | L45: =D45*I45/100+K45 -> 4.219055e+08 | M45: =L45/$L$59 -> 0.016454696 | N45: =D45*E45%/360 -> 73611.111 | O45: =K45+N45 -> 21273611
A46: Министерство Финансов Республики Казахстан | B46: KZKD00001202 | C46: 737000 | D46: =C46*1000 -> 737000000 | E46: 11 | F46: 45771 | G46: 47518 | H46: 6.4967099e+08 | I46: =VLOOKUP(B46,'KASE за 07.08.25'!$C$5:$F$162,4,0) -> 82.7361 | J46: =VLOOKUP(B46,'KASE за 07.08.25'!$C$5:$G$162,5,0) -> 88.3278 | K46: 41210583 | L46: =D46*I46/100+K46 -> 6.5097564e+08 | M46: =L46/$L$59 -> 0.025388639 | N46: =D46*E46%/360 -> 225194.44 | O46: =K46+N46 -> 41435778
A47: Министерство Финансов Республики Казахстан | B47: KZKD00001129 | C47: 6000 | D47: =C47*1000 -> 6000000 | E47: 10.3 | F47: 45775 | G47: 47924 | H47: 4822485.3 | I47: =VLOOKUP(B47,'KASE за 07.08.25'!$C$5:$F$162,4,0) -> 77.8037 | J47: =VLOOKUP(B47,'KASE за 07.08.25'!$C$5:$G$162,5,0) -> 81.8093 | K47: 240333.33 | L47: =D47*I47/100+K47 -> 4908555.3 | M47: =L47/$L$59 -> 0.0001914381 | N47: =D47*E47%/360 -> 1716.6667 | O47: =K47+N47 -> 242050
A48: Министерство Финансов Республики Казахстан | B48: KZKD00001129 | C48: 6000 | D48: =C48*1000 -> 6000000 | E48: 10.3 | F48: 45775 | G48: 47924 | H48: 4841157.3 | I48: =VLOOKUP(B48,'KASE за 07.08.25'!$C$5:$F$162,4,0) -> 77.8037 | J48: =VLOOKUP(B48,'KASE за 07.08.25'!$C$5:$G$162,5,0) -> 81.8093 | K48: 240333.33 | L48: =D48*I48/100+K48 -> 4908555.3 | M48: =L48/$L$59 -> 0.0001914381 | N48: =D48*E48%/360 -> 1716.6667 | O48: =K48+N48 -> 242050
A49: АО "Банк Развития Казахстана" | B49: KZ2C00010106 | C49: 500000 | D49: =C49*1000 -> 500000000 | E49: 17 | F49: 45782 | G49: 46147 | H49: 500000000 | I49: 100 | J49: 100 | K49: 21722222 | L49: =D49*I49/100+K49 -> 5.2172222e+08 | M49: =L49/$L$59 -> 0.020347639 | N49: =D49*E49%/360 -> 236111.11 | O49: =K49+N49 -> 21958333
A50: Министерство Финансов Республики Казахстан | B50: KZKD00000964 | C50: 500000 | D50: =C50*1000 -> 500000000 | E50: 8.44 | F50: 45799 | G50: 47978 | H50: 3.7223717e+08 | I50: =VLOOKUP(B50,'KASE за 07.08.25'!$C$5:$F$165,4,0) -> 70.9505 | J50: =VLOOKUP(B50,'KASE за 07.08.25'!$C$5:$G$165,5,0) -> 72.9902 | K50: 10198333 | L50: =D50*I50/100+K50 -> 3.6495083e+08 | M50: =L50/$L$59 -> 0.014233413 | N50: =D50*E50%/360 -> 117222.22 | O50: =K50+N50 -> 10315556
A51: Министерство Финансов Республики Казахстан | B51: KZKD00000790 | C51: 500000 | D51: =C51*1000 -> 500000000 | E51: 7.68 | F51: 45813 | G51: 47343 | H51: 4.0360417e+08 | I51: =VLOOKUP(B51,'KASE за 07.08.25'!$C$5:$F$165,4,0) -> 75.0736 | J51: =VLOOKUP(B51,'KASE за 07.08.25'!$C$5:$G$165,5,0) -> 82.6256 | K51: 37760000 | L51: =D51*I51/100+K51 -> 4.13128e+08 | M51: =L51/$L$59 -> 0.016112366 | N51: =D51*E51%/360 -> 106666.67 | O51: =K51+N51 -> 37866667
A52: Министерство Финансов Республики Казахстан | B52: KZKD00000543 | C52: 500000 | D52: =C52*1000 -> 500000000 | E52: 5 | F52: 45813 | G52: 46861 | H52: 3.7940239e+08 | I52: =VLOOKUP(B52,'KASE за 07.08.25'!$C$5:$F$165,4,0) -> 75.9721 | J52: =VLOOKUP(B52,'KASE за 07.08.25'!$C$5:$G$165,5,0) -> 77.486 | K52: 7569444.4 | L52: =D52*I52/100+K52 -> 3.8742994e+08 | M52: =L52/$L$59 -> 0.015110119 | N52: =D52*E52%/360 -> 69444.444 | O52: =K52+N52 -> 7638888.9
A53: Министерство Финансов Республики Казахстан | B53: KZKD00001160 | C53: 200000 | D53: =C53*1000 -> 200000000 | E53: 10.55 | F53: 45820 | G53: 47327 | H53: 1.8266529e+08 | I53: =VLOOKUP(B53,'KASE за 07.08.25'!$C$5:$F$165,4,0) -> 83.1474 | J53: =VLOOKUP(B53,'KASE за 07.08.25'!$C$5:$G$165,5,0) -> 83.4112 | K53: 527500 | L53: =D53*I53/100+K53 -> 166822300 | M53: =L53/$L$59 -> 0.0065062207 | N53: =D53*E53%/360 -> 58611.111 | O53: =K53+N53 -> 586111.11
A54: Министерство Финансов Республики Казахстан | B54: KZKD00001251 | C54: 500000 | D54: =C54*1000 -> 500000000 | E54: 12 | F54: 45832 | G54: 47549 | H54: 4.4701683e+08 | I54: =VLOOKUP(B54,'KASE за 07.08.25'!$C$5:$F$165,4,0) -> 85.6151 | J54: =VLOOKUP(B54,'KASE за 07.08.25'!$C$5:$G$165,5,0) -> 90.6151 | K54: 25000000 | L54: =D54*I54/100+K54 -> 4.530755e+08 | M54: =L54/$L$59 -> 0.017670355 | N54: =D54*E54%/360 -> 166666.67 | O54: =K54+N54 -> 25166667
A55: Министерство Финансов Республики Казахстан | B55: KZKD00001251 | C55: 500000 | D55: =C55*1000 -> 500000000 | E55: 12 | F55: 45832 | G55: 47549 | H55: 4.4561733e+08 | I55: =VLOOKUP(B55,'KASE за 07.08.25'!$C$5:$F$165,4,0) -> 85.6151 | J55: =VLOOKUP(B55,'KASE за 07.08.25'!$C$5:$G$165,5,0) -> 90.6151 | K55: 25000000 | L55: =D55*I55/100+K55 -> 4.530755e+08 | M55: =L55/$L$59 -> 0.017670355 | N55: =D55*E55%/360 -> 166666.67 | O55: =K55+N55 -> 25166667
A56: Министерство Финансов Республики Казахстан | B56: KZKD00001251 | C56: 411421 | D56: =C56*1000 -> 411421000 | E56: 12 | F56: 45832 | G56: 47549 | H56: 3.6376844e+08 | I56: =VLOOKUP(B56,'KASE за 07.08.25'!$C$5:$F$165,4,0) -> 85.6151 | J56: =VLOOKUP(B56,'KASE за 07.08.25'!$C$5:$G$165,5,0) -> 90.6151 | K56: 20571050 | L56: =D56*I56/100+K56 -> 3.7280955e+08 | M56: =L56/$L$59 -> 0.01453991 | N56: =D56*E56%/360 -> 137140.33 | O56: =K56+N56 -> 20708190
A57: Министерство Финансов Республики Казахстан | B57: KZKD00001301 | C57: 500000 | D57: =C57*1000 -> 500000000 | E57: 14.45 | F57: 45848 | G57: 48735 | H57: 4.5341681e+08 | I57: =VLOOKUP(B57,'KASE за 07.08.25'!$C$5:$F$165,4,0) -> 90.6911 | J57: =VLOOKUP(B57,'KASE за 07.08.25'!$C$5:$G$165,5,0) -> 93.1797 | K57: 12443056 | L57: =D57*I57/100+K57 -> 4.6589856e+08 | M57: =L57/$L$59 -> 0.018170465 | N57: =D57*E57%/360 -> 200694.44 | O57: =K57+N57 -> 12643750
A58: Министерство Финансов Республики Казахстан | B58: KZKD00000964 | C58: 500000 | D58: =C58*1000 -> 500000000 | E58: 8.44 | F58: 45862 | G58: 47978 | H58: 3.5788194e+08 | I58: =VLOOKUP(B58,'KASE за 07.08.25'!$C$5:$F$165,4,0) -> 70.9505 | J58: =VLOOKUP(B58,'KASE за 07.08.25'!$C$5:$G$165,5,0) -> 72.9902 | K58: 10198333 | L58: =D58*I58/100+K58 -> 3.6495083e+08 | M58: =L58/$L$59 -> 0.014233413 | N58: =D58*E58%/360 -> 117222.22 | O58: =K58+N58 -> 10315556
A59: ИТОГО | C59: =SUM(C6:C58) -> 31893061 | D59: =SUM(D6:D58) -> 31893061000 | H59: =SUM(H6:H58) -> 2.7348601e+10 | K59: =SUM(K6:K58) -> 1.1498212e+09 | L59: =SUM(L6:L58) -> 2.564043e+10 | M59: =SUM(M6:M58) -> 1 | N59: 2.564043e+10 | O59: =L59-N59 -> 0
A61: Остатки на инвест. cчетах
A62: KZT | B62: 801094.88 | C62: 801094.88 | D62: =B62-C62 -> 0
A64: Обратное репо
A65: Наименование эмитента и вид ЦБ | B65: НИН (ISIN) | C65: Количество | D65: Валюта | E65: Дата открытия | F65: Дата закрытия | G65: Цена открытия | H65: Цена закрытия | I65: Сумма открытия операции. в тг | J65: Сумма закрытия операции. в тг | K65: Ставка доходности. % | L65: Сумма начисленного вознагрждения | M65: Суммарная текущая стоимость. в тг
A66: Министерство Финансов Республики Казахстан | B66: XS2914770545 | C66: 3360955 | D66: KZT | E66: 45875 | F66: 45876 | G66: 530.5182 | H66: 530.74436 | I66: 1.7830478e+09 | J66: 1.7838079e+09 | K66: 15.5601 | L66: =IF(($B$1-E66)=0,0,(J66-I66)/(F66-E66)*($B$1-E66)) -> 760120.6 | M66: =IF((F66=$B$1),0,(I66+L66)) -> 0
A67: Министерство Финансов Республики Казахстан | B67: XS2914770545 | C67: 22620 | D67: KZT | E67: 45875 | F67: 45876 | G67: 530.5182 | H67: 530.74436 | I67: 12000322 | J67: 12005437 | K67: 15.560111 | L67: =IF(($B$1-E67)=0,0,(J67-I67)/(F67-E67)*($B$1-E67)) -> 5115.79 | M67: =IF((F67=$B$1),0,(I67+L67)) -> 0
A68: Министерство Финансов Республики Казахстан | B68: KZKD00000717 | C68: 2183616 | D68: KZT | E68: 45876 | F68: 45877 | G68: 817.115 | H68: 817.46289 | I68: 1.7842654e+09 | J68: 1.785025e+09 | K68: 15.54 | L68: =IF(($B$1-E68)=0,0,(J68-I68)/(F68-E68)*($B$1-E68)) -> 0 | M68: =IF((F68=$B$1),0,(I68+L68)) -> 1.7842654e+09
A69: Министерство Финансов Республики Казахстан | B69: KZKD00000717 | C69: 13464 | D69: KZT | E69: 45876 | F69: 45877 | G69: 817.115 | H69: 817.46289 | I69: 11001636 | J69: 11006320 | K69: 15.539986 | L69: =IF(($B$1-E69)=0,0,(J69-I69)/(F69-E69)*($B$1-E69)) -> 0 | M69: =IF((F69=$B$1),0,(I69+L69)) -> 11001636
A71: ИТОГО | C71: =SUM(C66:C69) -> 5580655 | I71: =SUM(I66:I69) -> 3.5903151e+09 | J71: =SUM(J66:J69) -> 3.5918447e+09 | L71: =SUM(L66:L69) -> 765236.39 | M71: =SUM(M66:M69) -> 1.795267e+09 | N71: 1.795267e+09 | O71: =M71-N71 -> 0
A74: Прочие активы (дебиторская задолженность. деньги в пути)
A75: № п/п | B75: Наименование | C75: Валюта | D75: Дата постановки на учет | E75: Количество | F75: Остаток в валюте | G75: Остаток в тенге
A77: ИТОГО | G77: =SUM(G76:G76) -> 0
A79: Итого активов | B79: =L59+B62+M71+G77 -> 2.7436499e+10 | C79: 2.7436499e+10 | D79: =B79-C79 -> 0
A83: 2) Кредиторская задолженность Фонда
A84: Комиссия ДУ (за управление) | B84: 4020961.4
A85: Комиссия ДУ (сверхдоходность)
A86: Комиссия Кастоди | B86: =2000+3000+5000+7000+2000+4000+3000+5000+2000+3000+3000+2000+2000+24000+2000+6000+2000+2000+2000+2000+351673.18+71000+2000+6000+2000+3000+2000+3000+2000+2000+2000+2000-434673.18+2000+2000+2000+2000+2000+3000+3000+4000+3000+2000+2000+342960.79+2000+2000+12000+2000+2000 -> 486960.79
A87: Комиссия Глобал кастоди
A88: Комиссия Центрального Депозитария | B88: 365447.82
A89: Клиринговый сбор | B89: =4083.63+3230.48+3265.02+12872.21+3281.52+3247.37+2574.32+7640.52+2575.08+2576.75+2575.88+2577.32+7662+2583.06+2582.99+2585.09+2053.2+6452.61+2743.63+2707.86+2708.65+2708.58+8059.51+2714.35+2877.07+2713.89+2715.72 -> 104368.31
A90: Комиссия биржи | B90: =1606.55+1607.59+1608.19+6436.1+1611.94+1612.29+46613.68+3820.27+1275.38+1275.47+1276.53+1276.5+3831+1278.62+1279.34+1280.38+36800.38+3224.64+1340.74+1341.77+1342.17+1342.88+4029.76+1345.03+1345.6+1346.29+1346.45 -> 132495.54
A91: Комиссия брокера
A92: Кредиторская задолженность (прочая комиссия)
A93: Остаток прочих обязательств на конец дня
A94: Итого | B94: =SUM(B84:B93) -> 5110233.8

Sheet KASE за 07.08.25
A1: Дата оценки | B1: 45876
A3: № п/п | B3: Код | C3: ISIN | D3: Вид ценной бумаги | E3: Компания | F3: Рыночная цена | G3: Рыночная "грязная" цена | H3: Доходность до погашения, % годовых | I3: Срок до погашения | J3: Единица измерения цены
A5: 1 | B5: 1AIRA | C5: KZ1C00004050 | D5: акции | E5: Эйр Астана | F5: 740.72 | G5: – | H5: – | I5: – | J5: KZT
A6: 2 | B6: 2AIRAd | C6: US0090632078 | D6: производные ЦБ | E6: Эйр Астана | F6: 5.61 | G6: – | H6: – | I6: – | J6: USD
A7: 3 | B7: 3AKZM | C7: KZ1C00001288 | D7: акции | E7: Актюбинский завод металлоконструкций | F7: 6266.18 | G7: – | H7: – | I7: – | J7: KZT
A8: 4 | B8: 4ALMSb1 | C8: KZ2C00012953 | D8: долговые ЦБ | E8: АК Алтыналмас | F8: 100.0225 | G8: 100.9336 | H8: 7,99 | I8: 859 (2) | J8: %
A9: 5 | B9: 5BCCIbe | C9: KZPF00000553 | D9: ЦБ инвест. фондов | E9: BCC Invest | F9: 1455.09 | G9: – | H9: – | I9: – | J9: KZT
A10: 6 | B10: 6BCCIrb | C10: KZPF00000231 | D10: ЦБ инвест. фондов | E10: BCC Invest | F10: 6.77 | G10: – | H10: – | I10: – | J10: KZT
A11: 7 | B11: 7BIGDb5 | C11: KZ2D00012861 | D11: долговые ЦБ | E11: Частная компания BI Development Ltd. | F11: 100.8085 | G11: 104.4918 | H11: 18,88 | I11: 652 (2) | J11: %
A12: 8 | B12: 8BRKZe18 | C12: XS3032932645 | D12: долговые ЦБ | E12: Банк Развития Казахстана | F12: 101.4645 | G12: 103.3395 | H12: 5,27 | I12: 1 680 (5) | J12: %
A13: 9 | B13: 9BRKZe4 | C13: XS0248160102 | D13: долговые ЦБ | E13: Банк Развития Казахстана | F13: 99.8281 | G13: 102.0614 | H13: 6,27 | I13: 226 (1) | J13: %
A14: 10 | B14: 10BTRKe1 | C14: XS3067899610 | D14: долговые ЦБ | E14: Национальный управляющий холдинг "Байтерек" | F14: 101.1766 | G14: 102.524 | H14: 4,98 | I14: 991 (3) | J14: %
A15: 11 | B15: 11CCBN | C15: KZ0007786572 | D15: акции | E15: Банк ЦентрКредит | F15: 3697.3 | G15: – | H15: – | I15: – | J15: KZT
A16: 12 | B16: 12CCBNp | C16: KZ000A0H0930 | D16: акции | E16: Банк ЦентрКредит | F16: 5430.25 | G16: – | H16: – | I16: – | J16: KZT
A17: 13 | B17: 13CSECfe | C17: KZPF00000025 | D17: ЦБ инвест. фондов | E17: Сентрас Секьюритиз | F17: 5928926.6 | G17: – | H17: – | I17: – | J17: KZT
A18: 14 | B18: 14CSECtf | C18: KZPF00000280 | D18: ЦБ инвест. фондов | E18: Сентрас Секьюритиз | F18: 1718841.4 | G18: – | H18: – | I18: – | J18: KZT
A19: 15 | B19: 15EABRb40 | C19: KZ2D00009628 | D19: ЦБ МФО | E19: Евразийский банк развития | F19: 99.6766 | G19: 101.8534 | H19: 6,25 | I19: 223 (1) | J19: %
A20: 16 | B20: 16EABRb42 | C20: KZ2D00009222 | D20: ЦБ МФО | E20: Евразийский банк развития | F20: 100 | G20: 107.2568 | H20: 16,24 | I20: 932 (3) | J20: %
A21: 17 | B21: 17EABRb53 | C21: KZ2D00013620 | D21: ЦБ МФО | E21: Евразийский банк развития | F21: 100 | G21: 106.3767 | H21: 17,46 | I21: 963 (3) | J21: %
A22: 18 | B22: 18FFIN_or | C22: KZPF00000082 | D22: ЦБ инвест. фондов | E22: Фридом Финанс | F22: 89325.7 | G22: – | H22: – | I22: – | J22: KZT
A23: 19 | B23: 19FFINgw | C23: KZPF00000090 | D23: ЦБ инвест. фондов | E23: Фридом Финанс | F23: 5370.98 | G23: – | H23: – | I23: – | J23: KZT
A24: 20 | B24: 20FHJIag | C24: KZPF00000132 | D24: ЦБ инвест. фондов | E24: Alatau City Invest | F24: 1017.55 | G24: – | H24: – | I24: – | J24: USD
A25: 21 | B25: 21FHJIpc | C25: KZPF00000140 | D25: ЦБ инвест. фондов | E25: Alatau City Invest | F25: 1159.13 | G25: – | H25: – | I25: – | J25: USD
A26: 22 | B26: 22FPSTb5 | C26: KZ2P00011778 | D26: долговые ЦБ | E26: BASS Gold | F26: 89.4062 | G26: 94.0812 | H26: 22,60 | I26: 387 (1) | J26: %
A27: 23 | B27: 23HCBNb13 | C27: KZ2C00011195 | D27: долговые ЦБ | E27: Home Credit Bank | F27: 99.7625 | G27: 107.8292 | H27: 18,25 | I27: 920 (3) | J27: %
A28: 24 | B28: 24HFINhl | C28: KZPF00000538 | D28: ЦБ инвест. фондов | E28: Halyk Finance | F28: 53357.87 | G28: – | H28: – | I28: – | J28: KZT
A29: 25 | B29: 25HFINhp | C29: KZPF00000546 | D29: ЦБ инвест. фондов | E29: Halyk Finance | F29: 73742.74 | G29: – | H29: – | I29: – | J29: KZT
A30: 26 | B30: 26HFINhs | C30: KZPF00000520 | D30: ЦБ инвест. фондов | E30: Halyk Finance | F30: 72902.15 | G30: – | H30: – | I30: – | J30: KZT
A31: 27 | B31: 27HFINhv | C31: KZPF00000041 | D31: ЦБ инвест. фондов | E31: Halyk Finance | F31: 580696.53 | G31: – | H31: – | I31: – | J31: KZT
A32: 28 | B32: 28HSBK | C32: KZ000A0LE0S4 | D32: акции | E32: Народный Банк Казахстана | F32: 334.25 | G32: – | H32: – | I32: – | J32: KZT
A33: 29 | B33: 29HSBKd | C33: US46627J3023 | D33: производные ЦБ | E33: Народный Банк Казахстана | F33: 24.81 | G33: – | H33: – | I33: – | J33: USD
A34: 30 | B34: 30IFDR | C34: KZ1C00000256 | D34: акции | E34: Teniz Capital Investment Banking | F34: 9455.19 | G34: – | H34: – | I34: – | J34: KZT
A35: 31 | B35: 31KCEL | C35: KZ1C00000876 | D35: акции | E35: Kcell | F35: 3392.89 | G35: – | H35: – | I35: – | J35: KZT
A36: 32 | B36: 32KEGC | C36: KZ1C00000959 | D36: акции | E36: KEGOC | F36: 1445.8 | G36: – | H36: – | I36: – | J36: KZT
A37: 33 | B37: 33KMGZ | C37: KZ1C00001122 | D37: акции | E37: Национальная компания "КазМунайГаз" | F37: 20034.87 | G37: – | H37: – | I37: – | J37: KZT
A38: 34 | B38: 34KMGZe12 | C38: XS1595714087 | D38: долговые ЦБ | E38: Национальная компания "КазМунайГаз" | F38: 88.2751 | G38: 90.0001 | H38: 6,79 | I38: 7 812 (22) | J38: %
A39: 35 | B39: 35KMGZe14 | C39: XS1807300105 | D39: долговые ЦБ | E39: Национальная компания "КазМунайГаз" | F39: 101.6075 | G39: 103.1453 | H39: 4,99 | I39: 1 697 (5) | J39: %
A40: 36 | B40: 36KMGZe15 | C40: XS1807299331 | D40: долговые ЦБ | E40: Национальная компания "КазМунайГаз" | F40: 94.1216 | G40: 95.9456 | H40: 6,89 | I40: 8 357 (23) | J40: %
A41: 37 | B41: 37KMGZe16 | C41: XS2242422397 | D41: долговые ЦБ | E41: Национальная компания "КазМунайГаз" | F41: 87.8326 | G41: 88.9312 | H41: 5,46 | I41: 2 767 (8) | J41: %
A42: 38 | B42: 38KSPI | C42: KZ1C00001536 | D42: акции | E42: Kaspi.kz | F42: 48221.69 | G42: – | H42: – | I42: – | J42: KZT
A43: 39 | B43: 39KSPId | C43: US48581R2058 | D43: производные ЦБ | E43: Kaspi.kz | F43: 84.67 | G43: – | H43: – | I43: – | J43: USD
A44: 40 | B44: 40KZAP | C44: KZ1C00001619 | D44: акции | E44: Национальная атомная компания "Казатомпром" | F44: 22972.51 | G44: – | H44: – | I44: – | J44: KZT
A45: 41 | B45: 41KZTCb3 | C45: KZ2C00012961 | D45: долговые ЦБ | E45: Jusan Mobile | F45: 104.1934 | G45: 112.749 | H45: 19,82 | I45: 940 (3) | J45: %
A46: 42 | B46: 42KZTK | C46: KZ0009093241 | D46: акции | E46: Казахтелеком | F46: 40970.83 | G46: – | H46: – | I46: – | J46: KZT
A47: 43 | B47: 43KZTKp | C47: KZ0009094645 | D47: акции | E47: Казахтелеком | F47: 33371.49 | G47: – | H47: – | I47: – | J47: KZT
A48: 44 | B48: 44KZTO | C48: KZ1C00000744 | D48: акции | E48: КазТрансОйл | F48: 809.16 | G48: – | H48: – | I48: – | J48: KZT
A49: 45 | B49: 45KZ_23_3504 | C49: XS2914770545 | D49: ГЦБ | E49: Минфин | F49: 97.5 | G49: 99.0451 | H49: 5,04 | I49: 3 482 (10) | J49: %
A50: 46 | B50: 46MFACb3 | C50: KZ2P00014434 | D50: долговые ЦБ | E50: МФО "Арнур Кредит" | F50: 98.3795 | G50: 98.7684 | H50: 21,01 | I50: 713 (2) | J50: %
A51: 47 | B51: 47MFMCb2 | C51: KZ2P00011968 | D51: долговые ЦБ | E51: МФО MyCar Finance | F51: 98.8181 | G51: 102.8528 | H51: 18,50 | I51: 457 (1) | J51: %
A52: 48 | B52: 48MFMOb10 | C52: KZ2P00012651 | D52: долговые ЦБ | E52: МФО "Mogo Kazakhstan (Мого Казахстан) | F52: 77.725 | G52: 80.5583 | H52: 34,47 | I52: 455 (1) | J52: %
A53: 49 | B53: 49MFMOb17 | C53: KZ2P00013329 | D53: долговые ЦБ | E53: МФО "Mogo Kazakhstan (Мого Казахстан) | F53: 76.05 | G53: 76.5833 | H53: 66,00 | I53: 194 (1) | J53: %
A54: 50 | B54: 50MFMOb23 | C54: KZ2P00013154 | D54: долговые ЦБ | E54: МФО "Mogo Kazakhstan (Мого Казахстан) | F54: 99.9989 | G54: 101.2822 | H54: 22,00 | I54: 639 (2) | J54: %
A55: 51 | B55: 51MFMOb26 | C55: KZ2P00013204 | D55: долговые ЦБ | E55: МФО "Mogo Kazakhstan (Мого Казахстан) | F55: 100.5 | G55: 101.2 | H55: 11,69 | I55: 639 (2) | J55: %
A56: 52 | B56: 52MFMOb28 | C56: KZ2P00013352 | D56: долговые ЦБ | E56: МФО "Mogo Kazakhstan (Мого Казахстан) | F56: 99.9899 | G56: 100.5566 | H56: 12,01 | I56: 673 (2) | J56: %
A57: 53 | B57: 53MFOKb16 | C57: KZ2C00010171 | D57: долговые ЦБ | E57: МФО ОнлайнКазФинанс | F57: 100.3049 | G57: 101.7347 | H57: 21,20 | I57: 97 (0) | J57: %
A58: 54 | B58: 54MFOKb18 | C58: KZ2C00010478 | D58: долговые ЦБ | E58: МФО ОнлайнКазФинанс | F58: 99.3632 | G58: 99.9743 | H58: 20,96 | I58: 259 (1) | J58: %
A59: 55 | B59: 55MFOKb19 | C59: KZ2C00010825 | D59: долговые ЦБ | E59: МФО ОнлайнКазФинанс | F59: 99.4446 | G59: 99.9724 | H59: 10,38 | I59: 581 (2) | J59: %
A60: 56 | B60: 56MFOKb20 | C60: KZ2C00010916 | D60: долговые ЦБ | E60: МФО ОнлайнКазФинанс | F60: 99.7197 | G60: 101.0446 | H60: 21,85 | I60: 728 (2) | J60: %
... A174: 170 | B174: 170SKKZe1 | C174: XS2399149694 | D174: долговые ЦБ | E174: Фонд национального благосостояния "Самрук-Қазына | F174: 96.4002 | G174: 96.9502 | H174: 5,07 | I174: 441 (1) | J174: %

Sheet Риск цены за 07.08.25
A1: Дата оценки | C1: 45876
A3: № п/п | B3: Торговый код | C3: ISIN | D3: Алгоритмы и параметры расчета ЦБ | E3: Краткое наименование эмитента | F3: Расчетная цена | G3: Расчетная грязная | H3: Доходность до погашения. % годовых | I3: Дней до погашения | J3: Единица измерения цены
A4: 1 | B4: AAFD | C4: KZ1C00008721 | D4: Акции | E4: АО "АзияАгроФуд" | F4: 100 | G4: 100 | H4: 0 | I4: 0 | J4: KZT
A5: 2 | B5: AAL_KZ | C5: US02376R1023 | D5: Акции | E5: American Airlines | F5: 6177.915 | G5: 6177.915 | H5: 0 | I5: 0 | J5: KZT
A6: 3 | B6: AAPL_KZ | C6: US0378331005 | D6: Акции | E6: Apple Inc. | F6: 113012.87 | G6: 113012.87 | H6: 0 | I6: 0 | J6: KZT
A7: 4 | B7: ABK022_210 | C7: KZMJ00002103 | D7: Облигации | E7: Акимат Актюбинской области | F7: 100 | G7: 100.9799 | H7: 4.23 | I7: 397 | J7: %
A8: 5 | B8: ABK024_183 | C8: KZMJ00001832 | D8: Облигации | E8: Акимат Актюбинской области | F8: 100 | G8: 100.0671 | H8: 0.35 | I8: 291 | J8: %
A9: 6 | B9: ABK114_193 | C9: KZMJ00001931 | D9: Облигации | E9: Акимат Актюбинской области | F9: 100 | G9: 100.0173 | H9: 0.02 | I9: 3113 | J9: %
A10: 7 | B10: ABK119_006 | C10: KZMF00000069 | D10: Облигации | E10: Акимат Актюбинской области | F10: 100 | G10: 100.7117 | H10: 6.08 | I10: 1728 | J10: %
A11: 8 | B11: ABK119_081 | C11: KZMF00000812 | D11: Облигации | E11: Акимат Актюбинской области | F11: 100 | G11: 105.5222 | H11: 7.08 | I11: 2210 | J11: %
A12: 9 | B12: ABK131_021 | C12: KZMF00000218 | D12: Облигации | E12: Акимат Актюбинской области | F12: 100 | G12: 105.9814 | H12: 6.09 | I12: 2137 | J12: %
A13: 10 | B13: ABK143_032 | C13: KZMF00000325 | D13: Облигации | E13: Акимат Актюбинской области | F13: 100 | G13: 104.8292 | H13: 6.08 | I13: 2565 | J13: %
A14: 11 | B14: ABK143_033 | C14: KZMF00000333 | D14: Облигации | E14: Акимат Актюбинской области | F14: 100 | G14: 104.8292 | H14: 6.08 | I14: 2565 | J14: %
A15: 12 | B15: ABT_KZ | C15: US0028241000 | D15: Акции | E15: Abbott Lab. | F15: 70119.335 | G15: 70119.335 | H15: 0 | I15: 0 | J15: KZT
... A1008: 1005 | B1008: ZKK143_044 | C1008: KZMF00000440 | D1008: Облигации | E1008: Акимат Западно-Казахстанской области | F1008: 100 | G1008: 104.8292 | H1008: 6.08 | I1008: 2565 | J1008: %
