Workbook

Sheet ДУ
A1: Сентрас Секьюритиз | B1: 45899
A2: 1) Активы
A4: ЦБ
A5: Наименование эмитента и вид ЦБ | B5: ISIN | C5: Количество ЦБ | D5: Номинальная стоимость. тенге | E5: Ставка | F5: Дата зачисления/приобретения | G5: Дата погашения | H5: Чистая покупная стоимоcть | I5: Расчетная цена на 30.08.25 | J5: Расчетная грязная цена 30.08.25 | K5: Накопленный купон | L5: Суммарно-текущая рыночная стоимость | M5: Вес
A6: Министерство Финансов Республики Казахстан купонные МЕУКАМ | B6: KZKD00000535 | C6: =3250000-500000-500000-500000 -> 1750000 | D6: =3250000000-500000000-500000000-500000000 -> 1750000000 | E6: 5.49 | F6: 45491 | G6: 27.03.2027 | H6: =2755458875/3250000000*D6 -> 1483708625 | I6: =VLOOKUP(B6,'KASE за 29.08.25'!$C$5:$F$162,4,0) -> 84.702 | J6: =VLOOKUP(B6,'KASE за 29.08.25'!$C$5:$G$162,5,0) -> 87.02 | K6: 40831875 | L6: =D6*I6/100+K6 -> 1523116875 | M6: =L6/$L$62 -> 0.057809759 | N6: =D6*E6%/360 -> 266875 | O6: =K6+N6 -> 41098750
A7: Министерство Финансов Республики Казахстан купонные МЕУКАМ | B7: KZKD00001137 | C7: 1950000 | D7: 1950000000 | E7: 10.4 | F7: 45491 | G7: 12.04.2028 | H7: 1838876000 | I7: =VLOOKUP(B7,'KASE за 29.08.25'!$C$5:$F$162,4,0) -> 86.3159 | J7: =VLOOKUP(B7,'KASE за 29.08.25'!$C$5:$G$162,5,0) -> 90.2737 | K7: 77740000 | L7: =D7*I7/100+K7 -> 1760900050 | M7: =L7/$L$62 -> 0.066834797 | N7: =D7*E7%/360 -> 563333.33 | O7: =K7+N7 -> 78303333
A8: Министерство Финансов Республики Казахстан МЕУКАМ | B8: KZKD00001087 | C8: =1950000-202300-182000-187350 -> 1378350 | D8: =C8*1000 -> 1378350000 | E8: 11 | F8: 45491 | G8: 31.03.2029 | H8: =1855844250/1950000000*D8 -> 1.3117964e+09 | I8: =VLOOKUP(B8,'KASE за 29.08.25'!$C$5:$F$162,4,0) -> 84.4062 | J8: =VLOOKUP(B8,'KASE за 29.08.25'!$C$5:$G$162,5,0) -> 88.959 | K8: 63174375 | L8: =D8*I8/100+K8 -> 1.2265872e+09 | M8: =L8/$L$62 -> 0.046555004 | N8: =D8*E8%/360 -> 421162.5 | O8: =K8+N8 -> 63595538
A9: Министерство Финансов Республики Казахстан купонные МЕУКАМ | B9: KZKD00001160 | C9: =1950000-225000-225000-208000-225000-225000 -> 842000 | D9: =C9*1000 -> 842000000 | E9: 10.55 | F9: 45491 | G9: 28.07.2029 | H9: =1504310166.66923/1500000000*D9 -> 8.4441944e+08 | I9: =VLOOKUP(B9,'KASE за 29.08.25'!$C$5:$F$162,4,0) -> 82.436 | J9: =VLOOKUP(B9,'KASE за 29.08.25'!$C$5:$G$162,5,0) -> 83.3445 | K9: 7896088.9 | L9: =D9*I9/100+K9 -> 7.0200721e+08 | M9: =L9/$L$62 -> 0.026644618 | N9: =D9*E9%/360 -> 246752.78 | O9: =K9+N9 -> 8142841.7
A10: Министерство Финансов Республики Казахстан купонные МЕУКАМ | B10: KZKD00001129 | C10: 1450000 | D10: 1450000000 | E10: 10.3 | F10: 45491 | G10: 17.03.2031 | H10: 1.307499e+09 | I10: =VLOOKUP(B10,'KASE за 29.08.25'!$C$5:$F$162,4,0) -> 77.219 | J10: =VLOOKUP(B10,'KASE за 29.08.25'!$C$5:$G$162,5,0) -> 81.854 | K10: 67622361 | L10: =D10*I10/100+K10 -> 1.1872979e+09 | M10: =L10/$L$62 -> 0.04506378 | N10: =D10*E10%/360 -> 414861.11 | O10: =K10+N10 -> 68037222
A11: Министерство Финансов Республики Казахстан МЕУКАМ | B11: KZKD00000949 | C11: 1950000 | D11: 1950000000 | E11: 8.45 | F11: 45491 | G11: 16.04.2032 | H11: 1.5403351e+09 | I11: =VLOOKUP(B11,'KASE за 29.08.25'!$C$5:$F$162,4,0) -> 67.8257 | J11: =VLOOKUP(B11,'KASE за 29.08.25'!$C$5:$G$162,5,0) -> 70.9475 | K11: 61332917 | L11: =D11*I11/100+K11 -> 1.3839341e+09 | M11: =L11/$L$62 -> 0.052527088 | N11: =D11*E11%/360 -> 457708.33 | O11: =K11+N11 -> 61790625
A12: Министерство Финансов Республики Казахстан Купонные Облигации | B12: KZKD00001152 | C12: =1950000-250000-250000-250000-218000 -> 982000 | D12: =C12*1000 -> 982000000 | E12: 10.65 | F12: 45491 | G12: 26.07.2032 | H12: =1897171250/1950000000*D12 -> 9.5539598e+08 | I12: =VLOOKUP(B12,'KASE за 29.08.25'!$C$5:$F$162,4,0) -> 75.783 | J12: =VLOOKUP(B12,'KASE за 29.08.25'!$C$5:$G$162,5,0) -> 76.7592 | K12: 9877283.3 | L12: =D12*I12/100+K12 -> 7.5406634e+08 | M12: =L12/$L$62 -> 0.028620518 | N12: =D12*E12%/360 -> 290508.33 | O12: =K12+N12 -> 10167792
A13: Министерство Финансов Республики Казахстан Купонные Облигации | B13: KZKD00001152 | C13: 250000 | D13: =C13*1000 -> 250000000 | E13: 10.65 | F13: 45673 | G13: 26.07.2032 | H13: =227969916.67/250000000*D13 -> 2.2796992e+08 | I13: =VLOOKUP(B13,'KASE за 29.08.25'!$C$5:$F$162,4,0) -> 75.783 | J13: =VLOOKUP(B13,'KASE за 29.08.25'!$C$5:$G$162,5,0) -> 76.7592 | K13: 2514583.3 | L13: =D13*I13/100+K13 -> 1.9197208e+08 | M13: =L13/$L$62 -> 0.0072862825 | N13: =D13*E13%/360 -> 73958.333 | O13: =K13+N13 -> 2588541.7
A14: Министерство Финансов Республики Казахстан купонные МЕУКАМ | B14: KZKD00000741 | C14: 1950000 | D14: 1950000000 | E14: 8.07 | F14: 45491 | G14: 12.05.2034 | H14: 1425576750 | I14: =VLOOKUP(B14,'KASE за 29.08.25'!$C$5:$F$173,4,0) -> 61.5307 | J14: =VLOOKUP(B14,'KASE за 29.08.25'!$C$5:$G$173,5,0) -> 63.9293 | K14: 47209500 | L14: =D14*I14/100+K14 -> 1247058150 | M14: =L14/$L$62 -> 0.047331976 | N14: =D14*E14%/360 -> 437125 | O14: =K14+N14 -> 47646625
A15: Министерство Финансов Республики Казахстан купонные МЕУКАМ | B15: KZKD00000832 | C15: 1950000 | D15: 1950000000 | E15: 8.07 | F15: 45491 | G15: 29.01.2035 | H15: 1449433375 | I15: =VLOOKUP(B15,'KASE за 29.08.25'!$C$5:$F$173,4,0) -> 60.1189 | J15: =VLOOKUP(B15,'KASE за 29.08.25'!$C$5:$G$173,5,0) -> 64.8264 | K15: 92233375 | L15: =D15*I15/100+K15 -> 1264551925 | M15: =L15/$L$62 -> 0.04799595 | N15: =D15*E15%/360 -> 437125 | O15: =K15+N15 -> 92670500
A16: Министерство Финансов Республики Казахстан купонные МЕУКАМ | B16: KZKD00000550 | C16: =312000-1 -> 311999 | D16: =C16*1000 -> 311999000 | E16: 5.5 | F16: 45509 | G16: 48328 | H16: 2.0448962e+08 | I16: =VLOOKUP(B16,'KASE за 29.08.25'!$C$5:$F$174,4,0) -> 56.5718 | J16: =VLOOKUP(B16,'KASE за 29.08.25'!$C$5:$G$174,5,0) -> 58.4815 | K16: 6005980.8 | L16: =D16*I16/100+K16 -> 1.8250943e+08 | M16: =L16/$L$62 -> 0.0069271284 | N16: =D16*E16%/360 -> 47666.514 | O16: =K16+N16 -> 6053647.3
A17: Министерство Финансов Республики Казахстан купонные МЕУКАМ | B17: KZKD00000550 | C17: 500000 | D17: 500000000 | E17: 5.5 | F17: 45532 | G17: 48328 | H17: 3.2653072e+08 | I17: =VLOOKUP(B17,'KASE за 29.08.25'!$C$5:$F$174,4,0) -> 56.5718 | J17: =VLOOKUP(B17,'KASE за 29.08.25'!$C$5:$G$174,5,0) -> 58.4815 | K17: 9625000 | L17: =D17*I17/100+K17 -> 292484000 | M17: =L17/$L$62 -> 0.011101203 | N17: =D17*E17%/360 -> 76388.889 | O17: =K17+N17 -> 9701388.9
A18: Министерство Финансов Республики Казахстан купонные МЕУКАМ | B18: KZKD00000550 | C18: 500000 | D18: 500000000 | E18: 5.5 | F18: 45566 | G18: 48328 | H18: 3.3409056e+08 | I18: =VLOOKUP(B18,'KASE за 29.08.25'!$C$5:$F$174,4,0) -> 56.5718 | J18: =VLOOKUP(B18,'KASE за 29.08.25'!$C$5:$G$174,5,0) -> 58.4815 | K18: 9625000 | L18: =D18*I18/100+K18 -> 292484000 | M18: =L18/$L$62 -> 0.011101203 | N18: =D18*E18%/360 -> 76388.889 | O18: =K18+N18 -> 9701388.9
A19: Министерство Финансов Республики Казахстан купонные МЕУКАМ | B19: KZKD00000550 | C19: 300000 | D19: =C19*1000 -> 300000000 | E19: 5.5 | F19: 45649 | G19: 48328 | H19: 2.0566557e+08 | I19: =VLOOKUP(B19,'KASE за 29.08.25'!$C$5:$F$174,4,0) -> 56.5718 | J19: =VLOOKUP(B19,'KASE за 29.08.25'!$C$5:$G$174,5,0) -> 58.4815 | K19: 5775000 | L19: =D19*I19/100+K19 -> 1.754904e+08 | M19: =L19/$L$62 -> 0.0066607218 | N19: =D19*E19%/360 -> 45833.333 | O19: =K19+N19 -> 5820833.3
A20: Министерство Финансов Республики Казахстан купонные МЕУКАМ | B20: KZKD00000550 | C20: 300000 | D20: =C20*1000 -> 300000000 | E20: 5.5 | F20: 45677 | G20: 48328 | H20: 2.0236587e+08 | I20: =VLOOKUP(B20,'KASE за 29.08.25'!$C$5:$F$174,4,0) -> 56.5718 | J20: =VLOOKUP(B20,'KASE за 29.08.25'!$C$5:$G$174,5,0) -> 58.4815 | K20: 5775000 | L20: =D20*I20/100+K20 -> 1.754904e+08 | M20: =L20/$L$62 -> 0.0066607218 | N20: =D20*E20%/360 -> 45833.333 | O20: =K20+N20 -> 5820833.3
A21: Министерство Финансов Республики Казахстан купонные МЕУКАМ | B21: KZKD00001160 | C21: 500000 | D21: =C21*1000 -> 500000000 | E21: 10.55 | F21: 45512 | G21: 28.07.2029 | H21: 4.5194078e+08 | I21: =VLOOKUP(B21,'KASE за 29.08.25'!$C$5:$F$162,4,0) -> 82.436 | J21: =VLOOKUP(B21,'KASE за 29.08.25'!$C$5:$G$162,5,0) -> 83.3445 | K21: 4688888.9 | L21: =D21*I21/100+K21 -> 4.1686889e+08 | M21: =L21/$L$62 -> 0.01582222 | N21: =D21*E21%/360 -> 146527.78 | O21: =K21+N21 -> 4835416.7
A22: Министерство Финансов Республики Казахстан купонные МЕУКАМ | B22: KZKD00001160 | C22: 553430 | D22: =C22*1000 -> 553430000 | E22: 10.55 | F22: 45512 | G22: 28.07.2029 | H22: 4.9999941e+08 | I22: =VLOOKUP(B22,'KASE за 29.08.25'!$C$5:$F$162,4,0) -> 82.436 | J22: =VLOOKUP(B22,'KASE за 29.08.25'!$C$5:$G$162,5,0) -> 83.3445 | K22: 5189943.6 | L22: =D22*I22/100+K22 -> 4.614155e+08 | M22: =L22/$L$62 -> 0.017512982 | N22: =D22*E22%/360 -> 162185.74 | O22: =K22+N22 -> 5352129.3
A23: Министерство Финансов Республики Казахстан МЕУКАМ | B23: KZKD00000543 | C23: 636055 | D23: =C23*1000 -> 636055000 | E23: 5 | F23: 45519 | G23: 46861 | H23: 4.9999966e+08 | I23: =VLOOKUP(B23,'KASE за 29.08.25'!$C$5:$F$174,4,0) -> 75.6266 | J23: =VLOOKUP(B23,'KASE за 29.08.25'!$C$5:$G$174,5,0) -> 77.446 | K23: 11661008 | L23: =D23*I23/100+K23 -> 4.9268778e+08 | M23: =L23/$L$62 -> 0.018699919 | N23: =D23*E23%/360 -> 88340.972 | O23: =K23+N23 -> 11749349
A24: Министерство Финансов Республики Казахстан купонные МЕУКАМ | B24: KZKD00000774 | C24: =715927-16841 -> 699086 | D24: =C24*1000 -> 699086000 | E24: 8.35 | F24: 45526 | G24: 50976 | H24: 4.8823782e+08 | I24: =VLOOKUP(B24,'KASE за 29.08.25'!$C$5:$F$173,4,0) -> 55.8555 | J24: =VLOOKUP(B24,'KASE за 29.08.25'!$C$5:$G$173,5,0) -> 56.6441 | K24: 5675219 | L24: =D24*I24/100+K24 -> 3.961532e+08 | M24: =L24/$L$62 -> 0.015035958 | N24: =D24*E24%/360 -> 162149.11 | O24: =K24+N24 -> 5837368.1
A25: Министерство Финансов Республики Казахстан купонные МЕУКАМ | B25: KZKD00000774 | C25: 284073 | D25: =C25*1000 -> 284073000 | E25: 8.35 | F25: 45617 | G25: 50976 | H25: 2.0393645e+08 | I25: =VLOOKUP(B25,'KASE за 29.08.25'!$C$5:$F$173,4,0) -> 55.8555 | J25: =VLOOKUP(B25,'KASE за 29.08.25'!$C$5:$G$173,5,0) -> 56.6441 | K25: 2306120.4 | L25: =D25*I25/100+K25 -> 1.6097651e+08 | M25: =L25/$L$62 -> 0.0061098486 | N25: =D25*E25%/360 -> 65889.154 | O25: =K25+N25 -> 2372009.5
A26: Министерство Финансов Республики Казахстан МЕУКАМ | B26: KZKD00000840 | C26: 500000 | D26: =C26*1000 -> 500000000 | E26: 7.68 | F26: 45526 | G26: 47518 | H26: 417099000 | I26: =VLOOKUP(B26,'KASE за 29.08.25'!$C$5:$F$162,4,0) -> 72.3769 | J26: =VLOOKUP(B26,'KASE за 29.08.25'!$C$5:$G$162,5,0) -> 76.7502 | K26: 21973333 | L26: =D26*I26/100+K26 -> 3.8385783e+08 | M26: =L26/$L$62 -> 0.014569288 | N26: =D26*E26%/360 -> 106666.67 | O26: =K26+N26 -> 22080000
A27: Министерство Финансов Республики Казахстан МЕУКАМ | B27: KZKD00000840 | C27: 500000 | D27: =C27*1000 -> 500000000 | E27: 7.68 | F27: 45527 | G27: 47518 | H27: 4.1494417e+08 | I27: =VLOOKUP(B27,'KASE за 29.08.25'!$C$5:$F$162,4,0) -> 72.3769 | J27: =VLOOKUP(B27,'KASE за 29.08.25'!$C$5:$G$162,5,0) -> 76.7502 | K27: 21973333 | L27: =D27*I27/100+K27 -> 3.8385783e+08 | M27: =L27/$L$62 -> 0.014569288 | N27: =D27*E27%/360 -> 106666.67 | O27: =K27+N27 -> 22080000
A28: Министерство Финансов Республики Казахстан МЕУКАМ | B28: KZKD00000840 | C28: 500000 | D28: =C28*1000 -> 500000000 | E28: 7.68 | F28: 45561 | G28: 47518 | H28: 4.2179517e+08 | I28: =VLOOKUP(B28,'KASE за 29.08.25'!$C$5:$F$162,4,0) -> 72.3769 | J28: =VLOOKUP(B28,'KASE за 29.08.25'!$C$5:$G$162,5,0) -> 76.7502 | K28: 21973333 | L28: =D28*I28/100+K28 -> 3.8385783e+08 | M28: =L28/$L$62 -> 0.014569288 | N28: =D28*E28%/360 -> 106666.67 | O28: =K28+N28 -> 22080000
A29: Евразийский банк развития | B29: KZ2D00011863 | C29: 1700000 | D29: =C29*1000 -> 1700000000 | E29: 14.3 | F29: 45538 | G29: 46633 | H29: 1700000000 | I29: =VLOOKUP(B29,'Риск цены за 29.08.25'!$C$4:$G$963,4,0) -> 93.307067 | J29: =VLOOKUP(B29,'Риск цены за 29.08.25'!$C$4:$G$963,5,0) -> 107.44817 | K29: 2.4107417e+08 | L29: =D29*I29/100+K29 -> 1.8272943e+09 | M29: =L29/$L$62 -> 0.069354785 | N29: =D29*E29%/360 -> 675277.78 | O29: =K29+N29 -> 2.4174944e+08
A30: Министерство Финансов Республики Казахстан МЕУКАМ | B30: KZKD00001244 | C30: 500000 | D30: =C30*1000 -> 500000000 | E30: 12 | F30: 45540 | G30: 47901 | H30: 5.0216167e+08 | I30: =VLOOKUP(B30,'KASE за 29.08.25'!$C$5:$F$162,4,0) -> 83.0321 | J30: =VLOOKUP(B30,'KASE за 29.08.25'!$C$5:$G$162,5,0) -> 89.2654 | K30: 31333333 | L30: =D30*I30/100+K30 -> 4.4649383e+08 | M30: =L30/$L$62 -> 0.016946632 | N30: =D30*E30%/360 -> 166666.67 | O30: =K30+N30 -> 31500000
A31: Министерство Финансов Республики Казахстан МЕУКАМ | B31: KZKD00001251 | C31: 300000 | D31: =C31*1000 -> 300000000 | E31: 12 | F31: 45547 | G31: 47549 | H31: 302854400 | I31: =VLOOKUP(B31,'KASE за 29.08.25'!$C$5:$F$162,4,0) -> 84.8937 | J31: =VLOOKUP(B31,'KASE за 29.08.25'!$C$5:$G$162,5,0) -> 90.627 | K31: 17300000 | L31: =D31*I31/100+K31 -> 271981100 | M31: =L31/$L$62 -> 0.010323017 | N31: =D31*E31%/360 -> 100000 | O31: =K31+N31 -> 17400000
A32: Министерство Финансов Республики Казахстан МЕУКАМ | B32: KZKD00001251 | C32: 288579 | D32: =C32*1000 -> 288579000 | E32: 12 | F32: 45582 | G32: 47549 | H32: 2.9999932e+08 | I32: =VLOOKUP(B32,'KASE за 29.08.25'!$C$5:$F$162,4,0) -> 84.8937 | J32: =VLOOKUP(B32,'KASE за 29.08.25'!$C$5:$G$162,5,0) -> 90.627 | K32: 16641389 | L32: =D32*I32/100+K32 -> 2.6162678e+08 | M32: =L32/$L$62 -> 0.00993002 | N32: =D32*E32%/360 -> 96193 | O32: =K32+N32 -> 16737582
A33: АО "Национальный управляющий холдинг "Байтерек" | B33: KZ2C00012698 | C33: 300000 | D33: =C33*1000 -> 300000000 | E33: 13.89 | F33: 45624 | G33: 46109 | H33: 300000000 | I33: =VLOOKUP(B33,'Риск цены за 29.08.25'!$C$4:$G$963,4,0) -> 98.003245 | J33: =VLOOKUP(B33,'Риск цены за 29.08.25'!$C$4:$G$963,5,0) -> 101.51434 | K33: 10649000 | L33: =D33*I33/100+K33 -> 3.0465873e+08 | M33: =L33/$L$62 -> 0.011563294 | N33: =D33*E33%/360 -> 115750 | O33: =K33+N33 -> 10764750
A34: Министерство Финансов Республики Казахстан МЕУКАМ | B34: KZKD00000964 | C34: =220000-213000 -> 7000 | D34: =C34*1000 -> 7000000 | E34: 8.44 | F34: 45639 | G34: 47978 | H34: =182967986.67/220000000*D34 -> 5821708.7 | I34: =VLOOKUP(B34,'KASE за 29.08.25'!$C$5:$F$162,4,0) -> 70.4585 | J34: =VLOOKUP(B34,'KASE за 29.08.25'!$C$5:$G$162,5,0) -> 73.0139 | K34: 180522.22 | L34: =D34*I34/100+K34 -> 5112617.2 | M34: =L34/$L$62 -> 0.00019404891 | N34: =D34*E34%/360 -> 1641.1111 | O34: =K34+N34 -> 182163.33
A35: Министерство Финансов Республики Казахстан МЕУКАМ | B35: KZKD00001236 | C35: =173000-163000 -> 10000 | D35: =C35*1000 -> 10000000 | E35: 14 | F35: 45639 | G35: 48353 | H35: =188266096.67/173000000*D35 -> 10882433 | I35: =VLOOKUP(B35,'KASE за 29.08.25'!$C$5:$F$162,4,0) -> 88.8397 | J35: =VLOOKUP(B35,'KASE за 29.08.25'!$C$5:$G$162,5,0) -> 92.7286 | K35: 392777.78 | L35: =D35*I35/100+K35 -> 9276747.8 | M35: =L35/$L$62 -> 0.0003520981 | N35: =D35*E35%/360 -> 3888.8889 | O35: =K35+N35 -> 396666.67
A36: Министерство Финансов Республики Казахстан МЕУКАМ | B36: KZKD00001079 | C36: 300000 | D36: =C36*1000 -> 300000000 | E36: 8.7 | F36: 45651 | G36: 50082 | H36: 237511300 | I36: =VLOOKUP(B36,'KASE за 29.08.25'!$C$5:$F$174,4,0) -> 60.0388 | J36: =VLOOKUP(B36,'KASE за 29.08.25'!$C$5:$G$174,5,0) -> 64.8238 | K36: 14427500 | L36: =D36*I36/100+K36 -> 194543900 | M36: =L36/$L$62 -> 0.0073838956 | N36: =D36*E36%/360 -> 72500 | O36: =K36+N36 -> 14500000
A37: Министерство Финансов Республики Казахстан МЕУКАМ | B37: KZKD00001079 | C37: 200000 | D37: =C37*1000 -> 200000000 | E37: 8.7 | F37: 45680 | G37: 50082 | H37: 157353400 | I37: =VLOOKUP(B37,'KASE за 29.08.25'!$C$5:$F$174,4,0) -> 60.0388 | J37: =VLOOKUP(B37,'KASE за 29.08.25'!$C$5:$G$174,5,0) -> 64.8238 | K37: 9618333.3 | L37: =D37*I37/100+K37 -> 1.2969593e+08 | M37: =L37/$L$62 -> 0.0049225971 | N37: =D37*E37%/360 -> 48333.333 | O37: =K37+N37 -> 9666666.7
A38: Министерство Финансов Республики Казахстан МЕУКАМ | B38: KZKD00001202 | C38: 263000 | D38: =C38*1000 -> 263000000 | E38: 11 | F38: 45656 | G38: 47518 | H38: 2.6372196e+08 | I38: =VLOOKUP(B38,'KASE за 29.08.25'!$C$5:$F$162,4,0) -> 82.0718 | J38: =VLOOKUP(B38,'KASE за 29.08.25'!$C$5:$G$162,5,0) -> 88.3357 | K38: 16554389 | L38: =D38*I38/100+K38 -> 2.3240322e+08 | M38: =L38/$L$62 -> 0.0088208426 | N38: =D38*E38%/360 -> 80361.111 | O38: =K38+N38 -> 16634750
A39: Министерство Финансов Республики Казахстан МЕУКАМ | B39: KZKD00001210 | C39: 341000 | D39: =C39*1000 -> 341000000 | E39: 15.3 | F39: 45657 | G39: 47180 | H39: 396883762 | I39: =VLOOKUP(B39,'KASE за 29.08.25'!$C$5:$F$162,4,0) -> 95.2474 | J39: =VLOOKUP(B39,'KASE за 29.08.25'!$C$5:$G$162,5,0) -> 102.7274 | K39: 25651725 | L39: =D39*I39/100+K39 -> 350445359 | M39: =L39/$L$62 -> 0.013301121 | N39: =D39*E39%/360 -> 144925 | O39: =K39+N39 -> 25796650
A40: Министерство Финансов Республики Казахстан МЕУКАМ | B40: KZKD00001095 | C40: =214727-132000 -> 82727 | D40: =C40*1000 -> 82727000 | E40: 10.47 | F40: 45673 | G40: 47053 | H40: 77053072 | I40: =VLOOKUP(B40,'KASE за 29.08.25'!$C$5:$F$162,4,0) -> 84.5639 | J40: =VLOOKUP(B40,'KASE за 29.08.25'!$C$5:$G$162,5,0) -> 93.3471 | K40: 7290110.1 | L40: =D40*I40/100+K40 -> 77247288 | M40: =L40/$L$62 -> 0.0029319136 | N40: =D40*E40%/360 -> 24059.769 | O40: =K40+N40 -> 7314169.8
A41: Министерство Финансов Республики Казахстан МЕУКАМ | B41: KZKD00000790 | C41: 227500 | D41: =C41*1000 -> 227500000 | E41: 7.68 | F41: 45702 | G41: 47343 | H41: 1.8902823e+08 | I41: =VLOOKUP(B41,'KASE за 29.08.25'!$C$5:$F$162,4,0) -> 74.538 | J41: =VLOOKUP(B41,'KASE за 29.08.25'!$C$5:$G$162,5,0) -> 74.8793 | K41: 825066.67 | L41: =D41*I41/100+K41 -> 1.7039902e+08 | M41: =L41/$L$62 -> 0.0064674788 | N41: =D41*E41%/360 -> 48533.333 | O41: =K41+N41 -> 873600
A42: Министерство Финансов Республики Казахстан | B42: KZKD00000717 | C42: 500000 | D42: =C42*1000 -> 500000000 | E42: 7.22 | F42: 45729 | G42: 47097 | H42: 3.9979333e+08 | I42: =VLOOKUP(B42,'KASE за 29.08.25'!$C$5:$F$162,4,0) -> 76.4732 | J42: =VLOOKUP(B42,'KASE за 29.08.25'!$C$5:$G$162,5,0) -> 81.6676 | K42: 26072222 | L42: =D42*I42/100+K42 -> 4.0843822e+08 | M42: =L42/$L$62 -> 0.015502235 | N42: =D42*E42%/360 -> 100277.78 | O42: =K42+N42 -> 26172500
A43: Министерство Финансов Республики Казахстан | B43: KZKD00001210 | C43: 259000 | D43: =C43*1000 -> 259000000 | E43: 15.3 | F43: 45750 | G43: 47180 | H43: 260647240 | I43: =VLOOKUP(B43,'KASE за 29.08.25'!$C$5:$F$162,4,0) -> 95.2474 | J43: =VLOOKUP(B43,'KASE за 29.08.25'!$C$5:$G$162,5,0) -> 102.7274 | K43: 19483275 | L43: =D43*I43/100+K43 -> 266174041 | M43: =L43/$L$62 -> 0.010102611 | N43: =D43*E43%/360 -> 110075 | O43: =K43+N43 -> 19593350
A44: АО "Национальный управляющий холдинг "Байтерек" | B44: KZ2C00012268 | C44: 200000 | D44: =C44*1000 -> 200000000 | E44: 16.7 | F44: 45757 | G44: 46122 | H44: 200000000 | I44: =VLOOKUP(B44,'Риск цены за 29.08.25'!$C$4:$G$963,4,0) -> 99.365755 | J44: =VLOOKUP(B44,'Риск цены за 29.08.25'!$C$4:$G$963,5,0) -> 105.81385 | K44: 12988889 | L44: =D44*I44/100+K44 -> 2.117204e+08 | M44: =L44/$L$62 -> 0.008035828 | N44: =D44*E44%/360 -> 92777.778 | O44: =K44+N44 -> 13081667
A45: Министерство Финансов Республики Казахстан | B45: KZKD00000477 | C45: 500000 | D45: =C45*1000 -> 500000000 | E45: 5.3 | F45: 45764 | G45: 46679 | H45: 4.1207678e+08 | I45: =VLOOKUP(B45,'KASE за 29.08.25'!$C$5:$F$162,4,0) -> 79.908 | J45: =VLOOKUP(B45,'KASE за 29.08.25'!$C$5:$G$162,5,0) -> 84.4719 | K45: 22893056 | L45: =D45*I45/100+K45 -> 4.2243306e+08 | M45: =L45/$L$62 -> 0.016033407 | N45: =D45*E45%/360 -> 73611.111 | O45: =K45+N45 -> 22966667
A46: Министерство Финансов Республики Казахстан | B46: KZKD00001202 | C46: 737000 | D46: =C46*1000 -> 737000000 | E46: 11 | F46: 45771 | G46: 47518 | H46: 6.4967099e+08 | I46: =VLOOKUP(B46,'KASE за 29.08.25'!$C$5:$F$162,4,0) -> 82.0718 | J46: =VLOOKUP(B46,'KASE за 29.08.25'!$C$5:$G$162,5,0) -> 88.3357 | K46: 46390056 | L46: =D46*I46/100+K46 -> 6.5125922e+08 | M46: =L46/$L$62 -> 0.024718483 | N46: =D46*E46%/360 -> 225194.44 | O46: =K46+N46 -> 46615250
A47: Министерство Финансов Республики Казахстан | B47: KZKD00001129 | C47: 6000 | D47: =C47*1000 -> 6000000 | E47: 10.3 | F47: 45775 | G47: 47924 | H47: 4822485.3 | I47: =VLOOKUP(B47,'KASE за 29.08.25'!$C$5:$F$162,4,0) -> 77.219 | J47: =VLOOKUP(B47,'KASE за 29.08.25'!$C$5:$G$162,5,0) -> 81.854 | K47: 279816.67 | L47: =D47*I47/100+K47 -> 4912956.7 | M47: =L47/$L$62 -> 0.00018647081 | N47: =D47*E47%/360 -> 1716.6667 | O47: =K47+N47 -> 281533.33
A48: Министерство Финансов Республики Казахстан | B48: KZKD00001129 | C48: 6000 | D48: =C48*1000 -> 6000000 | E48: 10.3 | F48: 45775 | G48: 47924 | H48: 4841157.3 | I48: =VLOOKUP(B48,'KASE за 29.08.25'!$C$5:$F$162,4,0) -> 77.219 | J48: =VLOOKUP(B48,'KASE за 29.08.25'!$C$5:$G$162,5,0) -> 81.854 | K48: 279816.67 | L48: =D48*I48/100+K48 -> 4912956.7 | M48: =L48/$L$62 -> 0.00018647081 | N48: =D48*E48%/360 -> 1716.6667 | O48: =K48+N48 -> 281533.33
A49: АО "Банк Развития Казахстана" | B49: KZ2C00010106 | C49: 500000 | D49: =C49*1000 -> 500000000 | E49: 17 | F49: 45782 | G49: 46147 | H49: 500000000 | I49: 100 | J49: 100 | K49: 27152778 | L49: =D49*I49/100+K49 -> 5.2715278e+08 | M49: =L49/$L$62 -> 0.020008035 | N49: =D49*E49%/360 -> 236111.11 | O49: =K49+N49 -> 27388889
A50: Министерство Финансов Республики Казахстан | B50: KZKD00000964 | C50: 500000 | D50: =C50*1000 -> 500000000 | E50: 8.44 | F50: 45799 | G50: 47978 | H50: 3.7223717e+08 | I50: =VLOOKUP(B50,'KASE за 29.08.25'!$C$5:$F$165,4,0) -> 70.4585 | J50: =VLOOKUP(B50,'KASE за 29.08.25'!$C$5:$G$165,5,0) -> 73.0139 | K50: 12894444 | L50: =D50*I50/100+K50 -> 3.6518694e+08 | M50: =L50/$L$62 -> 0.013860636 | N50: =D50*E50%/360 -> 117222.22 | O50: =K50+N50 -> 13011667
A51: Министерство Финансов Республики Казахстан | B51: KZKD00000790 | C51: 500000 | D51: =C51*1000 -> 500000000 | E51: 7.68 | F51: 45813 | G51: 47343 | H51: 4.0360417e+08 | I51: =VLOOKUP(B51,'KASE за 29.08.25'!$C$5:$F$165,4,0) -> 74.538 | J51: =VLOOKUP(B51,'KASE за 29.08.25'!$C$5:$G$165,5,0) -> 74.8793 | K51: 1813333.3 | L51: =D51*I51/100+K51 -> 3.7450333e+08 | M51: =L51/$L$62 -> 0.014214239 | N51: =D51*E51%/360 -> 106666.67 | O51: =K51+N51 -> 1920000
A52: Министерство Финансов Республики Казахстан | B52: KZKD00000543 | C52: 500000 | D52: =C52*1000 -> 500000000 | E52: 5 | F52: 45813 | G52: 46861 | H52: 3.7940239e+08 | I52: =VLOOKUP(B52,'KASE за 29.08.25'!$C$5:$F$165,4,0) -> 75.6266 | J52: =VLOOKUP(B52,'KASE за 29.08.25'!$C$5:$G$165,5,0) -> 77.446 | K52: 9166666.7 | L52: =D52*I52/100+K52 -> 3.8729967e+08 | M52: =L52/$L$62 -> 0.014699923 | N52: =D52*E52%/360 -> 69444.444 | O52: =K52+N52 -> 9236111.1
A53: Министерство Финансов Республики Казахстан | B53: KZKD00001160 | C53: 200000 | D53: =C53*1000 -> 200000000 | E53: 10.55 | F53: 45820 | G53: 47327 | H53: 1.8266529e+08 | I53: =VLOOKUP(B53,'KASE за 29.08.25'!$C$5:$F$165,4,0) -> 82.436 | J53: =VLOOKUP(B53,'KASE за 29.08.25'!$C$5:$G$165,5,0) -> 83.3445 | K53: 1875555.6 | L53: =D53*I53/100+K53 -> 1.6674756e+08 | M53: =L53/$L$62 -> 0.0063288879 | N53: =D53*E53%/360 -> 58611.111 | O53: =K53+N53 -> 1934166.7
A54: Министерство Финансов Республики Казахстан | B54: KZKD00001251 | C54: 500000 | D54: =C54*1000 -> 500000000 | E54: 12 | F54: 45832 | G54: 47549 | H54: 4.4701683e+08 | I54: =VLOOKUP(B54,'KASE за 29.08.25'!$C$5:$F$165,4,0) -> 84.8937 | J54: =VLOOKUP(B54,'KASE за 29.08.25'!$C$5:$G$165,5,0) -> 90.627 | K54: 28833333 | L54: =D54*I54/100+K54 -> 4.5330183e+08 | M54: =L54/$L$62 -> 0.017205029 | N54: =D54*E54%/360 -> 166666.67 | O54: =K54+N54 -> 29000000
A55: Министерство Финансов Республики Казахстан | B55: KZKD00001251 | C55: 500000 | D55: =C55*1000 -> 500000000 | E55: 12 | F55: 45832 | G55: 47549 | H55: 4.4561733e+08 | I55: =VLOOKUP(B55,'KASE за 29.08.25'!$C$5:$F$165,4,0) -> 84.8937 | J55: =VLOOKUP(B55,'KASE за 29.08.25'!$C$5:$G$165,5,0) -> 90.627 | K55: 28833333 | L55: =D55*I55/100+K55 -> 4.5330183e+08 | M55: =L55/$L$62 -> 0.017205029 | N55: =D55*E55%/360 -> 166666.67 | O55: =K55+N55 -> 29000000
A56: Министерство Финансов Республики Казахстан | B56: KZKD00001251 | C56: 411421 | D56: =C56*1000 -> 411421000 | E56: 12 | F56: 45832 | G56: 47549 | H56: 3.6376844e+08 | I56: =VLOOKUP(B56,'KASE за 29.08.25'!$C$5:$F$165,4,0) -> 84.8937 | J56: =VLOOKUP(B56,'KASE за 29.08.25'!$C$5:$G$165,5,0) -> 90.627 | K56: 23725278 | L56: =D56*I56/100+K56 -> 3.7299579e+08 | M56: =L56/$L$62 -> 0.01415702 | N56: =D56*E56%/360 -> 137140.33 | O56: =K56+N56 -> 23862418
A57: Министерство Финансов Республики Казахстан | B57: KZKD00001301 | C57: =500000-271261 -> 228739 | D57: =C57*1000 -> 228739000 | E57: 14.45 | F57: 45848 | G57: 48735 | H57: 2.0742821e+08 | I57: =VLOOKUP(B57,'KASE за 29.08.25'!$C$5:$F$174,4,0) -> 89.955 | J57: =VLOOKUP(B57,'KASE за 29.08.25'!$C$5:$G$174,5,0) -> 93.3267 | K57: 7804129.9 | L57: =D57*I57/100+K57 -> 2.135663e+08 | M57: =L57/$L$62 -> 0.0081058889 | N57: =D57*E57%/360 -> 91813.293 | O57: =K57+N57 -> 7895943.2
A58: Министерство Финансов Республики Казахстан | B58: KZKD00000964 | C58: 500000 | D58: =C58*1000 -> 500000000 | E58: 8.44 | F58: 45862 | G58: 47978 | H58: 3.5788194e+08 | I58: =VLOOKUP(B58,'KASE за 29.08.25'!$C$5:$F$174,4,0) -> 70.4585 | J58: =VLOOKUP(B58,'KASE за 29.08.25'!$C$5:$G$174,5,0) -> 73.0139 | K58: 12894444 | L58: =D58*I58/100+K58 -> 3.6518694e+08 | M58: =L58/$L$62 -> 0.013860636 | N58: =D58*E58%/360 -> 117222.22 | O58: =K58+N58 -> 13011667
A59: Министерство Финансов Республики Казахстан | B59: KZKD00001301 | C59: 500000 | D59: =C59*1000 -> 500000000 | E59: 14.45 | F59: 45883 | G59: 48735 | H59: 4.6018642e+08 | I59: =VLOOKUP(B59,'KASE за 29.08.25'!$C$5:$F$174,4,0) -> 89.955 | J59: =VLOOKUP(B59,'KASE за 29.08.25'!$C$5:$G$174,5,0) -> 93.3267 | K59: 17059028 | L59: =D59*I59/100+K59 -> 4.6683403e+08 | M59: =L59/$L$62 -> 0.017718642 | N59: =D59*E59%/360 -> 200694.44 | O59: =K59+N59 -> 17259722
A60: Министерство Финансов Республики Казахстан | B60: KZKD00000774 | C60: 16841 | D60: =C60*1000 -> 16841000 | E60: 8.35 | F60: 45890 | G60: 50976 | H60: 9465392.4 | I60: =VLOOKUP(B60,'KASE за 29.08.25'!$C$5:$F$174,4,0) -> 55.8555 | J60: =VLOOKUP(B60,'KASE за 29.08.25'!$C$5:$G$174,5,0) -> 56.6441 | K60: 136716.17 | L60: =D60*I60/100+K60 -> 9543340.9 | M60: =L60/$L$62 -> 0.00036221661 | N60: =D60*E60%/360 -> 3906.1764 | O60: =K60+N60 -> 140622.35
A61: АО "Казахстанская Жилищная Компания" | B61: KZ2C00014744 | C61: 500000 | D61: =C61*1000 -> 500000000 | E61: 18.7 | F61: 45896 | G61: 46992 | H61: 500000000 | I61: 100 | J61: 100 | K61: 779166.67 | L61: =D61*I61/100+K61 -> 5.0077917e+08 | M61: =L61/$L$62 -> 0.019007027 | N61: =D61*E61%/360 -> 259722.22 | O61: =K61+N61 -> 1038888.9
A62: ИТОГО | C62: =SUM(C6:C61) -> 32621800 | D62: =SUM(D6:D61) -> 32621800000 | H62: =SUM(H6:H61) -> 2.8060502e+10 | K62: =SUM(K6:K61) -> 1.2959732e+09 | L62: =SUM(L6:L61) -> 2.6347055e+10 | M62: =SUM(M6:M61) -> 1 | N62: 2.6347055e+10 | O62: =L62-N62 -> 0
A64: Остатки на инвест. cчетах
A65: KZT | B65: 364234.15 | C65: 364234.15 | D65: =B65-C65 -> 0
A67: Обратное репо
A68: Наименование эмитента и вид ЦБ | B68: НИН (ISIN) | C68: Количество | D68: Валюта | E68: Дата открытия | F68: Дата закрытия | G68: Цена открытия | H68: Цена закрытия | I68: Сумма открытия операции. в тг | J68: Сумма закрытия операции. в тг | K68: Ставка доходности. % | L68: Сумма начисленного вознагрждения | M68: Суммарная текущая стоимость. в тг
A69: Национальный Банк РК | B69: KZW100014320 | C69: 8102712 | D69: KZT | E69: 45898 | F69: 45902 | G69: 99.2291 | H69: 99.405266 | I69: 8.0402482e+08 | J69: 8.0545224e+08 | K69: 16.2 | L69: =IF(($B$1-E69)=0,0,(J69-I69)/(F69-E69)*($B$1-E69)) -> 356854.85 | M69: =IF((F69=$B$1),0,(I69+L69)) -> 8.0438167e+08
A70: Европейский банк реконструкции и развития | B70: XS2774403690 | C70: 337943300 | D70: KZT | E70: 45898 | F70: 45902 | G70: 1.0268 | H70: 1.0285723 | I70: 3.4700018e+08 | J70: 3.4759911e+08 | K70: 15.75 | L70: =IF(($B$1-E70)=0,0,(J70-I70)/(F70-E70)*($B$1-E70)) -> 149732.95 | M70: =IF((F70=$B$1),0,(I70+L70)) -> 3.4714991e+08
A71: Европейский банк реконструкции и развития | B71: XS2774403690 | C71: 6817300 | D71: KZT | E71: 45898 | F71: 45902 | G71: 1.0268 | H71: 1.0285723 | I71: 7000003.6 | J71: 7012085.8 | K71: 15.750003 | L71: =IF(($B$1-E71)=0,0,(J71-I71)/(F71-E71)*($B$1-E71)) -> 3020.55 | M71: =IF((F71=$B$1),0,(I71+L71)) -> 7003024.2
A73: ИТОГО | C73: =SUM(C69:C71) -> 352863312 | I73: =SUM(I69:I71) -> 1.158025e+09 | J73: =SUM(J69:J71) -> 1.1600634e+09 | L73: =SUM(L69:L71) -> 509608.36 | M73: =SUM(M69:M71) -> 1.1585346e+09 | N73: 1.1585346e+09 | O73: =M73-N73 -> 0
A76: Прочие активы (дебиторская задолженность. деньги в пути)
A77: № п/п | B77: Наименование | C77: Валюта | D77: Дата постановки на учет | E77: Количество | F77: Остаток в валюте | G77: Остаток в тенге
A79: ИТОГО | G79: =SUM(G78:G78) -> 0
A81: Итого активов | B81: =L62+B65+M73+G79 -> 2.7505953e+10 | C81: 2.7505953e+10 | D81: =B81-C81 -> 0
A85: 2) Кредиторская задолженность Фонда
A86: Комиссия ДУ (за управление) | B86: =4020961.36-4020961.36 -> 0
A87: Комиссия ДУ (сверхдоходность)
A88: Комиссия Кастоди | B88: =2000+3000+5000+7000+2000+4000+3000+5000+2000+3000+3000+2000+2000+24000+2000+6000+2000+2000+2000+2000+351673.18+71000+2000+6000+2000+3000+2000+3000+2000+2000+2000+2000-434673.18+2000+2000+2000+2000+2000+3000+3000+4000+3000+2000+2000+342960.79+2000+2000+12000+2000+2000+2000+2000+3000+12000+3000+2000+5000-466960.79+3000+3000+4000+2000+2000+2000+5000+4000+3000 -> 77000
A89: Комиссия Глобал кастоди
A90: Комиссия Центрального Депозитария | B90: =365447.82+31954.05 -> 397401.87
A91: Клиринговый сбор | B91: =4083.63+3230.48+3265.02+12872.21+3281.52+3247.37+2574.32+7640.52+2575.08+2576.75+2575.88+2577.32+7662+2583.06+2582.99+2585.09+2053.2+6452.61+2743.63+2707.86+2708.65+2708.58+8059.51+2714.35+2877.07+2713.89+2715.72+8083.12+2715.44+2722.26+2808.08+2127.48+6288.59+2125.07+15057.91+2501.85+3003.68+7441.19+2508.07+2508.48+1753.99+1765.19+6948.15 -> 174726.86
A92: Комиссия биржи | B92: =1606.55+1607.59+1608.19+6436.1+1611.94+1612.29+46613.68+3820.27+1275.38+1275.47+1276.53+1276.5+3831+1278.62+1279.34+1280.38+36800.38+3224.64+1340.74+1341.77+1342.17+1342.88+4029.76+1345.03+1345.6+1346.29+1346.45+4041.56+1348.56+1349.73+1391.91-123082.41+47065.72+3144.3+1048.87+26352.67+1238.77+3185.44+3720.59+1241.87+1242.08+867.08+868.18+3474.07 -> 110994.53
A93: Комиссия брокера
A94: Кредиторская задолженность (прочая комиссия)
A95: Остаток прочих обязательств на конец дня
A96: Итого | B96: =SUM(B86:B95) -> 760123.26

Sheet KASE за 29.08.25
A1: Дата оценки | B1: 45898
A3: № п/п | B3: Код | C3: ISIN | D3: Вид ценной бумаги | E3: Компания | F3: Рыночная цена | G3: Рыночная "грязная" цена | H3: Доходность до погашения, % годовых | I3: Срок до погашения | J3: Единица измерения цены
A5: 1 | B5: 1AIRA | C5: KZ1C00004050 | D5: акции | E5: Эйр Астана | F5: 749.37 | G5: – | H5: – | I5: – | J5: KZT
A6: 2 | B6: 2AIRAd | C6: US0090632078 | D6: производные ЦБ | E6: Эйр Астана | F6: 5.68 | G6: – | H6: – | I6: – | J6: USD
A7: 3 | B7: 3AKZM | C7: KZ1C00001288 | D7: акции | E7: Актюбинский завод металлоконструкций | F7: 6273.97 | G7: – | H7: – | I7: – | J7: KZT
A8: 4 | B8: 4ALMSb1 | C8: KZ2C00012953 | D8: долговые ЦБ | E8: АК Алтыналмас | F8: 100.2662 | G8: 101.6662 | H8: 7,87 | I8: 837 (2) | J8: %
A9: 5 | B9: 5BCCIbe | C9: KZPF00000553 | D9: ЦБ инвест. фондов | E9: BCC Invest | F9: 1468.56 | G9: – | H9: – | I9: – | J9: KZT
A10: 6 | B10: 6BCCIrb | C10: KZPF00000231 | D10: ЦБ инвест. фондов | E10: BCC Invest | F10: 6.97 | G10: – | H10: – | I10: – | J10: KZT
A11: 7 | B11: 7BIGDb5 | C11: KZ2D00012861 | D11: долговые ЦБ | E11: Частная компания BI Development Ltd. | F11: 99.8905 | G11: 104.7655 | H11: 19,50 | I11: 630 (2) | J11: %
A12: 8 | B12: 8BRKZe18 | C12: XS3032932645 | D12: долговые ЦБ | E12: Банк Развития Казахстана | F12: 102.7071 | G12: 104.9259 | H12: 4,96 | I12: 1 658 (5) | J12: %
A13: 9 | B13: 9BRKZe4 | C13: XS0248160102 | D13: долговые ЦБ | E13: Банк Развития Казахстана | F13: 100.0066 | G13: 102.6066 | H13: 5,98 | I13: 204 (1) | J13: %
A14: 10 | B14: 10BTRKe1 | C14: XS3067899610 | D14: долговые ЦБ | E14: Национальный управляющий холдинг "Байтерек" | F14: 101.1512 | G14: 102.8316 | H14: 4,98 | I14: 969 (3) | J14: %
A15: 11 | B15: 11CCBN | C15: KZ0007786572 | D15: акции | E15: Банк ЦентрКредит | F15: 4724.02 | G15: – | H15: – | I15: – | J15: KZT
A16: 12 | B16: 12CSECfe | C16: KZPF00000025 | D16: ЦБ инвест. фондов | E16: Сентрас Секьюритиз | F16: 5878447.5 | G16: – | H16: – | I16: – | J16: KZT
A17: 13 | B17: 13CSECtf | C17: KZPF00000280 | D17: ЦБ инвест. фондов | E17: Сентрас Секьюритиз | F17: 1741209.1 | G17: – | H17: – | I17: – | J17: KZT
A18: 14 | B18: 14EABRb40 | C18: KZ2D00009628 | D18: ЦБ МФО | E18: Евразийский банк развития | F18: 99.9017 | G18: 102.428 | H18: 5,89 | I18: 201 (1) | J18: %
A19: 15 | B19: 15EABRb42 | C19: KZ2D00009222 | D19: ЦБ МФО | E19: Евразийский банк развития | F19: 100 | G19: 100.1781 | H19: 16,25 | I19: 910 (3) | J19: %
A20: 16 | B20: 16EABRb53 | C20: KZ2D00013620 | D20: ЦБ МФО | E20: Евразийский банк развития | F20: 100 | G20: 107.4315 | H20: 17,47 | I20: 941 (3) | J20: %
A21: 17 | B21: 17FFINgw | C21: KZPF00000090 | D21: ЦБ инвест. фондов | E21: Фридом Финанс | F21: 5496.9 | G21: – | H21: – | I21: – | J21: KZT
A22: 18 | B22: 18FHJIag | C22: KZPF00000132 | D22: ЦБ инвест. фондов | E22: Alatau City Invest | F22: 1039.42 | G22: – | H22: – | I22: – | J22: USD
A23: 19 | B23: 19FHJIpc | C23: KZPF00000140 | D23: ЦБ инвест. фондов | E23: Alatau City Invest | F23: 1163.35 | G23: – | H23: – | I23: – | J23: USD
A24: 20 | B24: 20HCBNb13 | C24: KZ2C00011195 | D24: долговые ЦБ | E24: Home Credit Bank | F24: 99.8077 | G24: 99.9085 | H24: 18,25 | I24: 898 (2) | J24: %
A25: 21 | B25: 21HCBNb17 | C25: KZ2C00014066 | D25: долговые ЦБ | E25: Home Credit Bank | F25: 95.7477 | G25: 98.1352 | H25: 20,49 | I25: 1 755 (5) | J25: %
A26: 22 | B26: 22HFINhl | C26: KZPF00000538 | D26: ЦБ инвест. фондов | E26: Halyk Finance | F26: 53058.85 | G26: – | H26: – | I26: – | J26: KZT
A27: 23 | B27: 23HFINhp | C27: KZPF00000546 | D27: ЦБ инвест. фондов | E27: Halyk Finance | F27: 73829.27 | G27: – | H27: – | I27: – | J27: KZT
A28: 24 | B28: 24HFINhs | C28: KZPF00000520 | D28: ЦБ инвест. фондов | E28: Halyk Finance | F28: 72876.92 | G28: – | H28: – | I28: – | J28: KZT
A29: 25 | B29: 25HFINhv | C29: KZPF00000041 | D29: ЦБ инвест. фондов | E29: Halyk Finance | F29: 579760.2 | G29: – | H29: – | I29: – | J29: KZT
A30: 26 | B30: 26HSBK | C30: KZ000A0LE0S4 | D30: акции | E30: Народный Банк Казахстана | F30: 365.1 | G30: – | H30: – | I30: – | J30: KZT
A31: 27 | B31: 27HSBKd | C31: US46627J3023 | D31: производные ЦБ | E31: Народный Банк Казахстана | F31: 26.58 | G31: – | H31: – | I31: – | J31: USD
A32: 28 | B32: 28IFDR | C32: KZ1C00000256 | D32: акции | E32: Teniz Capital Investment Banking | F32: 9352.98 | G32: – | H32: – | I32: – | J32: KZT
A33: 29 | B33: 29KCEL | C33: KZ1C00000876 | D33: акции | E33: Kcell | F33: 3367.23 | G33: – | H33: – | I33: – | J33: KZT
A34: 30 | B34: 30KEGC | C34: KZ1C00000959 | D34: акции | E34: KEGOC | F34: 1440.97 | G34: – | H34: – | I34: – | J34: KZT
A35: 31 | B35: 31KFUSb45 | C35: KZ2C00008910 | D35: долговые ЦБ | E35: Казахстанский фонд устойчивости | F35: 99.9591 | G35: 107.2738 | H35: 17,31 | I35: 31 (0) | J35: %
A36: 32 | B36: 32KMGZ | C36: KZ1C00001122 | D36: акции | E36: Национальная компания "КазМунайГаз" | F36: 19970.03 | G36: – | H36: – | I36: – | J36: KZT
A37: 33 | B37: 33KMGZe12 | C37: XS1595714087 | D37: долговые ЦБ | E37: Национальная компания "КазМунайГаз" | F37: 90.6386 | G37: 92.715 | H37: 6,57 | I37: 7 790 (22) | J37: %
A38: 34 | B38: 34KMGZe14 | C38: XS1807300105 | D38: долговые ЦБ | E38: Национальная компания "КазМунайГаз" | F38: 102.027 | G38: 103.8933 | H38: 4,88 | I38: 1 675 (5) | J38: %
A39: 35 | B39: 35KMGZe15 | C39: XS1807299331 | D39: долговые ЦБ | E39: Национальная компания "КазМунайГаз" | F39: 96.7301 | G39: 98.9436 | H39: 6,65 | I39: 8 335 (23) | J39: %
A40: 36 | B40: 36KMGZe16 | C40: XS2242422397 | D40: долговые ЦБ | E40: Национальная компания "КазМунайГаз" | F40: 88.8219 | G40: 90.1344 | H40: 5,30 | I40: 2 745 (8) | J40: %
A41: 37 | B41: 37KSPI | C41: KZ1C00001536 | D41: акции | E41: Kaspi.kz | F41: 50124.3 | G41: – | H41: – | I41: – | J41: KZT
A42: 38 | B42: 38KSPId | C42: US48581R2058 | D42: производные ЦБ | E42: Kaspi.kz | F42: 93.33 | G42: – | H42: – | I42: – | J42: USD
A43: 39 | B43: 39KZAP | C43: KZ1C00001619 | D43: акции | E43: Национальная атомная компания "Казатомпром" | F43: 24115.22 | G43: – | H43: – | I43: – | J43: KZT
A44: 40 | B44: 40KZTCb3 | C44: KZ2C00012961 | D44: долговые ЦБ | E44: Jusan Mobile | F44: 102.8452 | G44: 112.7452 | H44: 20,49 | I44: 918 (3) | J44: %
A45: 41 | B45: 41KZTK | C45: KZ0009093241 | D45: акции | E45: Казахтелеком | F45: 41457.45 | G45: – | H45: – | I45: – | J45: KZT
A46: 42 | B46: 42KZTKp | C46: KZ0009094645 | D46: акции | E46: Казахтелеком | F46: 33407.91 | G46: – | H46: – | I46: – | J46: KZT
A47: 43 | B47: 43KZTO | C47: KZ1C00000744 | D47: акции | E47: КазТрансОйл | F47: 809.79 | G47: – | H47: – | I47: – | J47: KZT
A48: 44 | B48: 44KZ_23_3504 | C48: XS2914770545 | D48: ГЦБ | E48: Минфин | F48: 97.5 | G48: 99.3332 | H48: 5,05 | I48: 3 460 (10) | J48: %
A49: 45 | B49: 45MFLGb8 | C49: KZ2P00012883 | D49: долговые ЦБ | E49: Ломбард "GoldFinMarket" | F49: 98.72 | G49: 98.8867 | H49: 21,02 | I49: 537 (1) | J49: %
A50: 46 | B50: 46MFMCb2 | C50: KZ2P00011968 | D50: долговые ЦБ | E50: МФО MyCar Finance | F50: 98.865 | G50: 103.9692 | H50: 18,50 | I50: 435 (1) | J50: %
A51: 47 | B51: 47MFMOb10 | C51: KZ2P00012651 | D51: долговые ЦБ | E51: МФО "Mogo Kazakhstan (Мого Казахстан) | F51: 87.4755 | G51: 88.0422 | H51: 24,31 | I51: 433 (1) | J51: %
A52: 48 | B52: 48MFMOb17 | C52: KZ2P00013329 | D52: долговые ЦБ | E52: МФО "Mogo Kazakhstan (Мого Казахстан) | F52: 76.25 | G52: 76.5167 | H52: 72,23 | I52: 172 (0) | J52: %
A53: 49 | B53: 49MFMOb25 | C53: KZ2P00013220 | D53: долговые ЦБ | E53: МФО "Mogo Kazakhstan (Мого Казахстан) | F53: 99.999 | G53: 101.099 | H53: 22,00 | I53: 702 (2) | J53: %
A54: 50 | B54: 50MFMOb26 | C54: KZ2P00013204 | D54: долговые ЦБ | E54: МФО "Mogo Kazakhstan (Мого Казахстан) | F54: 95.0929 | G54: 95.5262 | H54: 15,27 | I54: 617 (2) | J54: %
A55: 51 | B55: 51MFMOb28 | C55: KZ2P00013352 | D55: долговые ЦБ | E55: МФО "Mogo Kazakhstan (Мого Казахстан) | F55: 96.0057 | G55: 96.3057 | H55: 14,53 | I55: 651 (2) | J55: %
A56: 52 | B56: 52MFMOb32 | C56: KZ2P00014590 | D56: долговые ЦБ | E56: МФО "Mogo Kazakhstan (Мого Казахстан) | F56: 99.999 | G56: 100.274 | H56: 11,00 | I56: 711 (2) | J56: %
A57: 53 | B57: 53MFOKb16 | C57: KZ2C00010171 | D57: долговые ЦБ | E57: МФО ОнлайнКазФинанс | F57: 100.2097 | G57: 101.1801 | H57: 22,23 | I57: 75 (0) | J57: %
A58: 54 | B58: 54MFOKb18 | C58: KZ2C00010478 | D58: долговые ЦБ | E58: МФО ОнлайнКазФинанс | F58: 99.0377 | G58: 99.2044 | H58: 21,58 | I58: 237 (1) | J58: %
A59: 55 | B59: 55MFOKb19 | C59: KZ2C00010825 | D59: долговые ЦБ | E59: МФО ОнлайнКазФинанс | F59: 99.5283 | G59: 99.8339 | H59: 10,33 | I59: 559 (2) | J59: %
... A176: 172 | B176: 172SKKZe1 | C176: XS2399149694 | D176: долговые ЦБ | E176: Фонд национального благосостояния "Самрук-Қазына | F176: 97.1933 | G176: 97.8655 | H176: 4,50 | I176: 419 (1) | J176: %

Sheet Риск цены за 29.08.25
A1: Дата оценки | C1: 45898
A3: № п/п | B3: Торговый код | C3: ISIN | D3: Алгоритмы и параметры расчета ЦБ | E3: Краткое наименование эмитента | F3: Расчетная цена | G3: Расчетная грязная | H3: Доходность до погашения. % годовых | I3: Дней до погашения | J3: Единица измерения цены
A4: 1 | B4: AAFD | C4: KZ1C00008721 | D4: Акции | E4: АО "АзияАгроФуд" | F4: 100 | G4: 100 | H4: 0 | I4: 0 | J4: KZT
A5: 2 | B5: AAL_KZ | C5: US02376R1023 | D5: Акции | E5: American Airlines | F5: 7051.0175 | G5: 7051.0175 | H5: 0 | I5: 0 | J5: KZT
A6: 3 | B6: AAPL_KZ | C6: US0378331005 | D6: Акции | E6: Apple Inc. | F6: 123902.21 | G6: 123902.21 | H6: 0 | I6: 0 | J6: KZT
A7: 4 | B7: ABK022_210 | C7: KZMJ00002103 | D7: Облигации | E7: Акимат Актюбинской области | F7: 100 | G7: 101.2396 | H7: 4.23 | I7: 375 | J7: %
A8: 5 | B8: ABK024_183 | C8: KZMJ00001832 | D8: Облигации | E8: Акимат Актюбинской области | F8: 100 | G8: 100.0885 | H8: 0.35 | I8: 269 | J8: %
A9: 6 | B9: ABK114_193 | C9: KZMJ00001931 | D9: Облигации | E9: Акимат Актюбинской области | F9: 100 | G9: 100.0185 | H9: 0.02 | I9: 3091 | J9: %
A10: 7 | B10: ABK119_006 | C10: KZMF00000069 | D10: Облигации | E10: Акимат Актюбинской области | F10: 100 | G10: 101.0844 | H10: 6.08 | I10: 1706 | J10: %
A11: 8 | B11: ABK119_081 | C11: KZMF00000812 | D11: Облигации | E11: Акимат Актюбинской области | F11: 100 | G11: 105.9561 | H11: 7.08 | I11: 2188 | J11: %
A12: 9 | B12: ABK131_021 | C12: KZMF00000218 | D12: Облигации | E12: Акимат Актюбинской области | F12: 100 | G12: 100.2542 | H12: 6.09 | I12: 2115 | J12: %
A13: 10 | B13: ABK143_032 | C13: KZMF00000325 | D13: Облигации | E13: Акимат Актюбинской области | F13: 100 | G13: 105.2019 | H13: 6.09 | I13: 2543 | J13: %
A14: 11 | B14: ABK143_033 | C14: KZMF00000333 | D14: Облигации | E14: Акимат Актюбинской области | F14: 100 | G14: 105.2019 | H14: 6.09 | I14: 2543 | J14: %
A15: 12 | B15: ABT_KZ | C15: US0028241000 | D15: Акции | E15: Abbott Lab. | F15: 70262.865 | G15: 70262.865 | H15: 0 | I15: 0 | J15: KZT
... A1012: 1009 | B1012: ZKK143_044 | C1012: KZMF00000440 | D1012: Облигации | E1012: Акимат Западно-Казахстанской области | F1012: 100 | G1012: 105.2019 | H1012: 6.09 | I1012: 2543 | J1012: %
