Workbook

Sheet ДУ
A1: Сентрас Секьюритиз | B1: 45890
A2: 1) Активы
A4: ЦБ
A5: Наименование эмитента и вид ЦБ | B5: ISIN | C5: Количество ЦБ | D5: Номинальная стоимость. тенге | E5: Ставка | F5: Дата зачисления/приобретения | G5: Дата погашения | H5: Чистая покупная стоимоcть | I5: Расчетная цена на 21.08.25 | J5: Расчетная грязная цена 21.08.25 | K5: Накопленный купон | L5: Суммарно-текущая рыночная стоимость | M5: Вес
A6: Министерство Финансов Республики Казахстан купонные МЕУКАМ | B6: KZKD00000535 | C6: =3250000-500000-500000-500000 -> 1750000 | D6: =3250000000-500000000-500000000-500000000 -> 1750000000 | E6: 5.49 | F6: 45491 | G6: 27.03.2027 | H6: =2755458875/3250000000*D6 -> 1483708625 | I6: =VLOOKUP(B6,'KASE за 21.08.25'!$C$5:$F$162,4,0) -> 84.7907 | J6: =VLOOKUP(B6,'KASE за 21.08.25'!$C$5:$G$162,5,0) -> 86.9867 | K6: 38430000 | L6: =D6*I6/100+K6 -> 1522267250 | M6: =L6/$L$61 -> 0.059054078 | N6: =D6*E6%/360 -> 266875 | O6: =K6+N6 -> 38696875
A7: Министерство Финансов Республики Казахстан купонные МЕУКАМ | B7: KZKD00001137 | C7: 1950000 | D7: 1950000000 | E7: 10.4 | F7: 45491 | G7: 12.04.2028 | H7: 1838876000 | I7: =VLOOKUP(B7,'KASE за 21.08.25'!$C$5:$F$162,4,0) -> 86.4944 | J7: =VLOOKUP(B7,'KASE за 21.08.25'!$C$5:$G$162,5,0) -> 90.2211 | K7: 72670000 | L7: =D7*I7/100+K7 -> 1759310800 | M7: =L7/$L$61 -> 0.068249828 | N7: =D7*E7%/360 -> 563333.33 | O7: =K7+N7 -> 73233333
A8: Министерство Финансов Республики Казахстан МЕУКАМ | B8: KZKD00001087 | C8: =1950000-202300-182000-187350 -> 1378350 | D8: =C8*1000 -> 1378350000 | E8: 11 | F8: 45491 | G8: 31.03.2029 | H8: =1855844250/1950000000*D8 -> 1.3117964e+09 | I8: =VLOOKUP(B8,'KASE за 21.08.25'!$C$5:$F$162,4,0) -> 84.5426 | J8: =VLOOKUP(B8,'KASE за 21.08.25'!$C$5:$G$162,5,0) -> 88.8509 | K8: 59383912 | L8: =D8*I8/100+K8 -> 1.2246768e+09 | M8: =L8/$L$61 -> 0.047509504 | N8: =D8*E8%/360 -> 421162.5 | O8: =K8+N8 -> 59805075
A9: Министерство Финансов Республики Казахстан купонные МЕУКАМ | B9: KZKD00001160 | C9: =1950000-225000-225000-208000-225000-225000 -> 842000 | D9: =C9*1000 -> 842000000 | E9: 10.55 | F9: 45491 | G9: 28.07.2029 | H9: =1504310166.66923/1500000000*D9 -> 8.4441944e+08 | I9: =VLOOKUP(B9,'KASE за 21.08.25'!$C$5:$F$162,4,0) -> 82.5526 | J9: =VLOOKUP(B9,'KASE за 21.08.25'!$C$5:$G$162,5,0) -> 83.2266 | K9: 5675313.9 | L9: =D9*I9/100+K9 -> 7.0076821e+08 | M9: =L9/$L$61 -> 0.027185253 | N9: =D9*E9%/360 -> 246752.78 | O9: =K9+N9 -> 5922066.7
A10: Министерство Финансов Республики Казахстан купонные МЕУКАМ | B10: KZKD00001129 | C10: 1450000 | D10: 1450000000 | E10: 10.3 | F10: 45491 | G10: 17.03.2031 | H10: 1.307499e+09 | I10: =VLOOKUP(B10,'KASE за 21.08.25'!$C$5:$F$162,4,0) -> 77.2344 | J10: =VLOOKUP(B10,'KASE за 21.08.25'!$C$5:$G$162,5,0) -> 81.6405 | K10: 63888611 | L10: =D10*I10/100+K10 -> 1.1837874e+09 | M10: =L10/$L$61 -> 0.04592326 | N10: =D10*E10%/360 -> 414861.11 | O10: =K10+N10 -> 64303472
A11: Министерство Финансов Республики Казахстан МЕУКАМ | B11: KZKD00000949 | C11: 1950000 | D11: 1950000000 | E11: 8.45 | F11: 45491 | G11: 16.04.2032 | H11: 1.5403351e+09 | I11: =VLOOKUP(B11,'KASE за 21.08.25'!$C$5:$F$162,4,0) -> 67.7713 | J11: =VLOOKUP(B11,'KASE за 21.08.25'!$C$5:$G$162,5,0) -> 70.7053 | K11: 57213542 | L11: =D11*I11/100+K11 -> 1.3787539e+09 | M11: =L11/$L$61 -> 0.053486692 | N11: =D11*E11%/360 -> 457708.33 | O11: =K11+N11 -> 57671250
A12: Министерство Финансов Республики Казахстан Купонные Облигации | B12: KZKD00001152 | C12: =1950000-250000-250000-250000-218000 -> 982000 | D12: =C12*1000 -> 982000000 | E12: 10.65 | F12: 45491 | G12: 26.07.2032 | H12: =1897171250/1950000000*D12 -> 9.5539598e+08 | I12: =VLOOKUP(B12,'KASE за 21.08.25'!$C$5:$F$162,4,0) -> 75.7581 | J12: =VLOOKUP(B12,'KASE за 21.08.25'!$C$5:$G$162,5,0) -> 76.4977 | K12: 7262708.3 | L12: =D12*I12/100+K12 -> 7.5120725e+08 | M12: =L12/$L$61 -> 0.02914196 | N12: =D12*E12%/360 -> 290508.33 | O12: =K12+N12 -> 7553216.7
A13: Министерство Финансов Республики Казахстан Купонные Облигации | B13: KZKD00001152 | C13: 250000 | D13: =C13*1000 -> 250000000 | E13: 10.65 | F13: 45673 | G13: 26.07.2032 | H13: =227969916.67/250000000*D13 -> 2.2796992e+08 | I13: =VLOOKUP(B13,'KASE за 21.08.25'!$C$5:$F$162,4,0) -> 75.7581 | J13: =VLOOKUP(B13,'KASE за 21.08.25'!$C$5:$G$162,5,0) -> 76.4977 | K13: 1848958.3 | L13: =D13*I13/100+K13 -> 1.9124421e+08 | M13: =L13/$L$61 -> 0.0074190327 | N13: =D13*E13%/360 -> 73958.333 | O13: =K13+N13 -> 1922916.7
A14: Министерство Финансов Республики Казахстан купонные МЕУКАМ | B14: KZKD00000741 | C14: 1950000 | D14: 1950000000 | E14: 8.07 | F14: 45491 | G14: 12.05.2034 | H14: 1425576750 | I14: =VLOOKUP(B14,'KASE за 21.08.25'!$C$5:$F$173,4,0) -> 61.42 | J14: =VLOOKUP(B14,'KASE за 21.08.25'!$C$5:$G$173,5,0) -> 63.6393 | K14: 43275375 | L14: =D14*I14/100+K14 -> 1240965375 | M14: =L14/$L$61 -> 0.048141393 | N14: =D14*E14%/360 -> 437125 | O14: =K14+N14 -> 43712500
A15: Министерство Финансов Республики Казахстан купонные МЕУКАМ | B15: KZKD00000832 | C15: 1950000 | D15: 1950000000 | E15: 8.07 | F15: 45491 | G15: 29.01.2035 | H15: 1449433375 | I15: =VLOOKUP(B15,'KASE за 21.08.25'!$C$5:$F$173,4,0) -> 59.9893 | J15: =VLOOKUP(B15,'KASE за 21.08.25'!$C$5:$G$173,5,0) -> 64.5175 | K15: 88299250 | L15: =D15*I15/100+K15 -> 1258090600 | M15: =L15/$L$61 -> 0.048805741 | N15: =D15*E15%/360 -> 437125 | O15: =K15+N15 -> 88736375
A16: Министерство Финансов Республики Казахстан купонные МЕУКАМ | B16: KZKD00000550 | C16: =312000-1 -> 311999 | D16: =C16*1000 -> 311999000 | E16: 5.5 | F16: 45509 | G16: 48328 | H16: 2.0448962e+08 | I16: =VLOOKUP(B16,'KASE за 21.08.25'!$C$5:$F$177,4,0) -> 56.4733 | J16: =VLOOKUP(B16,'KASE за 21.08.25'!$C$5:$G$177,5,0) -> 58.2608 | K16: 5576982.1 | L16: =D16*I16/100+K16 -> 1.8177311e+08 | M16: =L16/$L$61 -> 0.0070516157 | N16: =D16*E16%/360 -> 47666.514 | O16: =K16+N16 -> 5624648.6
A17: Министерство Финансов Республики Казахстан купонные МЕУКАМ | B17: KZKD00000550 | C17: 500000 | D17: 500000000 | E17: 5.5 | F17: 45532 | G17: 48328 | H17: 3.2653072e+08 | I17: =VLOOKUP(B17,'KASE за 21.08.25'!$C$5:$F$177,4,0) -> 56.4733 | J17: =VLOOKUP(B17,'KASE за 21.08.25'!$C$5:$G$177,5,0) -> 58.2608 | K17: 8937500 | L17: =D17*I17/100+K17 -> 291304000 | M17: =L17/$L$61 -> 0.011300702 | N17: =D17*E17%/360 -> 76388.889 | O17: =K17+N17 -> 9013888.9
A18: Министерство Финансов Республики Казахстан купонные МЕУКАМ | B18: KZKD00000550 | C18: 500000 | D18: 500000000 | E18: 5.5 | F18: 45566 | G18: 48328 | H18: 3.3409056e+08 | I18: =VLOOKUP(B18,'KASE за 21.08.25'!$C$5:$F$177,4,0) -> 56.4733 | J18: =VLOOKUP(B18,'KASE за 21.08.25'!$C$5:$G$177,5,0) -> 58.2608 | K18: 8937500 | L18: =D18*I18/100+K18 -> 291304000 | M18: =L18/$L$61 -> 0.011300702 | N18: =D18*E18%/360 -> 76388.889 | O18: =K18+N18 -> 9013888.9
A19: Министерство Финансов Республики Казахстан купонные МЕУКАМ | B19: KZKD00000550 | C19: 300000 | D19: =C19*1000 -> 300000000 | E19: 5.5 | F19: 45649 | G19: 48328 | H19: 2.0566557e+08 | I19: =VLOOKUP(B19,'KASE за 21.08.25'!$C$5:$F$177,4,0) -> 56.4733 | J19: =VLOOKUP(B19,'KASE за 21.08.25'!$C$5:$G$177,5,0) -> 58.2608 | K19: 5362500 | L19: =D19*I19/100+K19 -> 174782400 | M19: =L19/$L$61 -> 0.0067804215 | N19: =D19*E19%/360 -> 45833.333 | O19: =K19+N19 -> 5408333.3
A20: Министерство Финансов Республики Казахстан купонные МЕУКАМ | B20: KZKD00000550 | C20: 300000 | D20: =C20*1000 -> 300000000 | E20: 5.5 | F20: 45677 | G20: 48328 | H20: 2.0236587e+08 | I20: =VLOOKUP(B20,'KASE за 21.08.25'!$C$5:$F$177,4,0) -> 56.4733 | J20: =VLOOKUP(B20,'KASE за 21.08.25'!$C$5:$G$177,5,0) -> 58.2608 | K20: 5362500 | L20: =D20*I20/100+K20 -> 174782400 | M20: =L20/$L$61 -> 0.0067804215 | N20: =D20*E20%/360 -> 45833.333 | O20: =K20+N20 -> 5408333.3
A21: Министерство Финансов Республики Казахстан купонные МЕУКАМ | B21: KZKD00001160 | C21: 500000 | D21: =C21*1000 -> 500000000 | E21: 10.55 | F21: 45512 | G21: 28.07.2029 | H21: 4.5194078e+08 | I21: =VLOOKUP(B21,'KASE за 21.08.25'!$C$5:$F$162,4,0) -> 82.5526 | J21: =VLOOKUP(B21,'KASE за 21.08.25'!$C$5:$G$162,5,0) -> 83.2266 | K21: 3370138.9 | L21: =D21*I21/100+K21 -> 4.1613314e+08 | M21: =L21/$L$61 -> 0.016143262 | N21: =D21*E21%/360 -> 146527.78 | O21: =K21+N21 -> 3516666.7
A22: Министерство Финансов Республики Казахстан купонные МЕУКАМ | B22: KZKD00001160 | C22: 553430 | D22: =C22*1000 -> 553430000 | E22: 10.55 | F22: 45512 | G22: 28.07.2029 | H22: 4.9999941e+08 | I22: =VLOOKUP(B22,'KASE за 21.08.25'!$C$5:$F$162,4,0) -> 82.5526 | J22: =VLOOKUP(B22,'KASE за 21.08.25'!$C$5:$G$162,5,0) -> 83.2266 | K22: 3730271.9 | L22: =D22*I22/100+K22 -> 4.6060113e+08 | M22: =L22/$L$61 -> 0.017868331 | N22: =D22*E22%/360 -> 162185.74 | O22: =K22+N22 -> 3892457.7
A23: Министерство Финансов Республики Казахстан МЕУКАМ | B23: KZKD00000543 | C23: 636055 | D23: =C23*1000 -> 636055000 | E23: 5 | F23: 45519 | G23: 46861 | H23: 4.9999966e+08 | I23: =VLOOKUP(B23,'KASE за 21.08.25'!$C$5:$F$178,4,0) -> 75.6955 | J23: =VLOOKUP(B23,'KASE за 21.08.25'!$C$5:$G$178,5,0) -> 77.4038 | K23: 10865940 | L23: =D23*I23/100+K23 -> 4.9233095e+08 | M23: =L23/$L$61 -> 0.019099242 | N23: =D23*E23%/360 -> 88340.972 | O23: =K23+N23 -> 10954281
A24: Министерство Финансов Республики Казахстан купонные МЕУКАМ | B24: KZKD00000774 | C24: =715927-16841 -> 699086 | D24: =C24*1000 -> 699086000 | E24: 8.35 | F24: 45526 | G24: 50976 | H24: 4.8823782e+08 | I24: =VLOOKUP(B24,'KASE за 21.08.25'!$C$5:$F$173,4,0) -> 55.7025 | J24: =VLOOKUP(B24,'KASE за 21.08.25'!$C$5:$G$173,5,0) -> 56.3056 | K24: 4215877 | L24: =D24*I24/100+K24 -> 3.9362426e+08 | M24: =L24/$L$61 -> 0.015270064 | N24: =D24*E24%/360 -> 162149.11 | O24: =K24+N24 -> 4378026.1
A25: Министерство Финансов Республики Казахстан купонные МЕУКАМ | B25: KZKD00000774 | C25: 284073 | D25: =C25*1000 -> 284073000 | E25: 8.35 | F25: 45617 | G25: 50976 | H25: 2.0393645e+08 | I25: =VLOOKUP(B25,'KASE за 21.08.25'!$C$5:$F$173,4,0) -> 55.7025 | J25: =VLOOKUP(B25,'KASE за 21.08.25'!$C$5:$G$173,5,0) -> 56.3056 | K25: 1713118 | L25: =D25*I25/100+K25 -> 1.5994888e+08 | M25: =L25/$L$61 -> 0.0062049773 | N25: =D25*E25%/360 -> 65889.154 | O25: =K25+N25 -> 1779007.2
A26: Министерство Финансов Республики Казахстан МЕУКАМ | B26: KZKD00000840 | C26: 500000 | D26: =C26*1000 -> 500000000 | E26: 7.68 | F26: 45526 | G26: 47518 | H26: 417099000 | I26: =VLOOKUP(B26,'KASE за 21.08.25'!$C$5:$F$162,4,0) -> 72.3985 | J26: =VLOOKUP(B26,'KASE за 21.08.25'!$C$5:$G$162,5,0) -> 76.6012 | K26: 21013333 | L26: =D26*I26/100+K26 -> 3.8300583e+08 | M26: =L26/$L$61 -> 0.014858138 | N26: =D26*E26%/360 -> 106666.67 | O26: =K26+N26 -> 21120000
A27: Министерство Финансов Республики Казахстан МЕУКАМ | B27: KZKD00000840 | C27: 500000 | D27: =C27*1000 -> 500000000 | E27: 7.68 | F27: 45527 | G27: 47518 | H27: 4.1494417e+08 | I27: =VLOOKUP(B27,'KASE за 21.08.25'!$C$5:$F$162,4,0) -> 72.3985 | J27: =VLOOKUP(B27,'KASE за 21.08.25'!$C$5:$G$162,5,0) -> 76.6012 | K27: 21013333 | L27: =D27*I27/100+K27 -> 3.8300583e+08 | M27: =L27/$L$61 -> 0.014858138 | N27: =D27*E27%/360 -> 106666.67 | O27: =K27+N27 -> 21120000
A28: Министерство Финансов Республики Казахстан МЕУКАМ | B28: KZKD00000840 | C28: 500000 | D28: =C28*1000 -> 500000000 | E28: 7.68 | F28: 45561 | G28: 47518 | H28: 4.2179517e+08 | I28: =VLOOKUP(B28,'KASE за 21.08.25'!$C$5:$F$162,4,0) -> 72.3985 | J28: =VLOOKUP(B28,'KASE за 21.08.25'!$C$5:$G$162,5,0) -> 76.6012 | K28: 21013333 | L28: =D28*I28/100+K28 -> 3.8300583e+08 | M28: =L28/$L$61 -> 0.014858138 | N28: =D28*E28%/360 -> 106666.67 | O28: =K28+N28 -> 21120000
A29: Евразийский банк развития | B29: KZ2D00011863 | C29: 1700000 | D29: =C29*1000 -> 1700000000 | E29: 14.3 | F29: 45538 | G29: 46633 | H29: 1700000000 | I29: =VLOOKUP(B29,'Риск цены за 21.08.25'!$C$4:$G$963,4,0) -> 93.395032 | J29: =VLOOKUP(B29,'Риск цены за 21.08.25'!$C$4:$G$963,5,0) -> 107.21833 | K29: 2.3499667e+08 | L29: =D29*I29/100+K29 -> 1.8227122e+09 | M29: =L29/$L$61 -> 0.070709391 | N29: =D29*E29%/360 -> 675277.78 | O29: =K29+N29 -> 2.3567194e+08
A30: Министерство Финансов Республики Казахстан МЕУКАМ | B30: KZKD00001244 | C30: 500000 | D30: =C30*1000 -> 500000000 | E30: 12 | F30: 45540 | G30: 47901 | H30: 5.0216167e+08 | I30: =VLOOKUP(B30,'KASE за 21.08.25'!$C$5:$F$162,4,0) -> 83.0763 | J30: =VLOOKUP(B30,'KASE за 21.08.25'!$C$5:$G$162,5,0) -> 89.043 | K30: 29833333 | L30: =D30*I30/100+K30 -> 4.4521483e+08 | M30: =L30/$L$61 -> 0.017271443 | N30: =D30*E30%/360 -> 166666.67 | O30: =K30+N30 -> 30000000
A31: Министерство Финансов Республики Казахстан МЕУКАМ | B31: KZKD00001251 | C31: 300000 | D31: =C31*1000 -> 300000000 | E31: 12 | F31: 45547 | G31: 47549 | H31: 302854400 | I31: =VLOOKUP(B31,'KASE за 21.08.25'!$C$5:$F$162,4,0) -> 84.991 | J31: =VLOOKUP(B31,'KASE за 21.08.25'!$C$5:$G$162,5,0) -> 90.4577 | K31: 16400000 | L31: =D31*I31/100+K31 -> 271373000 | M31: =L31/$L$61 -> 0.010527509 | N31: =D31*E31%/360 -> 100000 | O31: =K31+N31 -> 16500000
A32: Министерство Финансов Республики Казахстан МЕУКАМ | B32: KZKD00001251 | C32: 288579 | D32: =C32*1000 -> 288579000 | E32: 12 | F32: 45582 | G32: 47549 | H32: 2.9999932e+08 | I32: =VLOOKUP(B32,'KASE за 21.08.25'!$C$5:$F$162,4,0) -> 84.991 | J32: =VLOOKUP(B32,'KASE за 21.08.25'!$C$5:$G$162,5,0) -> 90.4577 | K32: 15775652 | L32: =D32*I32/100+K32 -> 2.6104183e+08 | M32: =L32/$L$61 -> 0.010126727 | N32: =D32*E32%/360 -> 96193 | O32: =K32+N32 -> 15871845
A33: АО "Национальный управляющий холдинг "Байтерек" | B33: KZ2C00012698 | C33: 300000 | D33: =C33*1000 -> 300000000 | E33: 13.89 | F33: 45624 | G33: 46109 | H33: 300000000 | I33: =VLOOKUP(B33,'Риск цены за 21.08.25'!$C$4:$G$963,4,0) -> 98.061975 | J33: =VLOOKUP(B33,'Риск цены за 21.08.25'!$C$4:$G$963,5,0) -> 101.26437 | K33: 9607250 | L33: =D33*I33/100+K33 -> 3.0379317e+08 | M33: =L33/$L$61 -> 0.011785201 | N33: =D33*E33%/360 -> 115750 | O33: =K33+N33 -> 9723000
A34: Министерство Финансов Республики Казахстан МЕУКАМ | B34: KZKD00000964 | C34: =220000-213000 -> 7000 | D34: =C34*1000 -> 7000000 | E34: 8.44 | F34: 45639 | G34: 47978 | H34: =182967986.67/220000000*D34 -> 5821708.7 | I34: =VLOOKUP(B34,'KASE за 21.08.25'!$C$5:$F$162,4,0) -> 70.4404 | J34: =VLOOKUP(B34,'KASE за 21.08.25'!$C$5:$G$162,5,0) -> 72.8083 | K34: 165752.22 | L34: =D34*I34/100+K34 -> 5096580.2 | M34: =L34/$L$61 -> 0.0001977142 | N34: =D34*E34%/360 -> 1641.1111 | O34: =K34+N34 -> 167393.33
A35: Министерство Финансов Республики Казахстан МЕУКАМ | B35: KZKD00001236 | C35: =173000-163000 -> 10000 | D35: =C35*1000 -> 10000000 | E35: 14 | F35: 45639 | G35: 48353 | H35: =188266096.67/173000000*D35 -> 10882433 | I35: =VLOOKUP(B35,'KASE за 21.08.25'!$C$5:$F$162,4,0) -> 88.8671 | J35: =VLOOKUP(B35,'KASE за 21.08.25'!$C$5:$G$162,5,0) -> 92.4449 | K35: 357777.78 | L35: =D35*I35/100+K35 -> 9244487.8 | M35: =L35/$L$61 -> 0.00035862606 | N35: =D35*E35%/360 -> 3888.8889 | O35: =K35+N35 -> 361666.67
A36: Министерство Финансов Республики Казахстан МЕУКАМ | B36: KZKD00001079 | C36: 300000 | D36: =C36*1000 -> 300000000 | E36: 8.7 | F36: 45651 | G36: 50082 | H36: 237511300 | I36: =VLOOKUP(B36,'KASE за 21.08.25'!$C$5:$F$178,4,0) -> 59.8905 | J36: =VLOOKUP(B36,'KASE за 21.08.25'!$C$5:$G$178,5,0) -> 64.4822 | K36: 13775000 | L36: =D36*I36/100+K36 -> 193446500 | M36: =L36/$L$61 -> 0.0075044673 | N36: =D36*E36%/360 -> 72500 | O36: =K36+N36 -> 13847500
A37: Министерство Финансов Республики Казахстан МЕУКАМ | B37: KZKD00001079 | C37: 200000 | D37: =C37*1000 -> 200000000 | E37: 8.7 | F37: 45680 | G37: 50082 | H37: 157353400 | I37: =VLOOKUP(B37,'KASE за 21.08.25'!$C$5:$F$178,4,0) -> 59.8905 | J37: =VLOOKUP(B37,'KASE за 21.08.25'!$C$5:$G$178,5,0) -> 64.4822 | K37: 9183333.3 | L37: =D37*I37/100+K37 -> 1.2896433e+08 | M37: =L37/$L$61 -> 0.0050029782 | N37: =D37*E37%/360 -> 48333.333 | O37: =K37+N37 -> 9231666.7
A38: Министерство Финансов Республики Казахстан МЕУКАМ | B38: KZKD00001202 | C38: 263000 | D38: =C38*1000 -> 263000000 | E38: 11 | F38: 45656 | G38: 47518 | H38: 2.6372196e+08 | I38: =VLOOKUP(B38,'KASE за 21.08.25'!$C$5:$F$162,4,0) -> 82.1529 | J38: =VLOOKUP(B38,'KASE за 21.08.25'!$C$5:$G$162,5,0) -> 88.1723 | K38: 15831139 | L38: =D38*I38/100+K38 -> 2.3189327e+08 | M38: =L38/$L$61 -> 0.008995952 | N38: =D38*E38%/360 -> 80361.111 | O38: =K38+N38 -> 15911500
A39: Министерство Финансов Республики Казахстан МЕУКАМ | B39: KZKD00001210 | C39: 341000 | D39: =C39*1000 -> 341000000 | E39: 15.3 | F39: 45657 | G39: 47180 | H39: 396883762 | I39: =VLOOKUP(B39,'KASE за 21.08.25'!$C$5:$F$162,4,0) -> 95.4684 | J39: =VLOOKUP(B39,'KASE за 21.08.25'!$C$5:$G$162,5,0) -> 102.6084 | K39: 24347400 | L39: =D39*I39/100+K39 -> 349894644 | M39: =L39/$L$61 -> 0.013573639 | N39: =D39*E39%/360 -> 144925 | O39: =K39+N39 -> 24492325
A40: Министерство Финансов Республики Казахстан МЕУКАМ | B40: KZKD00001095 | C40: =214727-132000 -> 82727 | D40: =C40*1000 -> 82727000 | E40: 10.47 | F40: 45673 | G40: 47053 | H40: 77053072 | I40: =VLOOKUP(B40,'KASE за 21.08.25'!$C$5:$F$162,4,0) -> 84.6988 | J40: =VLOOKUP(B40,'KASE за 21.08.25'!$C$5:$G$162,5,0) -> 93.2493 | K40: 7073572.1 | L40: =D40*I40/100+K40 -> 77142348 | M40: =L40/$L$61 -> 0.0029926219 | N40: =D40*E40%/360 -> 24059.769 | O40: =K40+N40 -> 7097631.9
A41: Министерство Финансов Республики Казахстан МЕУКАМ | B41: KZKD00000790 | C41: 227500 | D41: =C41*1000 -> 227500000 | E41: 7.68 | F41: 45702 | G41: 47343 | H41: 1.8902823e+08 | I41: =VLOOKUP(B41,'KASE за 21.08.25'!$C$5:$F$162,4,0) -> 74.5958 | J41: =VLOOKUP(B41,'KASE за 21.08.25'!$C$5:$G$162,5,0) -> 74.7665 | K41: 388266.67 | L41: =D41*I41/100+K41 -> 1.7009371e+08 | M41: =L41/$L$61 -> 0.0065985308 | N41: =D41*E41%/360 -> 48533.333 | O41: =K41+N41 -> 436800
A42: Министерство Финансов Республики Казахстан | B42: KZKD00000717 | C42: 500000 | D42: =C42*1000 -> 500000000 | E42: 7.22 | F42: 45729 | G42: 47097 | H42: 3.9979333e+08 | I42: =VLOOKUP(B42,'KASE за 21.08.25'!$C$5:$F$162,4,0) -> 76.5458 | J42: =VLOOKUP(B42,'KASE за 21.08.25'!$C$5:$G$162,5,0) -> 81.5797 | K42: 25169722 | L42: =D42*I42/100+K42 -> 4.0789872e+08 | M42: =L42/$L$61 -> 0.01582382 | N42: =D42*E42%/360 -> 100277.78 | O42: =K42+N42 -> 25270000
A43: Министерство Финансов Республики Казахстан | B43: KZKD00001210 | C43: 259000 | D43: =C43*1000 -> 259000000 | E43: 15.3 | F43: 45750 | G43: 47180 | H43: 260647240 | I43: =VLOOKUP(B43,'KASE за 21.08.25'!$C$5:$F$162,4,0) -> 95.4684 | J43: =VLOOKUP(B43,'KASE за 21.08.25'!$C$5:$G$162,5,0) -> 102.6084 | K43: 18492600 | L43: =D43*I43/100+K43 -> 265755756 | M43: =L43/$L$61 -> 0.010309597 | N43: =D43*E43%/360 -> 110075 | O43: =K43+N43 -> 18602675
A44: АО "Национальный управляющий холдинг "Байтерек" | B44: KZ2C00012268 | C44: 200000 | D44: =C44*1000 -> 200000000 | E44: 16.7 | F44: 45757 | G44: 46122 | H44: 200000000 | I44: =VLOOKUP(B44,'Риск цены за 21.08.25'!$C$4:$G$963,4,0) -> 99.479215 | J44: =VLOOKUP(B44,'Риск цены за 21.08.25'!$C$4:$G$963,5,0) -> 105.55611 | K44: 12153889 | L44: =D44*I44/100+K44 -> 2.1111232e+08 | M44: =L44/$L$61 -> 0.0081897863 | N44: =D44*E44%/360 -> 92777.778 | O44: =K44+N44 -> 12246667
A45: Министерство Финансов Республики Казахстан | B45: KZKD00000477 | C45: 500000 | D45: =C45*1000 -> 500000000 | E45: 5.3 | F45: 45764 | G45: 46679 | H45: 4.1207678e+08 | I45: =VLOOKUP(B45,'KASE за 21.08.25'!$C$5:$F$162,4,0) -> 79.9894 | J45: =VLOOKUP(B45,'KASE за 21.08.25'!$C$5:$G$162,5,0) -> 84.4355 | K45: 22230556 | L45: =D45*I45/100+K45 -> 4.2217756e+08 | M45: =L45/$L$61 -> 0.016377746 | N45: =D45*E45%/360 -> 73611.111 | O45: =K45+N45 -> 22304167
A46: Министерство Финансов Республики Казахстан | B46: KZKD00001202 | C46: 737000 | D46: =C46*1000 -> 737000000 | E46: 11 | F46: 45771 | G46: 47518 | H46: 6.4967099e+08 | I46: =VLOOKUP(B46,'KASE за 21.08.25'!$C$5:$F$162,4,0) -> 82.1529 | J46: =VLOOKUP(B46,'KASE за 21.08.25'!$C$5:$G$162,5,0) -> 88.1723 | K46: 44363306 | L46: =D46*I46/100+K46 -> 6.4983018e+08 | M46: =L46/$L$61 -> 0.025209189 | N46: =D46*E46%/360 -> 225194.44 | O46: =K46+N46 -> 44588500
A47: Министерство Финансов Республики Казахстан | B47: KZKD00001129 | C47: 6000 | D47: =C47*1000 -> 6000000 | E47: 10.3 | F47: 45775 | G47: 47924 | H47: 4822485.3 | I47: =VLOOKUP(B47,'KASE за 21.08.25'!$C$5:$F$162,4,0) -> 77.2344 | J47: =VLOOKUP(B47,'KASE за 21.08.25'!$C$5:$G$162,5,0) -> 81.6405 | K47: 264366.67 | L47: =D47*I47/100+K47 -> 4898430.7 | M47: =L47/$L$61 -> 0.00019002728 | N47: =D47*E47%/360 -> 1716.6667 | O47: =K47+N47 -> 266083.33
A48: Министерство Финансов Республики Казахстан | B48: KZKD00001129 | C48: 6000 | D48: =C48*1000 -> 6000000 | E48: 10.3 | F48: 45775 | G48: 47924 | H48: 4841157.3 | I48: =VLOOKUP(B48,'KASE за 21.08.25'!$C$5:$F$162,4,0) -> 77.2344 | J48: =VLOOKUP(B48,'KASE за 21.08.25'!$C$5:$G$162,5,0) -> 81.6405 | K48: 264366.67 | L48: =D48*I48/100+K48 -> 4898430.7 | M48: =L48/$L$61 -> 0.00019002728 | N48: =D48*E48%/360 -> 1716.6667 | O48: =K48+N48 -> 266083.33
A49: АО "Банк Развития Казахстана" | B49: KZ2C00010106 | C49: 500000 | D49: =C49*1000 -> 500000000 | E49: 17 | F49: 45782 | G49: 46147 | H49: 500000000 | I49: 100 | J49: 100 | K49: 25027778 | L49: =D49*I49/100+K49 -> 5.2502778e+08 | M49: =L49/$L$61 -> 0.020367666 | N49: =D49*E49%/360 -> 236111.11 | O49: =K49+N49 -> 25263889
A50: Министерство Финансов Республики Казахстан | B50: KZKD00000964 | C50: 500000 | D50: =C50*1000 -> 500000000 | E50: 8.44 | F50: 45799 | G50: 47978 | H50: 3.7223717e+08 | I50: =VLOOKUP(B50,'KASE за 21.08.25'!$C$5:$F$165,4,0) -> 70.4404 | J50: =VLOOKUP(B50,'KASE за 21.08.25'!$C$5:$G$165,5,0) -> 72.8083 | K50: 11839444 | L50: =D50*I50/100+K50 -> 3.6404144e+08 | M50: =L50/$L$61 -> 0.014122443 | N50: =D50*E50%/360 -> 117222.22 | O50: =K50+N50 -> 11956667
A51: Министерство Финансов Республики Казахстан | B51: KZKD00000790 | C51: 500000 | D51: =C51*1000 -> 500000000 | E51: 7.68 | F51: 45813 | G51: 47343 | H51: 4.0360417e+08 | I51: =VLOOKUP(B51,'KASE за 21.08.25'!$C$5:$F$165,4,0) -> 74.5958 | J51: =VLOOKUP(B51,'KASE за 21.08.25'!$C$5:$G$165,5,0) -> 74.7665 | K51: 853333.33 | L51: =D51*I51/100+K51 -> 3.7383233e+08 | M51: =L51/$L$61 -> 0.014502266 | N51: =D51*E51%/360 -> 106666.67 | O51: =K51+N51 -> 960000
A52: Министерство Финансов Республики Казахстан | B52: KZKD00000543 | C52: 500000 | D52: =C52*1000 -> 500000000 | E52: 5 | F52: 45813 | G52: 46861 | H52: 3.7940239e+08 | I52: =VLOOKUP(B52,'KASE за 21.08.25'!$C$5:$F$165,4,0) -> 75.6955 | J52: =VLOOKUP(B52,'KASE за 21.08.25'!$C$5:$G$165,5,0) -> 77.4038 | K52: 8541666.7 | L52: =D52*I52/100+K52 -> 3.8701917e+08 | M52: =L52/$L$61 -> 0.015013829 | N52: =D52*E52%/360 -> 69444.444 | O52: =K52+N52 -> 8611111.1
A53: Министерство Финансов Республики Казахстан | B53: KZKD00001160 | C53: 200000 | D53: =C53*1000 -> 200000000 | E53: 10.55 | F53: 45820 | G53: 47327 | H53: 1.8266529e+08 | I53: =VLOOKUP(B53,'KASE за 21.08.25'!$C$5:$F$165,4,0) -> 82.5526 | J53: =VLOOKUP(B53,'KASE за 21.08.25'!$C$5:$G$165,5,0) -> 83.2266 | K53: 1348055.6 | L53: =D53*I53/100+K53 -> 1.6645326e+08 | M53: =L53/$L$61 -> 0.0064573048 | N53: =D53*E53%/360 -> 58611.111 | O53: =K53+N53 -> 1406666.7
A54: Министерство Финансов Республики Казахстан | B54: KZKD00001251 | C54: 500000 | D54: =C54*1000 -> 500000000 | E54: 12 | F54: 45832 | G54: 47549 | H54: 4.4701683e+08 | I54: =VLOOKUP(B54,'KASE за 21.08.25'!$C$5:$F$165,4,0) -> 84.991 | J54: =VLOOKUP(B54,'KASE за 21.08.25'!$C$5:$G$165,5,0) -> 90.4577 | K54: 27333333 | L54: =D54*I54/100+K54 -> 4.5228833e+08 | M54: =L54/$L$61 -> 0.017545849 | N54: =D54*E54%/360 -> 166666.67 | O54: =K54+N54 -> 27500000
A55: Министерство Финансов Республики Казахстан | B55: KZKD00001251 | C55: 500000 | D55: =C55*1000 -> 500000000 | E55: 12 | F55: 45832 | G55: 47549 | H55: 4.4561733e+08 | I55: =VLOOKUP(B55,'KASE за 21.08.25'!$C$5:$F$165,4,0) -> 84.991 | J55: =VLOOKUP(B55,'KASE за 21.08.25'!$C$5:$G$165,5,0) -> 90.4577 | K55: 27333333 | L55: =D55*I55/100+K55 -> 4.5228833e+08 | M55: =L55/$L$61 -> 0.017545849 | N55: =D55*E55%/360 -> 166666.67 | O55: =K55+N55 -> 27500000
A56: Министерство Финансов Республики Казахстан | B56: KZKD00001251 | C56: 411421 | D56: =C56*1000 -> 411421000 | E56: 12 | F56: 45832 | G56: 47549 | H56: 3.6376844e+08 | I56: =VLOOKUP(B56,'KASE за 21.08.25'!$C$5:$F$165,4,0) -> 84.991 | J56: =VLOOKUP(B56,'KASE за 21.08.25'!$C$5:$G$165,5,0) -> 90.4577 | K56: 22491015 | L56: =D56*I56/100+K56 -> 3.7216184e+08 | M56: =L56/$L$61 -> 0.014437461 | N56: =D56*E56%/360 -> 137140.33 | O56: =K56+N56 -> 22628155
A57: Министерство Финансов Республики Казахстан | B57: KZKD00001301 | C57: =500000-271261 -> 228739 | D57: =C57*1000 -> 228739000 | E57: 14.45 | F57: 45848 | G57: 48735 | H57: 2.0742821e+08 | I57: =VLOOKUP(B57,'KASE за 21.08.25'!$C$5:$F$174,4,0) -> 89.9485 | J57: =VLOOKUP(B57,'KASE за 21.08.25'!$C$5:$G$174,5,0) -> 92.9991 | K57: 6977810.3 | L57: =D57*I57/100+K57 -> 2.1272511e+08 | M57: =L57/$L$61 -> 0.0082523521 | N57: =D57*E57%/360 -> 91813.293 | O57: =K57+N57 -> 7069623.6
A58: Министерство Финансов Республики Казахстан | B58: KZKD00000964 | C58: 500000 | D58: =C58*1000 -> 500000000 | E58: 8.44 | F58: 45862 | G58: 47978 | H58: 3.5788194e+08 | I58: =VLOOKUP(B58,'KASE за 21.08.25'!$C$5:$F$174,4,0) -> 70.4404 | J58: =VLOOKUP(B58,'KASE за 21.08.25'!$C$5:$G$174,5,0) -> 72.8083 | K58: 11839444 | L58: =D58*I58/100+K58 -> 3.6404144e+08 | M58: =L58/$L$61 -> 0.014122443 | N58: =D58*E58%/360 -> 117222.22 | O58: =K58+N58 -> 11956667
A59: Министерство Финансов Республики Казахстан | B59: KZKD00001301 | C59: 500000 | D59: =C59*1000 -> 500000000 | E59: 14.45 | F59: 45883 | G59: 48735 | H59: 4.6018642e+08 | I59: =VLOOKUP(B59,'KASE за 21.08.25'!$C$5:$F$174,4,0) -> 89.9485 | J59: =VLOOKUP(B59,'KASE за 21.08.25'!$C$5:$G$174,5,0) -> 92.9991 | K59: 15252778 | L59: =D59*I59/100+K59 -> 4.6499528e+08 | M59: =L59/$L$61 -> 0.018038795 | N59: =D59*E59%/360 -> 200694.44 | O59: =K59+N59 -> 15453472
A60: Министерство Финансов Республики Казахстан | B60: KZKD00000774 | C60: 16841 | D60: =C60*1000 -> 16841000 | E60: 8.35 | F60: 45890 | G60: 50976 | H60: 9465392.4 | I60: =VLOOKUP(B60,'KASE за 21.08.25'!$C$5:$F$174,4,0) -> 55.7025 | J60: =VLOOKUP(B60,'KASE за 21.08.25'!$C$5:$G$174,5,0) -> 56.3056 | K60: 101560.59 | L60: =D60*I60/100+K60 -> 9482418.6 | M60: =L60/$L$61 -> 0.00036785623 | N60: =D60*E60%/360 -> 3906.1764 | O60: =K60+N60 -> 105466.77
A61: ИТОГО | C61: =SUM(C6:C60) -> 32121800 | D61: =SUM(D6:D60) -> 32121800000 | H61: =SUM(H6:H60) -> 2.7560502e+10 | K61: =SUM(K6:K60) -> 1.2186735e+09 | L61: =SUM(L6:L60) -> 2.5777513e+10 | M61: =SUM(M6:M60) -> 1
A63: Остатки на инвест. cчетах
A64: KZT | B64: 1239151.5
A66: Обратное репо
A67: Наименование эмитента и вид ЦБ | B67: НИН (ISIN) | C67: Количество | D67: Валюта | E67: Дата открытия | F67: Дата закрытия | G67: Цена открытия | H67: Цена закрытия | I67: Сумма открытия операции. в тг | J67: Сумма закрытия операции. в тг | K67: Ставка доходности. % | L67: Сумма начисленного вознагрждения | M67: Суммарная текущая стоимость. в тг
A68: Министерство Финансов Республики Казахстан | B68: KZKD00001095 | C68: 212652 | D68: KZT | E68: 45889 | F68: 45890 | G68: 931.947 | H68: 932.34278 | I68: 1.9818039e+08 | J68: 1.9826456e+08 | K68: 15.5007 | L68: =IF(($B$1-E68)=0,0,(J68-I68)/(F68-E68)*($B$1-E68)) -> 84162.6 | M68: =IF((F68=$B$1),0,(I68+L68)) -> 0
A69: Министерство Финансов Республики Казахстан | B69: XS1263139856 | C69: 2440113 | D69: KZT | E69: 45889 | F69: 45890 | G69: 591.575 | H69: 591.82623 | I69: 1.4435098e+09 | J69: 1444122873 | K69: 15.5007 | L69: =IF(($B$1-E69)=0,0,(J69-I69)/(F69-E69)*($B$1-E69)) -> 613025.02 | M69: =IF((F69=$B$1),0,(I69+L69)) -> 0
A70: Министерство Финансов Республики Казахстан | B70: XS1263139856 | C70: 16910 | D70: KZT | E70: 45889 | F70: 45890 | G70: 591.575 | H70: 591.82623 | I70: 10003533 | J70: 10007782 | K70: 15.500709 | L70: =IF(($B$1-E70)=0,0,(J70-I70)/(F70-E70)*($B$1-E70)) -> 4248.27 | M70: =IF((F70=$B$1),0,(I70+L70)) -> 0
A71: Министерство Финансов Республики Казахстан | B71: KZKD00001095 | C71: 1761866 | D71: KZT | E71: 45890 | F71: 45891 | G71: 932.493 | H71: 932.88902 | I71: 1.6429277e+09 | J71: 1.6436254e+09 | K71: 15.501 | L71: =IF(($B$1-E71)=0,0,(J71-I71)/(F71-E71)*($B$1-E71)) -> 0 | M71: =IF((F71=$B$1),0,(I71+L71)) -> 1.6429277e+09
A72: Министерство Финансов Республики Казахстан | B72: KZKD00001095 | C72: 9657 | D72: KZT | E72: 45890 | F72: 45891 | G72: 932.493 | H72: 932.88902 | I72: 9005084.9 | J72: 9008909.2 | K72: 15.500984 | L72: =IF(($B$1-E72)=0,0,(J72-I72)/(F72-E72)*($B$1-E72)) -> 0 | M72: =IF((F72=$B$1),0,(I72+L72)) -> 9005084.9
A74: ИТОГО | C74: =SUM(C68:C72) -> 4441198 | I74: =SUM(I68:I72) -> 3.3036266e+09 | J74: =SUM(J68:J72) -> 3.3050296e+09 | L74: =SUM(L68:L72) -> 701435.89 | M74: =SUM(M68:M72) -> 1.6519328e+09
A77: Прочие активы (дебиторская задолженность. деньги в пути)
A78: № п/п | B78: Наименование | C78: Валюта | D78: Дата постановки на учет | E78: Количество | F78: Остаток в валюте | G78: Остаток в тенге
A80: ИТОГО | G80: =SUM(G79:G79) -> 0
A82: Итого активов | B82: =L61+B64+M74+G80 -> 2.7430685e+10
A86: 2) Кредиторская задолженность Фонда
A87: Комиссия ДУ (за управление) | B87: =4020961.36-4020961.36 -> 0
A88: Комиссия ДУ (сверхдоходность)
A89: Комиссия Кастоди | B89: =2000+3000+5000+7000+2000+4000+3000+5000+2000+3000+3000+2000+2000+24000+2000+6000+2000+2000+2000+2000+351673.18+71000+2000+6000+2000+3000+2000+3000+2000+2000+2000+2000-434673.18+2000+2000+2000+2000+2000+3000+3000+4000+3000+2000+2000+342960.79+2000+2000+12000+2000+2000+2000+2000+3000+12000+3000+2000+5000-466960.79+3000+3000+4000 -> 59000
A90: Комиссия Глобал кастоди
A91: Комиссия Центрального Депозитария | B91: =365447.82+31954.05 -> 397401.87
A92: Клиринговый сбор | B92: =4083.63+3230.48+3265.02+12872.21+3281.52+3247.37+2574.32+7640.52+2575.08+2576.75+2575.88+2577.32+7662+2583.06+2582.99+2585.09+2053.2+6452.61+2743.63+2707.86+2708.65+2708.58+8059.51+2714.35+2877.07+2713.89+2715.72+8083.12+2715.44+2722.26+2808.08+2127.48+6288.59+2125.07+15057.91+2501.85+3003.68 -> 151801.79
A93: Комиссия биржи | B93: =1606.55+1607.59+1608.19+6436.1+1611.94+1612.29+46613.68+3820.27+1275.38+1275.47+1276.53+1276.5+3831+1278.62+1279.34+1280.38+36800.38+3224.64+1340.74+1341.77+1342.17+1342.88+4029.76+1345.03+1345.6+1346.29+1346.45+4041.56+1348.56+1349.73+1391.91-123082.41+47065.72+3144.3+1048.87+26352.67+1238.77+3185.44 -> 99580.66
A94: Комиссия брокера
A95: Кредиторская задолженность (прочая комиссия)
A96: Остаток прочих обязательств на конец дня
A97: Итого | B97: =SUM(B87:B96) -> 707784.32

Sheet KASE за 21.08.25
A1: Дата оценки | B1: 45890
A3: № п/п | B3: Код | C3: ISIN | D3: Вид ценной бумаги | E3: Компания | F3: Рыночная цена | G3: Рыночная "грязная" цена | H3: Доходность до погашения, % годовых | I3: Срок до погашения | J3: Единица измерения цены
A5: 1 | B5: 1AIRA | C5: KZ1C00004050 | D5: акции | E5: Эйр Астана | F5: 757.2 | G5: – | H5: – | I5: – | J5: KZT
A6: 2 | B6: 2AIRAd | C6: US0090632078 | D6: производные ЦБ | E6: Эйр Астана | F6: 5.72 | G6: – | H6: – | I6: – | J6: USD
A7: 3 | B7: 3AKZM | C7: KZ1C00001288 | D7: акции | E7: Актюбинский завод металлоконструкций | F7: 6266.18 | G7: – | H7: – | I7: – | J7: KZT
A8: 4 | B8: 4ALMSb1 | C8: KZ2C00012953 | D8: долговые ЦБ | E8: АК Алтыналмас | F8: 100.0091 | G8: 101.2313 | H8: 7,99 | I8: 845 (2) | J8: %
A9: 5 | B9: 5ASBN | C9: KZ000A0F4546 | D9: акции | E9: ForteBank | F9: 24.59 | G9: – | H9: – | I9: – | J9: KZT
A10: 6 | B10: 6ASKQb1 | C10: KZ2C00010155 | D10: долговые ЦБ | E10: ALTYN SAMRUK QAZAQSTAN | F10: 93.1627 | G10: 95.1627 | H10: 15,04 | I10: 460 (1) | J10: %
A11: 7 | B11: 7BCCIbe | C11: KZPF00000553 | D11: ЦБ инвест. фондов | E11: BCC Invest | F11: 1461.81 | G11: – | H11: – | I11: – | J11: KZT
A12: 8 | B12: 8BCCIrb | C12: KZPF00000231 | D12: ЦБ инвест. фондов | E12: BCC Invest | F12: 6.92 | G12: – | H12: – | I12: – | J12: KZT
A13: 9 | B13: 9BIGDb5 | C13: KZ2D00012861 | D13: долговые ЦБ | E13: Частная компания BI Development Ltd. | F13: 99.8925 | G13: 104.3342 | H13: 19,50 | I13: 638 (2) | J13: %
A14: 10 | B14: 10BRKZe18 | C14: XS3032932645 | D14: долговые ЦБ | E14: Банк Развития Казахстана | F14: 102.4113 | G14: 104.5051 | H14: 5,03 | I14: 1 666 (5) | J14: %
A15: 11 | B15: 11BRKZe4 | C15: XS0248160102 | D15: долговые ЦБ | E15: Банк Развития Казахстана | F15: 99.9837 | G15: 102.4504 | H15: 6,02 | I15: 212 (1) | J15: %
A16: 12 | B16: 12BTRKe1 | C16: XS3067899610 | D16: долговые ЦБ | E16: Национальный управляющий холдинг "Байтерек" | F16: 101.1606 | G16: 102.7199 | H16: 4,98 | I16: 977 (3) | J16: %
A17: 13 | B17: 13CCBN | C17: KZ0007786572 | D17: акции | E17: Банк ЦентрКредит | F17: 4586.1 | G17: – | H17: – | I17: – | J17: KZT
A18: 14 | B18: 14CCBNp | C18: KZ000A0H0930 | D18: акции | E18: Банк ЦентрКредит | F18: 6515.65 | G18: – | H18: – | I18: – | J18: KZT
A19: 15 | B19: 15CSECfe | C19: KZPF00000025 | D19: ЦБ инвест. фондов | E19: Сентрас Секьюритиз | F19: 5899704 | G19: – | H19: – | I19: – | J19: KZT
A20: 16 | B20: 16CSECtf | C20: KZPF00000280 | D20: ЦБ инвест. фондов | E20: Сентрас Секьюритиз | F20: 1749268 | G20: – | H20: – | I20: – | J20: KZT
A21: 17 | B21: 17EABRb40 | C21: KZ2D00009628 | D21: ЦБ МФО | E21: Евразийский банк развития | F21: 99.7542 | G21: 102.1534 | H21: 6,15 | I21: 209 (1) | J21: %
A22: 18 | B22: 18EABRb42 | C22: KZ2D00009222 | D22: ЦБ МФО | E22: Евразийский банк развития | F22: 100 | G22: 107.8801 | H22: 16,25 | I22: 918 (3) | J22: %
A23: 19 | B23: 19EABRb53 | C23: KZ2D00013620 | D23: ЦБ МФО | E23: Евразийский банк развития | F23: 100 | G23: 107.0479 | H23: 17,47 | I23: 949 (3) | J23: %
A24: 20 | B24: 20FFIN_or | C24: KZPF00000082 | D24: ЦБ инвест. фондов | E24: Фридом Финанс | F24: 89463.69 | G24: – | H24: – | I24: – | J24: KZT
A25: 21 | B25: 21FFINgw | C25: KZPF00000090 | D25: ЦБ инвест. фондов | E25: Фридом Финанс | F25: 5456.72 | G25: – | H25: – | I25: – | J25: KZT
A26: 22 | B26: 22FHJIag | C26: KZPF00000132 | D26: ЦБ инвест. фондов | E26: Alatau City Invest | F26: 1039.45 | G26: – | H26: – | I26: – | J26: USD
A27: 23 | B27: 23FHJIpc | C27: KZPF00000140 | D27: ЦБ инвест. фондов | E27: Alatau City Invest | F27: 1162.15 | G27: – | H27: – | I27: – | J27: USD
A28: 24 | B28: 24HCBNb13 | C28: KZ2C00011195 | D28: долговые ЦБ | E28: Home Credit Bank | F28: 99.7899 | G28: 108.5624 | H28: 18,25 | I28: 906 (3) | J28: %
A29: 25 | B29: 25HFINhl | C29: KZPF00000538 | D29: ЦБ инвест. фондов | E29: Halyk Finance | F29: 53333.1 | G29: – | H29: – | I29: – | J29: KZT
A30: 26 | B30: 26HFINhp | C30: KZPF00000546 | D30: ЦБ инвест. фондов | E30: Halyk Finance | F30: 74138.19 | G30: – | H30: – | I30: – | J30: KZT
A31: 27 | B31: 27HFINhs | C31: KZPF00000520 | D31: ЦБ инвест. фондов | E31: Halyk Finance | F31: 73194.28 | G31: – | H31: – | I31: – | J31: KZT
A32: 28 | B32: 28HFINhv | C32: KZPF00000041 | D32: ЦБ инвест. фондов | E32: Halyk Finance | F32: 582200.46 | G32: – | H32: – | I32: – | J32: KZT
A33: 29 | B33: 29HSBK | C33: KZ000A0LE0S4 | D33: акции | E33: Народный Банк Казахстана | F33: 370.45 | G33: – | H33: – | I33: – | J33: KZT
A34: 30 | B34: 30HSBKd | C34: US46627J3023 | D34: производные ЦБ | E34: Народный Банк Казахстана | F34: 27.01 | G34: – | H34: – | I34: – | J34: USD
A35: 31 | B35: 31IFDR | C35: KZ1C00000256 | D35: акции | E35: Teniz Capital Investment Banking | F35: 9351 | G35: – | H35: – | I35: – | J35: KZT
A36: 32 | B36: 32KCEL | C36: KZ1C00000876 | D36: акции | E36: Kcell | F36: 3385.5 | G36: – | H36: – | I36: – | J36: KZT
A37: 33 | B37: 33KEGC | C37: KZ1C00000959 | D37: акции | E37: KEGOC | F37: 1441.94 | G37: – | H37: – | I37: – | J37: KZT
A38: 34 | B38: 34KFUSb45 | C38: KZ2C00008910 | D38: долговые ЦБ | E38: Казахстанский фонд устойчивости | F38: 99.9497 | G38: 106.8739 | H38: 17,32 | I38: 39 (0) | J38: %
A39: 35 | B39: 35KMGZ | C39: KZ1C00001122 | D39: акции | E39: Национальная компания "КазМунайГаз" | F39: 19914.17 | G39: – | H39: – | I39: – | J39: KZT
A40: 36 | B40: 36KMGZe12 | C40: XS1595714087 | D40: долговые ЦБ | E40: Национальная компания "КазМунайГаз" | F40: 90.2278 | G40: 92.1764 | H40: 6,60 | I40: 7 798 (22) | J40: %
A41: 37 | B41: 37KMGZe14 | C41: XS1807300105 | D41: долговые ЦБ | E41: Национальная компания "КазМунайГаз" | F41: 101.7763 | G41: 103.5232 | H41: 4,94 | I41: 1 683 (5) | J41: %
A42: 38 | B42: 38KMGZe15 | C42: XS1807299331 | D42: долговые ЦБ | E42: Национальная компания "КазМунайГаз" | F42: 96.068 | G42: 98.1399 | H42: 6,71 | I42: 8 343 (23) | J42: %
A43: 39 | B43: 39KMGZe16 | C43: XS2242422397 | D43: долговые ЦБ | E43: Национальная компания "КазМунайГаз" | F43: 88.4348 | G43: 89.6695 | H43: 5,36 | I43: 2 753 (8) | J43: %
A44: 40 | B44: 40KSPI | C44: KZ1C00001536 | D44: акции | E44: Kaspi.kz | F44: 51278.79 | G44: – | H44: – | I44: – | J44: KZT
A45: 41 | B45: 41KSPId | C45: US48581R2058 | D45: производные ЦБ | E45: Kaspi.kz | F45: 96.11 | G45: – | H45: – | I45: – | J45: USD
A46: 42 | B46: 42KZAP | C46: KZ1C00001619 | D46: акции | E46: Национальная атомная компания "Казатомпром" | F46: 23961.74 | G46: – | H46: – | I46: – | J46: KZT
A47: 43 | B47: 43KZTCb3 | C47: KZ2C00012961 | D47: долговые ЦБ | E47: Jusan Mobile | F47: 102.8477 | G47: 112.2588 | H47: 20,49 | I47: 926 (3) | J47: %
A48: 44 | B48: 44KZTK | C48: KZ0009093241 | D48: акции | E48: Казахтелеком | F48: 41224.26 | G48: – | H48: – | I48: – | J48: KZT
A49: 45 | B49: 45KZTKp | C49: KZ0009094645 | D49: акции | E49: Казахтелеком | F49: 33977.85 | G49: – | H49: – | I49: – | J49: KZT
A50: 46 | B50: 46KZTO | C50: KZ1C00000744 | D50: акции | E50: КазТрансОйл | F50: 808.03 | G50: – | H50: – | I50: – | J50: KZT
A51: 47 | B51: 47KZ_23_3504 | C51: XS2914770545 | D51: ГЦБ | E51: Минфин | F51: 97.5 | G51: 99.2285 | H51: 5,04 | I51: 3 468 (10) | J51: %
A52: 48 | B52: 48MFKTb4 | C52: KZ2P00010002 | D52: долговые ЦБ | E52: МФО "Кредит Time" | F52: 100 | G52: 103.3889 | H52: 19,99 | I52: 1 109 (3) | J52: %
A53: 49 | B53: 49MFMCb2 | C53: KZ2P00011968 | D53: долговые ЦБ | E53: МФО MyCar Finance | F53: 98.846 | G53: 103.5613 | H53: 18,50 | I53: 443 (1) | J53: %
A54: 50 | B54: 50MFMOb10 | C54: KZ2P00012651 | D54: долговые ЦБ | E54: МФО "Mogo Kazakhstan (Мого Казахстан) | F54: 82.3171 | G54: 82.6171 | H54: 29,74 | I54: 441 (1) | J54: %
A55: 51 | B55: 51MFMOb17 | C55: KZ2P00013329 | D55: долговые ЦБ | E55: МФО "Mogo Kazakhstan (Мого Казахстан) | F55: 95.7406 | G55: 95.7406 | H55: 21,05 | I55: 180 (0) | J55: %
A56: 52 | B56: 52MFMOb23 | C56: KZ2P00013154 | D56: долговые ЦБ | E56: МФО "Mogo Kazakhstan (Мого Казахстан) | F56: 99.7876 | G56: 100.0932 | H56: 22,15 | I56: 625 (2) | J56: %
A57: 53 | B57: 53MFMOb25 | C57: KZ2P00013220 | D57: долговые ЦБ | E57: МФО "Mogo Kazakhstan (Мого Казахстан) | F57: 99.999 | G57: 100.6101 | H57: 22,00 | I57: 710 (2) | J57: %
A58: 54 | B58: 54MFMOb26 | C58: KZ2P00013204 | D58: долговые ЦБ | E58: МФО "Mogo Kazakhstan (Мого Казахстан) | F58: 100.47 | G58: 100.6367 | H58: 11,70 | I58: 625 (2) | J58: %
A59: 55 | B59: 55MFMOb27 | C59: KZ2P00013345 | D59: долговые ЦБ | E59: МФО "Mogo Kazakhstan (Мого Казахстан) | F59: 99.9989 | G59: 100.5989 | H59: 12,00 | I59: 672 (2) | J59: %
A60: 56 | B60: 56MFMOb28 | C60: KZ2P00013352 | D60: долговые ЦБ | E60: МФО "Mogo Kazakhstan (Мого Казахстан) | F60: 99.9891 | G60: 100.0224 | H60: 12,01 | I60: 659 (2) | J60: %
A61: 57 | B61: 57MFOKb16 | C61: KZ2C00010171 | D61: долговые ЦБ | E61: МФО ОнлайнКазФинанс | F61: 100.4333 | G61: 100.8862 | H61: 21,33 | I61: 83 (0) | J61: %
A62: 58 | B62: 58MFOKb18 | C62: KZ2C00010478 | D62: долговые ЦБ | E62: МФО ОнлайнКазФинанс | F62: 99.0623 | G62: 100.4512 | H62: 21,49 | I62: 245 (1) | J62: %
... A179: 175 | B179: 175SKKZe1 | C179: XS2399149694 | D179: долговые ЦБ | E179: Фонд национального благосостояния "Самрук-Қазына | F179: 96.3032 | G179: 96.931 | H179: 5,25 | I179: 427 (1) | J179: %

Sheet Риск цены за 21.08.25
A1: Дата оценки | C1: 45890
A3: № п/п | B3: Торговый код | C3: ISIN | D3: Алгоритмы и параметры расчета ЦБ | E3: Краткое наименование эмитента | F3: Расчетная цена | G3: Расчетная грязная | H3: Доходность до погашения. % годовых | I3: Дней до погашения | J3: Единица измерения цены
A4: 1 | B4: AAFD | C4: KZ1C00008721 | D4: Акции | E4: АО "АзияАгроФуд" | F4: 100 | G4: 100 | H4: 0 | I4: 0 | J4: KZT
A5: 2 | B5: AAL_KZ | C5: US02376R1023 | D5: Акции | E5: American Airlines | F5: 6957.42 | G5: 6957.42 | H5: 0 | I5: 0 | J5: KZT
A6: 3 | B6: AAPL_KZ | C6: US0378331005 | D6: Акции | E6: Apple Inc. | F6: 122613.76 | G6: 122613.76 | H6: 0 | I6: 0 | J6: KZT
A7: 4 | B7: ABK022_210 | C7: KZMJ00002103 | D7: Облигации | E7: Акимат Актюбинской области | F7: 100 | G7: 101.1451 | H7: 4.23 | I7: 383 | J7: %
A8: 5 | B8: ABK024_183 | C8: KZMJ00001832 | D8: Облигации | E8: Акимат Актюбинской области | F8: 100 | G8: 100.0807 | H8: 0.35 | I8: 277 | J8: %
A9: 6 | B9: ABK114_193 | C9: KZMJ00001931 | D9: Облигации | E9: Акимат Актюбинской области | F9: 100 | G9: 100.0181 | H9: 0.02 | I9: 3099 | J9: %
A10: 7 | B10: ABK119_006 | C10: KZMF00000069 | D10: Облигации | E10: Акимат Актюбинской области | F10: 100 | G10: 100.9489 | H10: 6.08 | I10: 1714 | J10: %
A11: 8 | B11: ABK119_081 | C11: KZMF00000812 | D11: Облигации | E11: Акимат Актюбинской области | F11: 100 | G11: 105.7983 | H11: 7.08 | I11: 2196 | J11: %
A12: 9 | B12: ABK131_021 | C12: KZMF00000218 | D12: Облигации | E12: Акимат Актюбинской области | F12: 100 | G12: 100.1186 | H12: 6.09 | I12: 2123 | J12: %
A13: 10 | B13: ABK143_032 | C13: KZMF00000325 | D13: Облигации | E13: Акимат Актюбинской области | F13: 100 | G13: 105.0664 | H13: 6.08 | I13: 2551 | J13: %
A14: 11 | B14: ABK143_033 | C14: KZMF00000333 | D14: Облигации | E14: Акимат Актюбинской области | F14: 100 | G14: 105.0664 | H14: 6.08 | I14: 2551 | J14: %
A15: 12 | B15: ABT_KZ | C15: US0028241000 | D15: Акции | E15: Abbott Lab. | F15: 71598.96 | G15: 71598.96 | H15: 0 | I15: 0 | J15: KZT
... A1009: 1006 | B1009: ZKK143_044 | C1009: KZMF00000440 | D1009: Облигации | E1009: Акимат Западно-Казахстанской области | F1009: 100 | G1009: 105.0664 | H1009: 6.08 | I1009: 2551 | J1009: %
